Workbook

Sheet Kraken
A1: ü c | B1: Date sent to acctnt | C1: Entry Date | D1: XRP address | E1: Desti- nation tag | F1: Tran- action ID | G1: Description | H1: Type | I1: Amount | J1: Fee | K1: Balance | L1: Asset | M1: Amount | N1: Fee | O1: Balance | P1: Asset | Q1: Aleksey Trofimov GBP | S1: Evgeniy Ulyukin GBP | U1: Category | V1: # | W1: Payslip date | X1: Comment
A2: ü | C2: 44824 | G2: Transfer from Santander Business | H2: DEPOSIT | I2: 100.05 | K2: =+I2-J2 -> 100.05 | L2: GBP | O2: =+M2-N2 -> 0 | X2: Deposit via payment processor Payward Ltd
A3: ü | C3: 44824 | G3: Transfer from Santander Business | H3: DEPOSIT | I3: 3300 | K3: =+K2+I3-J3 -> 3400.05 | L3: GBP | O3: =+O2+M3-N3 -> 0 | X3: Deposit via payment processor Payward Ltd
A4: ü | C4: 44825 | G4: Convert GBP to XRP | H4: TRADE | I4: -34.797 | J4: 0.0905 | K4: =+K3+I4-J4 -> 3365.1625 | L4: GBP | M4: 100 | N4: 0 | O4: =+O3+M4-N4 -> 100 | P4: XRP | R4: x | V4: 5 | W4: 43707
A5: ü | C5: 44825 | D5: rEb8TK3gBgk5auZkwc6sHnwrGVJH8DuaLh | E5: 547786843 | F5: https://xrpscan.com/tx/9FBD5122F4A1ABF20B0705C3447962E6F13C24D7B045494CD8DB71FA7DAD2B21 | G5: Aleksey Trofimov | H5: WITHDRAW | K5: =+K4+I5-J5 -> 3365.1625 | M5: -99.98 | N5: 0.02 | O5: =+O4+M5-N5 -> -3.9794557e-15 | P5: XRP | R5: x | V5: 5 | W5: 43707
A6: ü | C6: 44825 | G6: Convert GBP to XRP | H6: TRADE | I6: -1716.3447 | J6: 4.4625 | K6: =+K5+I6-J6 -> 1644.3553 | L6: GBP | M6: 4900 | N6: 0 | O6: =+O5+M6-N6 -> 4900 | P6: XRP | R6: x
A7: ü | C7: 44825 | D7: rEb8TK3gBgk5auZkwc6sHnwrGVJH8DuaLh | E7: 547786843 | F7: https://xrpscan.com/tx/9ED991B6FD966C3739300B4009C5CBCC786DF95B3E65C161ED78ABECD8BE2317 | G7: Aleksey Trofimov | H7: WITHDRAW | K7: =+K6+I7-J7 -> 1644.3553 | M7: -4899.98 | N7: 0.02 | O7: =+O6+M7-N7 -> 4.3655704e-13 | P7: XRP | R7: x
A8: ü | C8: 44825 | G8: Convert GBP to XRP | H8: TRADE | I8: -1585.7104 | J8: 4.1228 | K8: =+K7+I8-J8 -> 54.5221 | L8: GBP | M8: 4500 | N8: 0 | O8: =+O7+M8-N8 -> 4500 | P8: XRP | R8: x
A9: ü | B9: 44844 | C9: 44825 | D9: rEb8TK3gBgk5auZkwc6sHnwrGVJH8DuaLh | E9: 547786843 | F9: https://xrpscan.com/tx/5A244C410691D52736EE42C6C070B03D25604A34EC222046B9D30E308913F5D7 | G9: Aleksey Trofimov | H9: WITHDRAW | K9: =+K8+I9-J9 -> 54.5221 | M9: -4499.98 | N9: 0.02 | O9: =+O8+M9-N9 -> 4.3655704e-13 | P9: XRP | Q9: =-(I4+I6+I8) -> 3336.8521 | R9: x | U9: Consulting fee - Aleksey Trofimov
A10: ü | C10: 44833 | G10: Transfer from Santander Business | H10: DEPOSIT | I10: 100 | K10: =+K9+I10-J10 -> 154.5221 | L10: GBP | O10: =+O9+M10-N10 -> 4.3655704e-13 | X10: Deposit via payment processor Payward Ltd
A11: ü | C11: 44833 | G11: Convert GBP to XRP | H11: TRADE | I11: -152.3258 | J11: 0.3961 | K11: =+K10+I11-J11 -> 1.8002 | L11: GBP | M11: 375 | N11: 0 | O11: =+O10+M11-N11 -> 375 | P11: XRP | T11: x
A12: ü | B12: 44844 | C12: 44833 | D12: rEb8TK3gBgk5auZkwc6sHnwrGVJH8DuaLh | E12: 442734179 | F12: https://xrpscan.com/tx/437FA042365ECE9CD8DD068C413D4FBFCB4B91DA8B64A0010B9FB501FD655CBC | G12: Evgeniy Ulyukin | H12: WITHDRAW | K12: =+K11+I12-J12 -> 1.8002 | M12: -374.98 | N12: 0.02 | O12: =+O11+M12-N12 -> 4.3655704e-13 | P12: XRP | R12: x | S12: =-I11 -> 152.3258 | T12: x | U12: Consulting fee - Evgeniy Ulyukin
A13: ü | C13: 44841 | G13: Transfer from Santander Business | H13: DEPOSIT | I13: 3300 | K13: =+K12+I13-J13 -> 3301.8002 | L13: GBP | O13: =+O12+M13-N13 -> 4.3655704e-13 | X13: Deposit via payment processor Payward Ltd
A14: ü | C14: 44841 | G14: Convert GBP to XRP | H14: TRADE | I14: -1808.0891 | J14: 4.701 | K14: =+K13+I14-J14 -> 1489.0101 | L14: GBP | M14: 4000.02 | N14: 0 | O14: =+O13+M14-N14 -> 4000.02 | P14: XRP | R14: x
A15: ü | C15: 44841 | G15: Convert GBP to XRP | H15: TRADE | I15: -1486.0731 | J15: 0.351 | K15: =+K14+I15-J15 -> 2.586 | L15: GBP | M15: 3280.02 | N15: 7.7541988 | O15: =+O14+M15-N15 -> 7272.2858 | P15: XRP | R15: x
A16: ü | B16: 44844 | C16: 44841 | D16: rEb8TK3gBgk5auZkwc6sHnwrGVJH8DuaLh | E16: 547786843 | F16: https://xrpscan.com/tx/02EC21E0D411DE5EEE4A006C3CC2D95DE95B19E031D9C05D9AB49513036904F6 | G16: Aleksey Trofimov | H16: WITHDRAW | K16: =+K15+I16-J16 -> 2.586 | M16: -7270.02 | N16: 0.02 | O16: =+O15+M16-N16 -> 2.2458012 | P16: XRP | Q16: =-(I14+I15) -> 3294.1622 | R16: x | U16: Consulting fee - Aleksey Trofimov
A17: ü | C17: 44842 | G17: Transfer from Santander Business | H17: DEPOSIT | I17: 525 | K17: =+K16+I17-J17 -> 527.586 | L17: GBP | O17: =+O16+M17-N17 -> 2.2458012 | X17: Deposit via payment processor Payward Ltd
A18: ü | C18: 44842 | G18: Convert GBP to XRP | H18: TRADE | I18: -520.6519 | J18: 1.3537 | K18: =+K17+I18-J18 -> 5.5804 | L18: GBP | M18: 1110.02 | N18: 0 | O18: =+O17+M18-N18 -> 1112.2658 | P18: XRP | T18: x
A19: ü | B19: 44844 | C19: 44842 | D19: rEb8TK3gBgk5auZkwc6sHnwrGVJH8DuaLh | E19: 442734179 | F19: https://xrpscan.com/tx/F25CE3B619F0778F769EFF5B5752B15F4375A349D504DD38D4313F5D97868E51 | G19: Evgeniy Ulyukin | H19: WITHDRAW | K19: =+K18+I19-J19 -> 5.5804 | M19: -1110 | N19: 0.02 | O19: =+O18+M19-N19 -> 2.2458012 | P19: XRP | R19: x | S19: =-I18 -> 520.6519 | T19: x | U19: Consulting fee - Evgeniy Ulyukin
A20: ü | B20: 44844 | C20: 44842 | G20: Total Kraken fees for the month | J20: =SUM(J4:J19) -> 15.4776 | N20: =SUM(N4:N19) -> 7.8741988 | U20: Bank charges
A21: ü | C21: 44846 | G21: Transfer from Santander Business | H21: DEPOSIT | I21: 2205 | K21: =+K19+I21-J21 -> 2210.5804 | L21: GBP | O21: =+O19+M21-N21 -> 2.2458012 | X21: Deposit via payment processor Payward Ltd
A22: ü | C22: 44846 | G22: Convert GBP to XRP | H22: TRADE | I22: -2206.0574 | J22: 3.8092 | K22: =+K21+I22-J22 -> 0.7138 | L22: GBP | M22: 5000.02 | N22: 4.3675806 | O22: =+O21+M22-N22 -> 4997.8982 | P22: XRP | R22: x
A23: ü | B23: 44844 | C23: 44846 | D23: rEb8TK3gBgk5auZkwc6sHnwrGVJH8DuaLh | E23: 547786843 | F23: https://xrpscan.com/tx/2194D82FB4E82F6B64F0232B2B78FADB9DC1A17FB95CC8F9DC91514C6D99EBF4 | G23: Aleksey Trofimov | H23: WITHDRAW | K23: =+K22+I23-J23 -> 0.7138 | M23: -4995 | N23: 0.02 | O23: =+O22+M23-N23 -> 2.8782206 | P23: XRP | Q23: =-(I22) -> 2206.0574 | R23: x | U23: Consulting fee - Aleksey Trofimov
A24: ü | C24: 44855 | G24: Transfer from Santander Business | H24: DEPOSIT | I24: 100 | K24: =+K23+I24-J24 -> 100.7138 | L24: GBP | O24: =+O23+M24-N24 -> 2.8782206 | X24: Deposit via payment processor Payward Ltd
A25: ü | C25: 44855 | G25: Convert GBP to XRP | H25: TRADE | I25: -99.981 | J25: 0.26 | K25: =+K24+I25-J25 -> 0.4728 | L25: GBP | M25: 252 | N25: 0 | O25: =+O24+M25-N25 -> 254.87822 | P25: XRP | T25: x
A26: ü | B26: 44844 | C26: 44855 | D26: rEb8TK3gBgk5auZkwc6sHnwrGVJH8DuaLh | E26: 442734179 | F26: https://xrpscan.com/tx/3123170F050322C06D94A1C32D2CD56DFDAD23EC6450162C70CDEA1B55B3694E | G26: Evgeniy Ulyukin | H26: WITHDRAW | K26: =+K25+I26-J26 -> 0.4728 | M26: -250 | N26: 0.02 | O26: =+O25+M26-N26 -> 4.8582206 | P26: XRP | R26: x | S26: =-I25 -> 99.981 | T26: x | U26: Consulting fee - Evgeniy Ulyukin
A27: ü | C27: 44872 | G27: Transfer from Santander Business | H27: DEPOSIT | I27: 5000 | K27: =+K26+I27-J27 -> 5000.4728 | L27: GBP | O27: =+O26+M27-N27 -> 4.8582206 | X27: Deposit via payment processor Payward Ltd
A28: ü | C28: 44872 | G28: Convert GBP to XRP | H28: TRADE | I28: -5000.4728 | J28: 0 | K28: =+K27+I28-J28 -> 9.094947e-13 | L28: GBP | M28: 12112.744 | N28: 31.493136 | O28: =+O27+M28-N28 -> 12086.109 | P28: XRP | R28: x
A29: ü | B29: 44888 | C29: 44872 | D29: rEb8TK3gBgk5auZkwc6sHnwrGVJH8DuaLh | E29: 547786843 | F29: https://xrpscan.com/tx/5AB9C1C3052B58C5870398B4A7EB68738C3EBBED79AE1A75722E9BE4A235D8A2 | G29: Aleksey Trofimov | H29: WITHDRAW | K29: =+K28+I29-J29 -> 9.094947e-13 | M29: -12050 | N29: 0.02 | O29: =+O28+M29-N29 -> 36.089443 | P29: XRP | Q29: =-(I28) -> 5000.4728 | R29: x | U29: Consulting fee - Aleksey Trofimov
A30: ü | C30: 44872 | G30: Transfer from Santander Business | H30: DEPOSIT | I30: 500 | K30: =+K29+I30-J30 -> 500 | L30: GBP | O30: =+O29+M30-N30 -> 36.089443 | X30: Deposit via payment processor Payward Ltd
A31: ü | C31: 44872 | G31: Convert GBP to XRP | H31: TRADE | I31: -498.4837 | J31: 1.2961 | K31: =+K30+I31-J31 -> 0.2202 | L31: GBP | M31: 1210 | N31: 0 | O31: =+O30+M31-N31 -> 1246.0894 | P31: XRP | R31: x
A32: ü | B32: 44888 | C32: 44872 | D32: rEb8TK3gBgk5auZkwc6sHnwrGVJH8DuaLh | E32: 442734179 | F32: https://xrpscan.com/tx/B5E50E80B9A6016B1B2BF2150C79149F511227851CDB9E974A8F6030CDBC0A74 | G32: Evgeniy Ulyukin | H32: WITHDRAW | K32: =+K31+I32-J32 -> 0.2202 | M32: -1245 | N32: 0.02 | O32: =+O31+M32-N32 -> 1.0694428 | P32: XRP | R32: x | S32: =-(I31) -> 498.4837 | U32: Consulting fee - Evgeniy Ulyukin
A33: ü | B33: 44888 | C33: 44888 | G33: Total Kraken fees for the month | J33: =SUM(J22:J32) -> 5.3653 | L33: GBP | N33: =SUM(N22:N32) -> 35.940716 | P33: XRP | U33: Bank charges
A34: ü | B34: 45012 | C34: 44901 | G34: Transfer from Santander Business | H34: DEPOSIT | I34: 4765 | K34: =+K32+I34-J34 -> 4765.2202 | L34: GBP | O34: =+O33+M34-N34 -> 0 | X34: Deposit via payment processor Payward Ltd
A35: ü | B35: 45012 | C35: 44901 | G35: Convert GBP to XRP | H35: TRADE | I35: -4750.2938 | J35: 0 | K35: =+K34+I35-J35 -> 14.9264 | L35: GBP | M35: 15065 | N35: 0 | O35: =+O32+M35-N35 -> 15066.069 | P35: XRP | R35: x
A36: ü | B36: 45012 | C36: 44901 | D36: rEb8TK3gBgk5auZkwc6sHnwrGVJH8DuaLh | E36: 442734179 | F36: TBA | G36: Evgeniy Ulyukin | H36: WITHDRAW | K36: =+K35+I36-J36 -> 14.9264 | M36: -2060 | N36: 0.02 | O36: =+O35+M36-N36 -> 13006.049 | P36: XRP | R36: x | S36: =-M36/(M36+M37)*I35 -> 649.77458 | U36: Consulting fee - Evgeniy Ulyukin
A37: ü | B37: 45012 | C37: 44901 | D37: rEb8TK3gBgk5auZkwc6sHnwrGVJH8DuaLh | E37: 547786843 | F37: TBA | G37: Aleksey Trofimov | H37: WITHDRAW | K37: =+K36+I37-J37 -> 14.9264 | M37: -13000 | N37: 0.02 | O37: =+O36+M37-N37 -> 6.0294428 | P37: XRP | Q37: =-M37/(M36+M37)*I35 -> 4100.5192 | R37: x | U37: Consulting fee - Aleksey Trofimov
A38: ü | B38: 45012 | C38: 44916 | G38: Transfer from Santander Business | H38: DEPOSIT | I38: 350 | K38: =+K37+I38-J38 -> 364.9264 | L38: GBP | O38: =+O37+M38-N38 -> 6.0294428 | X38: Deposit via payment processor Payward Ltd
A39: ü | B39: 45012 | C39: 44916 | G39: Convert GBP to XRP | H39: TRADE | I39: -361.1116 | J39: 0 | K39: =+K38+I39-J39 -> 3.8148 | L39: GBP | M39: 1275 | N39: 0 | O39: =+O38+M39-N39 -> 1281.0294 | P39: XRP | R39: x
A40: ü | B40: 45012 | C40: 44916 | D40: rEb8TK3gBgk5auZkwc6sHnwrGVJH8DuaLh | E40: 547786843 | F40: TBA | G40: Aleksey Trofimov | H40: WITHDRAW | K40: =+K39+I40-J40 -> 3.8148 | M40: -1280 | N40: 0.02 | O40: =+O39+M40-N40 -> 1.0094428 | P40: XRP | Q40: =-(I39) -> 361.1116 | R40: x | U40: Consulting fee - Aleksey Trofimov
A41: ü | B41: 45012 | C41: 44931 | G41: Transfer from Santander Business | H41: DEPOSIT | I41: 1500 | K41: =+K40+I41-J41 -> 1503.8148 | L41: GBP | O41: =+O40+M41-N41 -> 1.0094428 | X41: Deposit via payment processor Payward Ltd
A42: ü | B42: 45012 | C42: 44931 | G42: Convert GBP to XRP | H42: TRADE | I42: -1499.9997 | J42: 0 | K42: =+K41+I42-J42 -> 3.8151 | L42: GBP | M42: 5270 | N42: 0 | O42: =+O41+M42-N42 -> 5271.0094 | P42: XRP | R42: x
A43: ü | B43: 45012 | C43: 44931 | D43: rEb8TK3gBgk5auZkwc6sHnwrGVJH8DuaLh | E43: 547786843 | F43: https://xrpscan.com/tx/E42794DDF0B8CE3960322E6700460B93FB22424BC9A17811F101C4EB0C3C81E3 | G43: Aleksey Trofimov | H43: WITHDRAW | K43: =+K42+I43-J43 -> 3.8151 | M43: -4130 | N43: 0.02 | O43: =+O42+M43-N43 -> 1140.9894 | P43: XRP | Q43: =-M43/(M43+M44)*I42 -> 1175.5216 | R43: x | U43: Consulting fee - Aleksey Trofimov
A44: ü | B44: 45012 | C44: 44931 | D44: rEb8TK3gBgk5auZkwc6sHnwrGVJH8DuaLh | E44: 442734179 | F44: https://xrpscan.com/tx/A94E9955466AD7ED93A9BCE196649FFB49B875F711A481181854B8D0642934DC | G44: Evgeniy Ulyukin | H44: WITHDRAW | K44: =+K43+I44-J44 -> 3.8151 | M44: -1140 | N44: 0.02 | O44: =+O43+M44-N44 -> 0.96944284 | P44: XRP | R44: x | S44: =-M44/(M43+M44)*I42 -> 324.47811 | U44: Consulting fee - Evgeniy Ulyukin
A45: ü | B45: 45012 | C45: 44940 | G45: Transfer from Santander Business | H45: DEPOSIT | I45: 300 | K45: =+K44+I45-J45 -> 303.8151 | L45: GBP | O45: =+O44+M45-N45 -> 0.96944284 | X45: Deposit via payment processor Payward Ltd
A46: ü | B46: 45012 | C46: 44940 | G46: Convert GBP to XRP | H46: TRADE | I46: -302.1054 | J46: 0 | K46: =+K45+I46-J46 -> 1.7097 | L46: GBP | M46: 950 | N46: 0 | O46: =+O45+M46-N46 -> 950.96944 | P46: XRP | R46: x
A47: ü | B47: 45012 | C47: 44940 | D47: rEb8TK3gBgk5auZkwc6sHnwrGVJH8DuaLh | E47: 442734179 | F47: https://xrpscan.com/tx/D5C73A3C04E7375AF18E917CC31A2068F1D4B2EE1778A250288923087EA48250 | G47: Evgeniy Ulyukin | H47: WITHDRAW | K47: =+K46+I47-J47 -> 1.7097 | M47: -950 | N47: 0.02 | O47: =+O46+M47-N47 -> 0.94944284 | P47: XRP | R47: x | S47: =-(I46) -> 302.1054 | U47: Consulting fee - Evgeniy Ulyukin
A48: ü | B48: 45012 | C48: 44945 | G48: Transfer from Santander Business | H48: DEPOSIT | I48: 850 | K48: =+K47+I48-J48 -> 851.7097 | L48: GBP | O48: =+O47+M48-N48 -> 0.94944284 | X48: Deposit via payment processor Payward Ltd
A49: ü | B49: 45012 | C49: 44945 | G49: Convert GBP to XRP | H49: TRADE | I49: -850.2842 | J49: 0 | K49: =+K48+I49-J49 -> 1.4255 | L49: GBP | M49: 2700 | N49: 0 | O49: =+O48+M49-N49 -> 2700.9494 | P49: XRP | R49: x
A50: ü | B50: 45012 | C50: 44945 | D50: rEb8TK3gBgk5auZkwc6sHnwrGVJH8DuaLh | E50: 547786843 | F50: https://xrpscan.com/tx/A31CC19EC91A33B093D5E9398A42C4E12FFBC8FFDBF8F30A2F96AE6C9E5AE890 | G50: Aleksey Trofimov | H50: WITHDRAW | K50: =+K49+I50-J50 -> 1.4255 | M50: -2700 | N50: 0.02 | O50: =+O49+M50-N50 -> 0.92944284 | P50: XRP | Q50: =-(I49) -> 850.2842 | R50: x | U50: Consulting fee - Aleksey Trofimov
A51: ü | B51: 45012 | C51: 44954 | G51: Transfer from Santander Business | H51: DEPOSIT | I51: 175 | K51: =+K50+I51-J51 -> 176.4255 | L51: GBP | O51: =+O50+M51-N51 -> 0.92944284 | X51: Deposit via payment processor Payward Ltd
A52: ü | B52: 45012 | C52: 44954 | G52: Convert GBP to XRP | H52: TRADE | I52: -175.3876 | J52: 0 | K52: =+K51+I52-J52 -> 1.0379 | L52: GBP | M52: 530 | N52: 0 | O52: =+O51+M52-N52 -> 530.92944 | P52: XRP | R52: x
A53: ü | B53: 45012 | C53: 44954 | D53: rEb8TK3gBgk5auZkwc6sHnwrGVJH8DuaLh | E53: 442734179 | F53: https://xrpscan.com/tx/0921F43F19B9E22CE791D4A5971638A4519E98A73E93C78FBB09A08C03356562 | G53: Evgeniy Ulyukin | H53: WITHDRAW | K53: =+K52+I53-J53 -> 1.0379 | M53: -530 | N53: 0.02 | O53: =+O52+M53-N53 -> 0.90944284 | P53: XRP | R53: x | S53: =-(I52) -> 175.3876 | U53: Consulting fee - Evgeniy Ulyukin
A54: ü | B54: 45012 | C54: 44971 | G54: Transfer from Santander Business | H54: DEPOSIT | I54: 675 | K54: =+K53+I54-J54 -> 676.0379 | L54: GBP | O54: =+O53+M54-N54 -> 0.90944284 | X54: Deposit via payment processor Payward Ltd
A55: ü | B55: 45012 | C55: 44971 | G55: Convert GBP to XRP | H55: TRADE | I55: -675.476 | J55: 0 | K55: =+K54+I55-J55 -> 0.5619 | L55: GBP | M55: 2195 | N55: 0 | O55: =+O54+M55-N55 -> 2195.9094 | P55: XRP | R55: x
A56: ü | B56: 45012 | C56: 44971 | D56: rEb8TK3gBgk5auZkwc6sHnwrGVJH8DuaLh | E56: 547786843 | F56: https://xrpscan.com/tx/79A623618F79701B689496F06F28E3604FBB1EF2EAC8222D0DBAB4FCDEA11A73 | G56: Aleksey Trofimov | H56: WITHDRAW | K56: =+K55+I56-J56 -> 0.5619 | M56: -2195 | N56: 0.02 | O56: =+O55+M56-N56 -> 0.88944284 | P56: XRP | Q56: =-(I55) -> 675.476 | R56: x | U56: Consulting fee - Aleksey Trofimov
A57: ü | B57: 45012 | C57: 44986 | G57: Transfer from Santander Business | H57: DEPOSIT | I57: 450 | J57: 0 | K57: =+K56+I57-J57 -> 450.5619 | L57: GBP | O57: =+O56+M57-N57 -> 0.88944284 | X57: Deposit via payment processor Payward Ltd
A58: ü | B58: 45012 | C58: 44986 | G58: Convert GBP to XRP | H58: TRADE | I58: -235.4498 | K58: =+K57+I58-J58 -> 215.1121 | L58: GBP | M58: 745 | N58: 0 | O58: =+O57+M58-N58 -> 745.88944 | P58: XRP | R58: x
A59: ü | B59: 45012 | C59: 44986 | G59: Convert GBP to XRP | H59: TRADE | I59: -215.0432 | K59: =+K58+I59-J59 -> 0.0689 | L59: GBP | M59: 680 | N59: 0 | O59: =+O58+M59-N59 -> 1425.8894 | P59: XRP | R59: x
A60: ü | B60: 45012 | C60: 44986 | D60: rEb8TK3gBgk5auZkwc6sHnwrGVJH8DuaLh | E60: 547786843 | F60: https://xrpscan.com/tx/D9B6075638926640A0EA9F1094F6FB2F5C56746A300B25E6389E67700795F9B0 | G60: Aleksey Trofimov | H60: WITHDRAW | K60: =+K59+I60-J60 -> 0.0689 | M60: -745 | N60: 0.02 | O60: =+O59+M60-N60 -> 680.86944 | P60: XRP | Q60: =-I58 -> 235.4498 | R60: x | U60: Consulting fee - Aleksey Trofimov
A61: ü | B61: 45012 | C61: 44986 | D61: rEb8TK3gBgk5auZkwc6sHnwrGVJH8DuaLh | E61: 442734179 | F61: https://xrpscan.com/tx/C6B2E38C8960FF64DDA0B3827D1615E31234460A28055AC361123CE201741299 | G61: Evgeniy Ulyukin | H61: WITHDRAW | J61: 0 | K61: =+K60+I61-J61 -> 0.0689 | M61: -680 | N61: 0.02 | O61: =+O60+M61-N61 -> 0.84944284 | P61: XRP | R61: x | S61: =-I59 -> 215.0432 | U61: Consulting fee - Evgeniy Ulyukin
A62: ü | B62: 45012 | C62: 45007 | G62: Transfer from Santander Business | H62: DEPOSIT | I62: 275 | K62: =+K61+I62-J62 -> 275.0689 | L62: GBP | O62: =+O61+M62-N62 -> 0.84944284 | X62: Deposit via payment processor Payward Ltd
A63: ü | B63: 45012 | C63: 45007 | G63: Convert GBP to XRP | H63: TRADE | I63: -256.9455 | K63: =+K62+I63-J63 -> 18.1234 | L63: GBP | M63: 700 | N63: 0 | O63: =+O62+M63-N63 -> 700.84944 | P63: XRP | R63: x
A64: ü | B64: 45012 | C64: 45007 | D64: rEb8TK3gBgk5auZkwc6sHnwrGVJH8DuaLh | E64: 442734179 | F64: https://xrpscan.com/tx/655A1BB8EDDDBB5612166F1CBE0839717AE30DF770B6A85C183277DA5C3A8259 | G64: Evgeniy Ulyukin | H64: WITHDRAW | J64: 0 | K64: =+K63+I64-J64 -> 18.1234 | M64: -700 | N64: 0.02 | O64: =+O63+M64-N64 -> 0.82944284 | P64: XRP | R64: x | S64: =-(I63) -> 256.9455 | U64: Consulting fee - Evgeniy Ulyukin
A65: ü | B65: 45012 | C65: 45010 | G65: Transfer from Santander Business | H65: DEPOSIT | I65: 1500 | K65: =+K64+I65-J65 -> 1518.1234 | L65: GBP | O65: =+O64+M65-N65 -> 0.82944284 | X65: Deposit via payment processor Payward Ltd
A66: ü | B66: 45012 | C66: 45010 | G66: Convert GBP to XRP | H66: TRADE | I66: -1327.7607 | K66: =+K65+I66-J66 -> 190.3627 | L66: GBP | M66: 3645 | N66: 0 | O66: =+O65+M66-N66 -> 3645.8294 | P66: XRP | R66: x
A67: ü | B67: 45012 | C67: 45010 | D67: rEb8TK3gBgk5auZkwc6sHnwrGVJH8DuaLh | E67: 547786843 | F67: https://xrpscan.com/tx/01CD79A6370ED295F052D1429E4A90831A48B4F174CBD9A900058F28D27C9CAA | G67: Aleksey Trofimov | H67: WITHDRAW | K67: =+K66+I67-J67 -> 190.3627 | M67: -3645 | N67: 0.02 | O67: =+O66+M67-N67 -> 0.80944284 | P67: XRP | Q67: =-(I66) -> 1327.7607 | R67: x | U67: Consulting fee - Aleksey Trofimov
A68: ü | B68: 45012 | C68: 45012 | G68: Total Kraken fees 6 Dec 22 - 25 Mar 23 | J68: =SUM(J57:J67) -> 0 | L68: GBP | N68: =SUM(N34:N67) -> 0.26 | P68: XRP | U68: Bank charges
A69: ü | B69: 45104 | C69: 45019 | D69: rEb8TK3gBgk5auZkwc6sHnwrGVJH8DuaLh | E69: 518294827 | F69: https://bithomp.com/explorer/89DA6E0506E88DEFB02147D8E2E7C4E531A429CF2C0F17FBF6B4D4A4431648A3 | G69: Alex Smirnov | H69: WITHDRAW | I69: 1536.5424 | L69: GBP | M69: -3700 | P69: XRP | U69: =_xlfn.CONCAT("Consulting fee - ",G69) -> Consulting fee - Alex Smirnov
A70: ü | B70: 45104 | C70: 45028 | D70: rEb8TK3gBgk5auZkwc6sHnwrGVJH8DuaLh | E70: 547786843 | F70: https://bithomp.com/explorer/183EDFFF6925D95DC65C5D0CB5D48F4EEC77B7304AD0D56DBAD0FE6A2082092F | G70: Aleksey Trofimov | H70: WITHDRAW | I70: 800.56051 | L70: GBP | M70: -1975 | P70: XRP | U70: =_xlfn.CONCAT("Consulting fee - ",G70) -> Consulting fee - Aleksey Trofimov
A71: ü | B71: 45104 | C71: 45032 | D71: rEb8TK3gBgk5auZkwc6sHnwrGVJH8DuaLh | E71: 442734179 | F71: https://bithomp.com/explorer/8F2873BFE79F71897C41F309842C424029A574E5868A0731EEB8B760454C43C4 | G71: Evgeniy Ulyukin | H71: WITHDRAW | I71: 98.85745 | L71: GBP | M71: -235 | P71: XRP | U71: =_xlfn.CONCAT("Consulting fee - ",G71) -> Consulting fee - Evgeniy Ulyukin
A72: ü | B72: 45104 | C72: 45037 | D72: rEb8TK3gBgk5auZkwc6sHnwrGVJH8DuaLh | E72: 518294827 | F72: https://bithomp.com/explorer/2B372258F7200F7B81D0C160CDB258C6FC22178C7DB0F9D84AC8334D16853A79 | G72: Alex Smirnov | H72: WITHDRAW | I72: 860.8966 | L72: GBP | M72: -2285 | P72: XRP | U72: =_xlfn.CONCAT("Consulting fee - ",G72) -> Consulting fee - Alex Smirnov
A73: ü | B73: 45104 | C73: 45037 | D73: rEb8TK3gBgk5auZkwc6sHnwrGVJH8DuaLh | E73: 442734179 | F73: https://bithomp.com/explorer/6CF6E9B042139AEAC3F03C58EA3F40D8F934935AD52F22AAC440D121986AC864 | G73: Evgeniy Ulyukin | H73: WITHDRAW | I73: 250.30962 | L73: GBP | M73: -665 | P73: XRP | U73: =_xlfn.CONCAT("Consulting fee - ",G73) -> Consulting fee - Evgeniy Ulyukin
A74: ü | B74: 45104 | C74: 45038 | D74: rEb8TK3gBgk5auZkwc6sHnwrGVJH8DuaLh | E74: 547786843 | F74: https://bithomp.com/explorer/704889305D36DF433262F28E79CE91937CA569E011503C87AB0FC82BCCC2F4CA | G74: Aleksey Trofimov | H74: WITHDRAW | I74: 2764.0468 | L74: GBP | M74: -7600 | P74: XRP | U74: =_xlfn.CONCAT("Consulting fee - ",G74) -> Consulting fee - Aleksey Trofimov
A75: ü | B75: 45104 | C75: 45047 | D75: rEb8TK3gBgk5auZkwc6sHnwrGVJH8DuaLh | E75: 518294827 | F75: https://bithomp.com/explorer/A018CECE9725A49000646A608054148E517225135ACADBF13EF12CAC13D190CB | G75: Alex Smirnov | H75: WITHDRAW | I75: 1707.2419 | L75: GBP | M75: -4630 | P75: XRP | U75: =_xlfn.CONCAT("Consulting fee - ",G75) -> Consulting fee - Alex Smirnov
A76: ü | B76: 45104 | C76: 45054 | D76: rEb8TK3gBgk5auZkwc6sHnwrGVJH8DuaLh | E76: 442734179 | F76: https://bithomp.com/explorer/1E4EA2BDD8885081435589A48A5EAC3111EB2B240019EA56CF572EC1998460E3 | G76: Evgeniy Ulyukin | H76: WITHDRAW | I76: 1344.8547 | L76: GBP | M76: -3900 | P76: XRP | U76: =_xlfn.CONCAT("Consulting fee - ",G76) -> Consulting fee - Evgeniy Ulyukin
A77: ü | B77: 45104 | C77: 45060 | D77: rEb8TK3gBgk5auZkwc6sHnwrGVJH8DuaLh | E77: 518294827 | F77: https://bithomp.com/explorer/59A4310F3F8B04267CB5F758B44C5125FD0A7BA4AC62AB2F867E8E42BFE26658 | G77: Alex Smirnov | H77: WITHDRAW | I77: 384.45508 | L77: GBP | M77: -1119.82 | P77: XRP | U77: =_xlfn.CONCAT("Consulting fee - ",G77) -> Consulting fee - Alex Smirnov
A78: ü | B78: 45104 | C78: 45068 | D78: rEb8TK3gBgk5auZkwc6sHnwrGVJH8DuaLh | E78: 518294827 | F78: https://bithomp.com/explorer/B3B9FB2CF3EA0679A0783E8292DFEA8278B62B746CADD2C957A2A2EB8DB715B2 | G78: Alex Smirnov | H78: WITHDRAW | I78: 738.93379 | L78: GBP | M78: -2000 | P78: XRP | U78: =_xlfn.CONCAT("Consulting fee - ",G78) -> Consulting fee - Alex Smirnov
A79: ü | B79: 45104 | C79: 45068 | D79: rEb8TK3gBgk5auZkwc6sHnwrGVJH8DuaLh | E79: 547786843 | F79: https://bithomp.com/explorer/864A7C15A8B6E91BF8A0F4E3140938FA2483A3B55B05B689DAB360360E4CF013 | G79: Aleksey Trofimov | H79: WITHDRAW | I79: 2122.9857 | L79: GBP | M79: -5780 | P79: XRP | U79: =_xlfn.CONCAT("Consulting fee - ",G79) -> Consulting fee - Aleksey Trofimov
A80: ü | B80: 45104 | C80: 45070 | D80: rEb8TK3gBgk5auZkwc6sHnwrGVJH8DuaLh | E80: 442734179 | F80: https://bithomp.com/explorer/142156A29078CDA90AE38A2213CC8F3618C12E86F969E01EC8B9A0C5BF66C67F | G80: Evgeniy Ulyukin | H80: WITHDRAW | I80: 500.03961 | L80: GBP | M80: -1365 | P80: XRP | U80: =_xlfn.CONCAT("Consulting fee - ",G80) -> Consulting fee - Evgeniy Ulyukin
... A87: ü | B87: 45104 | C87: 45099 | D87: rEb8TK3gBgk5auZkwc6sHnwrGVJH8DuaLh | E87: 442734179 | F87: https://bithomp.com/explorer/EEF584E49FF4E944C471935F760DC932DD866073792F0DAF467D951D0E67B59F | G87: Evgeniy Ulyukin | H87: WITHDRAW | I87: 310.58033 | L87: GBP | M87: -800 | P87: XRP | U87: =_xlfn.CONCAT("Consulting fee - ",G87) -> Consulting fee - Evgeniy Ulyukin

Sheet Kraken Ledger
P1: LOOKUP "Kraken Trades"
A2: SENT | B2: DONE | C2: TX ID | D2: DEST TAG | E2: WHO | F2: txid (filter out BLANK) | G2: refid (LOOKUP) | H2: time | I2: type | J2: subtype | K2: aclass | L2: asset | M2: amount | N2: fee | O2: balance | P2: txid | Q2: ordertxid | R2: pair | S2: time | T2: type | U2: ordertype | V2: price | W2: cost | X2: fee | Y2: vol | Z2: margin | AA2: misc | AB2: ledgers
B3: yes | E3: =_xlfn.XLOOKUP(D3,'DEST TAGs'!$A$2:$A$5,'DEST TAGs'!$B$2:$B$5,"--",0) -> -- | G3: QYP53GS-N2K7N6-UNC5Y7 | H3: 44931.559 | I3: deposit | K3: currency | L3: ZGBP | M3: 1500 | N3: 0 | P3: =_xlfn.XLOOKUP(G3,'Kraken Trades'!$A$2:$A$28,'Kraken Trades'!$A$2:$A$28,"--",0) -> -- | Q3: =_xlfn.XLOOKUP(G3,'Kraken Trades'!$A$2:$A$28,'Kraken Trades'!$B$2:$B$28,"--",0) -> -- | R3: =_xlfn.XLOOKUP(G3,'Kraken Trades'!$A$2:$A$28,'Kraken Trades'!$C$2:$C$28,"--",0) -> -- | S3: =_xlfn.XLOOKUP(G3,'Kraken Trades'!$A$2:$A$28,'Kraken Trades'!$D$2:$D$28,"--",0) -> -- | T3: =_xlfn.XLOOKUP(G3,'Kraken Trades'!$A$2:$A$28,'Kraken Trades'!$E$2:$E$28,"--",0) -> -- | U3: =_xlfn.XLOOKUP(G3,'Kraken Trades'!$A$2:$A$28,'Kraken Trades'!$F$2:$F$28,"--",0) -> -- | V3: =_xlfn.XLOOKUP(G3,'Kraken Trades'!$A$2:$A$28,'Kraken Trades'!$G$2:$G$28,"--",0) -> -- | W3: =_xlfn.XLOOKUP(G3,'Kraken Trades'!$A$2:$A$28,'Kraken Trades'!$H$2:$H$28,"--",0) -> -- | X3: =_xlfn.XLOOKUP(G3,'Kraken Trades'!$A$2:$A$28,'Kraken Trades'!$I$2:$I$28,"--",0) -> -- | Y3: =_xlfn.XLOOKUP(G3,'Kraken Trades'!$A$2:$A$28,'Kraken Trades'!$J$2:$J$28,"--",0) -> -- | Z3: =_xlfn.XLOOKUP(G3,'Kraken Trades'!$A$2:$A$28,'Kraken Trades'!$K$2:$K$28,"--",0) -> -- | AA3: =_xlfn.XLOOKUP(G3,'Kraken Trades'!$A$2:$A$28,'Kraken Trades'!$L$2:$L$28,"--",0) -> -- | AB3: =_xlfn.XLOOKUP(G3,'Kraken Trades'!$A$2:$A$28,'Kraken Trades'!$M$2:$M$28,"--",0) -> --
B4: yes | E4: =_xlfn.XLOOKUP(D4,'DEST TAGs'!$A$2:$A$5,'DEST TAGs'!$B$2:$B$5,"--",0) -> -- | F4: LBAYNS-MDQPF-FVYDWI | G4: QYP53GS-N2K7N6-UNC5Y7 | H4: 44931.567 | I4: deposit | K4: currency | L4: ZGBP | M4: 1500 | N4: 0 | O4: 1503.8148 | P4: =_xlfn.XLOOKUP(G4,'Kraken Trades'!$A$2:$A$28,'Kraken Trades'!$A$2:$A$28,"--",0) -> -- | Q4: =_xlfn.XLOOKUP(G4,'Kraken Trades'!$A$2:$A$28,'Kraken Trades'!$B$2:$B$28,"--",0) -> -- | R4: =_xlfn.XLOOKUP(G4,'Kraken Trades'!$A$2:$A$28,'Kraken Trades'!$C$2:$C$28,"--",0) -> -- | S4: =_xlfn.XLOOKUP(G4,'Kraken Trades'!$A$2:$A$28,'Kraken Trades'!$D$2:$D$28,"--",0) -> -- | T4: =_xlfn.XLOOKUP(G4,'Kraken Trades'!$A$2:$A$28,'Kraken Trades'!$E$2:$E$28,"--",0) -> -- | U4: =_xlfn.XLOOKUP(G4,'Kraken Trades'!$A$2:$A$28,'Kraken Trades'!$F$2:$F$28,"--",0) -> -- | V4: =_xlfn.XLOOKUP(G4,'Kraken Trades'!$A$2:$A$28,'Kraken Trades'!$G$2:$G$28,"--",0) -> -- | W4: =_xlfn.XLOOKUP(G4,'Kraken Trades'!$A$2:$A$28,'Kraken Trades'!$H$2:$H$28,"--",0) -> -- | X4: =_xlfn.XLOOKUP(G4,'Kraken Trades'!$A$2:$A$28,'Kraken Trades'!$I$2:$I$28,"--",0) -> -- | Y4: =_xlfn.XLOOKUP(G4,'Kraken Trades'!$A$2:$A$28,'Kraken Trades'!$J$2:$J$28,"--",0) -> -- | Z4: =_xlfn.XLOOKUP(G4,'Kraken Trades'!$A$2:$A$28,'Kraken Trades'!$K$2:$K$28,"--",0) -> -- | AA4: =_xlfn.XLOOKUP(G4,'Kraken Trades'!$A$2:$A$28,'Kraken Trades'!$L$2:$L$28,"--",0) -> -- | AB4: =_xlfn.XLOOKUP(G4,'Kraken Trades'!$A$2:$A$28,'Kraken Trades'!$M$2:$M$28,"--",0) -> --
B5: yes | E5: =_xlfn.XLOOKUP(D5,'DEST TAGs'!$A$2:$A$5,'DEST TAGs'!$B$2:$B$5,"--",0) -> -- | F5: LOC5M4-VGITG-62OW6U | G5: TVJHYS-EB5IK-4X5X33 | H5: 44931.569 | I5: trade | K5: currency | L5: ZGBP | M5: -1499.9997 | N5: 0 | O5: 3.8151 | P5: =_xlfn.XLOOKUP(G5,'Kraken Trades'!$A$2:$A$28,'Kraken Trades'!$A$2:$A$28,"--",0) -> TVJHYS-EB5IK-4X5X33 | Q5: =_xlfn.XLOOKUP(G5,'Kraken Trades'!$A$2:$A$28,'Kraken Trades'!$B$2:$B$28,"--",0) -> OX3DXP-OFPAQ-NWPXZK | R5: =_xlfn.XLOOKUP(G5,'Kraken Trades'!$A$2:$A$28,'Kraken Trades'!$C$2:$C$28,"--",0) -> XRPGBP | S5: =_xlfn.XLOOKUP(G5,'Kraken Trades'!$A$2:$A$28,'Kraken Trades'!$D$2:$D$28,"--",0) -> 0.027545139 | T5: =_xlfn.XLOOKUP(G5,'Kraken Trades'!$A$2:$A$28,'Kraken Trades'!$E$2:$E$28,"--",0) -> buy | U5: =_xlfn.XLOOKUP(G5,'Kraken Trades'!$A$2:$A$28,'Kraken Trades'!$F$2:$F$28,"--",0) -> market | V5: =_xlfn.XLOOKUP(G5,'Kraken Trades'!$A$2:$A$28,'Kraken Trades'!$G$2:$G$28,"--",0) -> 0.28462991 | W5: =_xlfn.XLOOKUP(G5,'Kraken Trades'!$A$2:$A$28,'Kraken Trades'!$H$2:$H$28,"--",0) -> 1499.9996 | X5: =_xlfn.XLOOKUP(G5,'Kraken Trades'!$A$2:$A$28,'Kraken Trades'!$I$2:$I$28,"--",0) -> 3.899999 | Y5: =_xlfn.XLOOKUP(G5,'Kraken Trades'!$A$2:$A$28,'Kraken Trades'!$J$2:$J$28,"--",0) -> 5270 | Z5: =_xlfn.XLOOKUP(G5,'Kraken Trades'!$A$2:$A$28,'Kraken Trades'!$K$2:$K$28,"--",0) -> 0 | AA5: =_xlfn.XLOOKUP(G5,'Kraken Trades'!$A$2:$A$28,'Kraken Trades'!$L$2:$L$28,"--",0) -> initiated | AB5: =_xlfn.XLOOKUP(G5,'Kraken Trades'!$A$2:$A$28,'Kraken Trades'!$M$2:$M$28,"--",0) -> LJHWVK-UM23A-Z4NP7D,LS3HC5-BWXDY-DROKXS,LOC5M4-VGITG-62OW6U
B6: yes | E6: =_xlfn.XLOOKUP(D6,'DEST TAGs'!$A$2:$A$5,'DEST TAGs'!$B$2:$B$5,"--",0) -> -- | F6: LS3HC5-BWXDY-DROKXS | G6: TVJHYS-EB5IK-4X5X33 | H6: 44931.569 | I6: trade | K6: currency | L6: XXRP | M6: 5270 | N6: 0 | O6: 5271.0094 | P6: =_xlfn.XLOOKUP(G6,'Kraken Trades'!$A$2:$A$28,'Kraken Trades'!$A$2:$A$28,"--",0) -> TVJHYS-EB5IK-4X5X33 | Q6: =_xlfn.XLOOKUP(G6,'Kraken Trades'!$A$2:$A$28,'Kraken Trades'!$B$2:$B$28,"--",0) -> OX3DXP-OFPAQ-NWPXZK | R6: =_xlfn.XLOOKUP(G6,'Kraken Trades'!$A$2:$A$28,'Kraken Trades'!$C$2:$C$28,"--",0) -> XRPGBP | S6: =_xlfn.XLOOKUP(G6,'Kraken Trades'!$A$2:$A$28,'Kraken Trades'!$D$2:$D$28,"--",0) -> 0.027545139 | T6: =_xlfn.XLOOKUP(G6,'Kraken Trades'!$A$2:$A$28,'Kraken Trades'!$E$2:$E$28,"--",0) -> buy | U6: =_xlfn.XLOOKUP(G6,'Kraken Trades'!$A$2:$A$28,'Kraken Trades'!$F$2:$F$28,"--",0) -> market | V6: =_xlfn.XLOOKUP(G6,'Kraken Trades'!$A$2:$A$28,'Kraken Trades'!$G$2:$G$28,"--",0) -> 0.28462991 | W6: =_xlfn.XLOOKUP(G6,'Kraken Trades'!$A$2:$A$28,'Kraken Trades'!$H$2:$H$28,"--",0) -> 1499.9996 | X6: =_xlfn.XLOOKUP(G6,'Kraken Trades'!$A$2:$A$28,'Kraken Trades'!$I$2:$I$28,"--",0) -> 3.899999 | Y6: =_xlfn.XLOOKUP(G6,'Kraken Trades'!$A$2:$A$28,'Kraken Trades'!$J$2:$J$28,"--",0) -> 5270 | Z6: =_xlfn.XLOOKUP(G6,'Kraken Trades'!$A$2:$A$28,'Kraken Trades'!$K$2:$K$28,"--",0) -> 0 | AA6: =_xlfn.XLOOKUP(G6,'Kraken Trades'!$A$2:$A$28,'Kraken Trades'!$L$2:$L$28,"--",0) -> initiated | AB6: =_xlfn.XLOOKUP(G6,'Kraken Trades'!$A$2:$A$28,'Kraken Trades'!$M$2:$M$28,"--",0) -> LJHWVK-UM23A-Z4NP7D,LS3HC5-BWXDY-DROKXS,LOC5M4-VGITG-62OW6U
B7: yes | E7: =_xlfn.XLOOKUP(D7,'DEST TAGs'!$A$2:$A$5,'DEST TAGs'!$B$2:$B$5,"--",0) -> -- | F7: LJHWVK-UM23A-Z4NP7D | G7: TVJHYS-EB5IK-4X5X33 | H7: 44931.569 | I7: trade | K7: currency | L7: KFEE | M7: 0 | N7: 466.73 | O7: 7910.27 | P7: =_xlfn.XLOOKUP(G7,'Kraken Trades'!$A$2:$A$28,'Kraken Trades'!$A$2:$A$28,"--",0) -> TVJHYS-EB5IK-4X5X33 | Q7: =_xlfn.XLOOKUP(G7,'Kraken Trades'!$A$2:$A$28,'Kraken Trades'!$B$2:$B$28,"--",0) -> OX3DXP-OFPAQ-NWPXZK | R7: =_xlfn.XLOOKUP(G7,'Kraken Trades'!$A$2:$A$28,'Kraken Trades'!$C$2:$C$28,"--",0) -> XRPGBP | S7: =_xlfn.XLOOKUP(G7,'Kraken Trades'!$A$2:$A$28,'Kraken Trades'!$D$2:$D$28,"--",0) -> 0.027545139 | T7: =_xlfn.XLOOKUP(G7,'Kraken Trades'!$A$2:$A$28,'Kraken Trades'!$E$2:$E$28,"--",0) -> buy | U7: =_xlfn.XLOOKUP(G7,'Kraken Trades'!$A$2:$A$28,'Kraken Trades'!$F$2:$F$28,"--",0) -> market | V7: =_xlfn.XLOOKUP(G7,'Kraken Trades'!$A$2:$A$28,'Kraken Trades'!$G$2:$G$28,"--",0) -> 0.28462991 | W7: =_xlfn.XLOOKUP(G7,'Kraken Trades'!$A$2:$A$28,'Kraken Trades'!$H$2:$H$28,"--",0) -> 1499.9996 | X7: =_xlfn.XLOOKUP(G7,'Kraken Trades'!$A$2:$A$28,'Kraken Trades'!$I$2:$I$28,"--",0) -> 3.899999 | Y7: =_xlfn.XLOOKUP(G7,'Kraken Trades'!$A$2:$A$28,'Kraken Trades'!$J$2:$J$28,"--",0) -> 5270 | Z7: =_xlfn.XLOOKUP(G7,'Kraken Trades'!$A$2:$A$28,'Kraken Trades'!$K$2:$K$28,"--",0) -> 0 | AA7: =_xlfn.XLOOKUP(G7,'Kraken Trades'!$A$2:$A$28,'Kraken Trades'!$L$2:$L$28,"--",0) -> initiated | AB7: =_xlfn.XLOOKUP(G7,'Kraken Trades'!$A$2:$A$28,'Kraken Trades'!$M$2:$M$28,"--",0) -> LJHWVK-UM23A-Z4NP7D,LS3HC5-BWXDY-DROKXS,LOC5M4-VGITG-62OW6U
B8: yes | E8: =_xlfn.XLOOKUP(D8,'DEST TAGs'!$A$2:$A$5,'DEST TAGs'!$B$2:$B$5,"--",0) -> -- | G8: AIBIVII-YHP3YE-IINMMX | H8: 44931.579 | I8: withdrawal | K8: currency | L8: XXRP | M8: -4130 | N8: 0.02 | P8: =_xlfn.XLOOKUP(G8,'Kraken Trades'!$A$2:$A$28,'Kraken Trades'!$A$2:$A$28,"--",0) -> -- | Q8: =_xlfn.XLOOKUP(G8,'Kraken Trades'!$A$2:$A$28,'Kraken Trades'!$B$2:$B$28,"--",0) -> -- | R8: =_xlfn.XLOOKUP(G8,'Kraken Trades'!$A$2:$A$28,'Kraken Trades'!$C$2:$C$28,"--",0) -> -- | S8: =_xlfn.XLOOKUP(G8,'Kraken Trades'!$A$2:$A$28,'Kraken Trades'!$D$2:$D$28,"--",0) -> -- | T8: =_xlfn.XLOOKUP(G8,'Kraken Trades'!$A$2:$A$28,'Kraken Trades'!$E$2:$E$28,"--",0) -> -- | U8: =_xlfn.XLOOKUP(G8,'Kraken Trades'!$A$2:$A$28,'Kraken Trades'!$F$2:$F$28,"--",0) -> -- | V8: =_xlfn.XLOOKUP(G8,'Kraken Trades'!$A$2:$A$28,'Kraken Trades'!$G$2:$G$28,"--",0) -> -- | W8: =_xlfn.XLOOKUP(G8,'Kraken Trades'!$A$2:$A$28,'Kraken Trades'!$H$2:$H$28,"--",0) -> -- | X8: =_xlfn.XLOOKUP(G8,'Kraken Trades'!$A$2:$A$28,'Kraken Trades'!$I$2:$I$28,"--",0) -> -- | Y8: =_xlfn.XLOOKUP(G8,'Kraken Trades'!$A$2:$A$28,'Kraken Trades'!$J$2:$J$28,"--",0) -> -- | Z8: =_xlfn.XLOOKUP(G8,'Kraken Trades'!$A$2:$A$28,'Kraken Trades'!$K$2:$K$28,"--",0) -> -- | AA8: =_xlfn.XLOOKUP(G8,'Kraken Trades'!$A$2:$A$28,'Kraken Trades'!$L$2:$L$28,"--",0) -> -- | AB8: =_xlfn.XLOOKUP(G8,'Kraken Trades'!$A$2:$A$28,'Kraken Trades'!$M$2:$M$28,"--",0) -> --
B9: yes | E9: =_xlfn.XLOOKUP(D9,'DEST TAGs'!$A$2:$A$5,'DEST TAGs'!$B$2:$B$5,"--",0) -> -- | F9: LIOUAB-5S2L2-EITVBQ | G9: AIBIVII-YHP3YE-IINMMX | H9: 44931.58 | I9: withdrawal | K9: currency | L9: XXRP | M9: -4130 | N9: 0.02 | O9: 1140.9894 | P9: =_xlfn.XLOOKUP(G9,'Kraken Trades'!$A$2:$A$28,'Kraken Trades'!$A$2:$A$28,"--",0) -> -- | Q9: =_xlfn.XLOOKUP(G9,'Kraken Trades'!$A$2:$A$28,'Kraken Trades'!$B$2:$B$28,"--",0) -> -- | R9: =_xlfn.XLOOKUP(G9,'Kraken Trades'!$A$2:$A$28,'Kraken Trades'!$C$2:$C$28,"--",0) -> -- | S9: =_xlfn.XLOOKUP(G9,'Kraken Trades'!$A$2:$A$28,'Kraken Trades'!$D$2:$D$28,"--",0) -> -- | T9: =_xlfn.XLOOKUP(G9,'Kraken Trades'!$A$2:$A$28,'Kraken Trades'!$E$2:$E$28,"--",0) -> -- | U9: =_xlfn.XLOOKUP(G9,'Kraken Trades'!$A$2:$A$28,'Kraken Trades'!$F$2:$F$28,"--",0) -> -- | V9: =_xlfn.XLOOKUP(G9,'Kraken Trades'!$A$2:$A$28,'Kraken Trades'!$G$2:$G$28,"--",0) -> -- | W9: =_xlfn.XLOOKUP(G9,'Kraken Trades'!$A$2:$A$28,'Kraken Trades'!$H$2:$H$28,"--",0) -> -- | X9: =_xlfn.XLOOKUP(G9,'Kraken Trades'!$A$2:$A$28,'Kraken Trades'!$I$2:$I$28,"--",0) -> -- | Y9: =_xlfn.XLOOKUP(G9,'Kraken Trades'!$A$2:$A$28,'Kraken Trades'!$J$2:$J$28,"--",0) -> -- | Z9: =_xlfn.XLOOKUP(G9,'Kraken Trades'!$A$2:$A$28,'Kraken Trades'!$K$2:$K$28,"--",0) -> -- | AA9: =_xlfn.XLOOKUP(G9,'Kraken Trades'!$A$2:$A$28,'Kraken Trades'!$L$2:$L$28,"--",0) -> -- | AB9: =_xlfn.XLOOKUP(G9,'Kraken Trades'!$A$2:$A$28,'Kraken Trades'!$M$2:$M$28,"--",0) -> --
B10: yes | E10: =_xlfn.XLOOKUP(D10,'DEST TAGs'!$A$2:$A$5,'DEST TAGs'!$B$2:$B$5,"--",0) -> -- | G10: AIBLWOI-K6V4V3-O252VX | H10: 44931.581 | I10: withdrawal | K10: currency | L10: XXRP | M10: -1140 | N10: 0.02 | P10: =_xlfn.XLOOKUP(G10,'Kraken Trades'!$A$2:$A$28,'Kraken Trades'!$A$2:$A$28,"--",0) -> -- | Q10: =_xlfn.XLOOKUP(G10,'Kraken Trades'!$A$2:$A$28,'Kraken Trades'!$B$2:$B$28,"--",0) -> -- | R10: =_xlfn.XLOOKUP(G10,'Kraken Trades'!$A$2:$A$28,'Kraken Trades'!$C$2:$C$28,"--",0) -> -- | S10: =_xlfn.XLOOKUP(G10,'Kraken Trades'!$A$2:$A$28,'Kraken Trades'!$D$2:$D$28,"--",0) -> -- | T10: =_xlfn.XLOOKUP(G10,'Kraken Trades'!$A$2:$A$28,'Kraken Trades'!$E$2:$E$28,"--",0) -> -- | U10: =_xlfn.XLOOKUP(G10,'Kraken Trades'!$A$2:$A$28,'Kraken Trades'!$F$2:$F$28,"--",0) -> -- | V10: =_xlfn.XLOOKUP(G10,'Kraken Trades'!$A$2:$A$28,'Kraken Trades'!$G$2:$G$28,"--",0) -> -- | W10: =_xlfn.XLOOKUP(G10,'Kraken Trades'!$A$2:$A$28,'Kraken Trades'!$H$2:$H$28,"--",0) -> -- | X10: =_xlfn.XLOOKUP(G10,'Kraken Trades'!$A$2:$A$28,'Kraken Trades'!$I$2:$I$28,"--",0) -> -- | Y10: =_xlfn.XLOOKUP(G10,'Kraken Trades'!$A$2:$A$28,'Kraken Trades'!$J$2:$J$28,"--",0) -> -- | Z10: =_xlfn.XLOOKUP(G10,'Kraken Trades'!$A$2:$A$28,'Kraken Trades'!$K$2:$K$28,"--",0) -> -- | AA10: =_xlfn.XLOOKUP(G10,'Kraken Trades'!$A$2:$A$28,'Kraken Trades'!$L$2:$L$28,"--",0) -> -- | AB10: =_xlfn.XLOOKUP(G10,'Kraken Trades'!$A$2:$A$28,'Kraken Trades'!$M$2:$M$28,"--",0) -> --
B11: yes | E11: =_xlfn.XLOOKUP(D11,'DEST TAGs'!$A$2:$A$5,'DEST TAGs'!$B$2:$B$5,"--",0) -> -- | F11: LT5VFU-GHMIT-5YX3OJ | G11: AIBLWOI-K6V4V3-O252VX | H11: 44931.582 | I11: withdrawal | K11: currency | L11: XXRP | M11: -1140 | N11: 0.02 | O11: 0.96944334 | P11: =_xlfn.XLOOKUP(G11,'Kraken Trades'!$A$2:$A$28,'Kraken Trades'!$A$2:$A$28,"--",0) -> -- | Q11: =_xlfn.XLOOKUP(G11,'Kraken Trades'!$A$2:$A$28,'Kraken Trades'!$B$2:$B$28,"--",0) -> -- | R11: =_xlfn.XLOOKUP(G11,'Kraken Trades'!$A$2:$A$28,'Kraken Trades'!$C$2:$C$28,"--",0) -> -- | S11: =_xlfn.XLOOKUP(G11,'Kraken Trades'!$A$2:$A$28,'Kraken Trades'!$D$2:$D$28,"--",0) -> -- | T11: =_xlfn.XLOOKUP(G11,'Kraken Trades'!$A$2:$A$28,'Kraken Trades'!$E$2:$E$28,"--",0) -> -- | U11: =_xlfn.XLOOKUP(G11,'Kraken Trades'!$A$2:$A$28,'Kraken Trades'!$F$2:$F$28,"--",0) -> -- | V11: =_xlfn.XLOOKUP(G11,'Kraken Trades'!$A$2:$A$28,'Kraken Trades'!$G$2:$G$28,"--",0) -> -- | W11: =_xlfn.XLOOKUP(G11,'Kraken Trades'!$A$2:$A$28,'Kraken Trades'!$H$2:$H$28,"--",0) -> -- | X11: =_xlfn.XLOOKUP(G11,'Kraken Trades'!$A$2:$A$28,'Kraken Trades'!$I$2:$I$28,"--",0) -> -- | Y11: =_xlfn.XLOOKUP(G11,'Kraken Trades'!$A$2:$A$28,'Kraken Trades'!$J$2:$J$28,"--",0) -> -- | Z11: =_xlfn.XLOOKUP(G11,'Kraken Trades'!$A$2:$A$28,'Kraken Trades'!$K$2:$K$28,"--",0) -> -- | AA11: =_xlfn.XLOOKUP(G11,'Kraken Trades'!$A$2:$A$28,'Kraken Trades'!$L$2:$L$28,"--",0) -> -- | AB11: =_xlfn.XLOOKUP(G11,'Kraken Trades'!$A$2:$A$28,'Kraken Trades'!$M$2:$M$28,"--",0) -> --
B12: yes | E12: =_xlfn.XLOOKUP(D12,'DEST TAGs'!$A$2:$A$5,'DEST TAGs'!$B$2:$B$5,"--",0) -> -- | G12: QYPDDSZ-2NWCKK-7SQZGB | H12: 44940.397 | I12: deposit | K12: currency | L12: ZGBP | M12: 300 | N12: 0 | P12: =_xlfn.XLOOKUP(G12,'Kraken Trades'!$A$2:$A$28,'Kraken Trades'!$A$2:$A$28,"--",0) -> -- | Q12: =_xlfn.XLOOKUP(G12,'Kraken Trades'!$A$2:$A$28,'Kraken Trades'!$B$2:$B$28,"--",0) -> -- | R12: =_xlfn.XLOOKUP(G12,'Kraken Trades'!$A$2:$A$28,'Kraken Trades'!$C$2:$C$28,"--",0) -> -- | S12: =_xlfn.XLOOKUP(G12,'Kraken Trades'!$A$2:$A$28,'Kraken Trades'!$D$2:$D$28,"--",0) -> -- | T12: =_xlfn.XLOOKUP(G12,'Kraken Trades'!$A$2:$A$28,'Kraken Trades'!$E$2:$E$28,"--",0) -> -- | U12: =_xlfn.XLOOKUP(G12,'Kraken Trades'!$A$2:$A$28,'Kraken Trades'!$F$2:$F$28,"--",0) -> -- | V12: =_xlfn.XLOOKUP(G12,'Kraken Trades'!$A$2:$A$28,'Kraken Trades'!$G$2:$G$28,"--",0) -> -- | W12: =_xlfn.XLOOKUP(G12,'Kraken Trades'!$A$2:$A$28,'Kraken Trades'!$H$2:$H$28,"--",0) -> -- | X12: =_xlfn.XLOOKUP(G12,'Kraken Trades'!$A$2:$A$28,'Kraken Trades'!$I$2:$I$28,"--",0) -> -- | Y12: =_xlfn.XLOOKUP(G12,'Kraken Trades'!$A$2:$A$28,'Kraken Trades'!$J$2:$J$28,"--",0) -> -- | Z12: =_xlfn.XLOOKUP(G12,'Kraken Trades'!$A$2:$A$28,'Kraken Trades'!$K$2:$K$28,"--",0) -> -- | AA12: =_xlfn.XLOOKUP(G12,'Kraken Trades'!$A$2:$A$28,'Kraken Trades'!$L$2:$L$28,"--",0) -> -- | AB12: =_xlfn.XLOOKUP(G12,'Kraken Trades'!$A$2:$A$28,'Kraken Trades'!$M$2:$M$28,"--",0) -> --
B13: yes | E13: =_xlfn.XLOOKUP(D13,'DEST TAGs'!$A$2:$A$5,'DEST TAGs'!$B$2:$B$5,"--",0) -> -- | F13: LC64M5-IU4N2-I6GYRU | G13: QYPDDSZ-2NWCKK-7SQZGB | H13: 44940.415 | I13: deposit | K13: currency | L13: ZGBP | M13: 300 | N13: 0 | O13: 303.8151 | P13: =_xlfn.XLOOKUP(G13,'Kraken Trades'!$A$2:$A$28,'Kraken Trades'!$A$2:$A$28,"--",0) -> -- | Q13: =_xlfn.XLOOKUP(G13,'Kraken Trades'!$A$2:$A$28,'Kraken Trades'!$B$2:$B$28,"--",0) -> -- | R13: =_xlfn.XLOOKUP(G13,'Kraken Trades'!$A$2:$A$28,'Kraken Trades'!$C$2:$C$28,"--",0) -> -- | S13: =_xlfn.XLOOKUP(G13,'Kraken Trades'!$A$2:$A$28,'Kraken Trades'!$D$2:$D$28,"--",0) -> -- | T13: =_xlfn.XLOOKUP(G13,'Kraken Trades'!$A$2:$A$28,'Kraken Trades'!$E$2:$E$28,"--",0) -> -- | U13: =_xlfn.XLOOKUP(G13,'Kraken Trades'!$A$2:$A$28,'Kraken Trades'!$F$2:$F$28,"--",0) -> -- | V13: =_xlfn.XLOOKUP(G13,'Kraken Trades'!$A$2:$A$28,'Kraken Trades'!$G$2:$G$28,"--",0) -> -- | W13: =_xlfn.XLOOKUP(G13,'Kraken Trades'!$A$2:$A$28,'Kraken Trades'!$H$2:$H$28,"--",0) -> -- | X13: =_xlfn.XLOOKUP(G13,'Kraken Trades'!$A$2:$A$28,'Kraken Trades'!$I$2:$I$28,"--",0) -> -- | Y13: =_xlfn.XLOOKUP(G13,'Kraken Trades'!$A$2:$A$28,'Kraken Trades'!$J$2:$J$28,"--",0) -> -- | Z13: =_xlfn.XLOOKUP(G13,'Kraken Trades'!$A$2:$A$28,'Kraken Trades'!$K$2:$K$28,"--",0) -> -- | AA13: =_xlfn.XLOOKUP(G13,'Kraken Trades'!$A$2:$A$28,'Kraken Trades'!$L$2:$L$28,"--",0) -> -- | AB13: =_xlfn.XLOOKUP(G13,'Kraken Trades'!$A$2:$A$28,'Kraken Trades'!$M$2:$M$28,"--",0) -> --
B14: yes | E14: =_xlfn.XLOOKUP(D14,'DEST TAGs'!$A$2:$A$5,'DEST TAGs'!$B$2:$B$5,"--",0) -> -- | F14: LAQ6TD-TG2HT-I27ECB | G14: TONPXD-KPDZU-5WAK7C | H14: 44940.426 | I14: trade | K14: currency | L14: ZGBP | M14: -302.1054 | N14: 0 | O14: 1.7097 | P14: =_xlfn.XLOOKUP(G14,'Kraken Trades'!$A$2:$A$28,'Kraken Trades'!$A$2:$A$28,"--",0) -> TONPXD-KPDZU-5WAK7C | Q14: =_xlfn.XLOOKUP(G14,'Kraken Trades'!$A$2:$A$28,'Kraken Trades'!$B$2:$B$28,"--",0) -> OA5AQQ-YBGEA-2YGS2M | R14: =_xlfn.XLOOKUP(G14,'Kraken Trades'!$A$2:$A$28,'Kraken Trades'!$C$2:$C$28,"--",0) -> XRPGBP | S14: =_xlfn.XLOOKUP(G14,'Kraken Trades'!$A$2:$A$28,'Kraken Trades'!$D$2:$D$28,"--",0) -> 0.0096805556 | T14: =_xlfn.XLOOKUP(G14,'Kraken Trades'!$A$2:$A$28,'Kraken Trades'!$E$2:$E$28,"--",0) -> buy | U14: =_xlfn.XLOOKUP(G14,'Kraken Trades'!$A$2:$A$28,'Kraken Trades'!$F$2:$F$28,"--",0) -> market | V14: =_xlfn.XLOOKUP(G14,'Kraken Trades'!$A$2:$A$28,'Kraken Trades'!$G$2:$G$28,"--",0) -> 0.31800562 | W14: =_xlfn.XLOOKUP(G14,'Kraken Trades'!$A$2:$A$28,'Kraken Trades'!$H$2:$H$28,"--",0) -> 302.10534 | X14: =_xlfn.XLOOKUP(G14,'Kraken Trades'!$A$2:$A$28,'Kraken Trades'!$I$2:$I$28,"--",0) -> 0.78547389 | Y14: =_xlfn.XLOOKUP(G14,'Kraken Trades'!$A$2:$A$28,'Kraken Trades'!$J$2:$J$28,"--",0) -> 950 | Z14: =_xlfn.XLOOKUP(G14,'Kraken Trades'!$A$2:$A$28,'Kraken Trades'!$K$2:$K$28,"--",0) -> 0 | AA14: =_xlfn.XLOOKUP(G14,'Kraken Trades'!$A$2:$A$28,'Kraken Trades'!$L$2:$L$28,"--",0) -> initiated | AB14: =_xlfn.XLOOKUP(G14,'Kraken Trades'!$A$2:$A$28,'Kraken Trades'!$M$2:$M$28,"--",0) -> L7GPCS-DXW2B-NSUS3D,LJGS5J-JIVT5-2JPEC4,LAQ6TD-TG2HT-I27ECB
B15: yes | E15: =_xlfn.XLOOKUP(D15,'DEST TAGs'!$A$2:$A$5,'DEST TAGs'!$B$2:$B$5,"--",0) -> -- | F15: LJGS5J-JIVT5-2JPEC4 | G15: TONPXD-KPDZU-5WAK7C | H15: 44940.426 | I15: trade | K15: currency | L15: XXRP | M15: 950 | N15: 0 | O15: 950.96944 | P15: =_xlfn.XLOOKUP(G15,'Kraken Trades'!$A$2:$A$28,'Kraken Trades'!$A$2:$A$28,"--",0) -> TONPXD-KPDZU-5WAK7C | Q15: =_xlfn.XLOOKUP(G15,'Kraken Trades'!$A$2:$A$28,'Kraken Trades'!$B$2:$B$28,"--",0) -> OA5AQQ-YBGEA-2YGS2M | R15: =_xlfn.XLOOKUP(G15,'Kraken Trades'!$A$2:$A$28,'Kraken Trades'!$C$2:$C$28,"--",0) -> XRPGBP | S15: =_xlfn.XLOOKUP(G15,'Kraken Trades'!$A$2:$A$28,'Kraken Trades'!$D$2:$D$28,"--",0) -> 0.0096805556 | T15: =_xlfn.XLOOKUP(G15,'Kraken Trades'!$A$2:$A$28,'Kraken Trades'!$E$2:$E$28,"--",0) -> buy | U15: =_xlfn.XLOOKUP(G15,'Kraken Trades'!$A$2:$A$28,'Kraken Trades'!$F$2:$F$28,"--",0) -> market | V15: =_xlfn.XLOOKUP(G15,'Kraken Trades'!$A$2:$A$28,'Kraken Trades'!$G$2:$G$28,"--",0) -> 0.31800562 | W15: =_xlfn.XLOOKUP(G15,'Kraken Trades'!$A$2:$A$28,'Kraken Trades'!$H$2:$H$28,"--",0) -> 302.10534 | X15: =_xlfn.XLOOKUP(G15,'Kraken Trades'!$A$2:$A$28,'Kraken Trades'!$I$2:$I$28,"--",0) -> 0.78547389 | Y15: =_xlfn.XLOOKUP(G15,'Kraken Trades'!$A$2:$A$28,'Kraken Trades'!$J$2:$J$28,"--",0) -> 950 | Z15: =_xlfn.XLOOKUP(G15,'Kraken Trades'!$A$2:$A$28,'Kraken Trades'!$K$2:$K$28,"--",0) -> 0 | AA15: =_xlfn.XLOOKUP(G15,'Kraken Trades'!$A$2:$A$28,'Kraken Trades'!$L$2:$L$28,"--",0) -> initiated | AB15: =_xlfn.XLOOKUP(G15,'Kraken Trades'!$A$2:$A$28,'Kraken Trades'!$M$2:$M$28,"--",0) -> L7GPCS-DXW2B-NSUS3D,LJGS5J-JIVT5-2JPEC4,LAQ6TD-TG2HT-I27ECB
B16: yes | E16: =_xlfn.XLOOKUP(D16,'DEST TAGs'!$A$2:$A$5,'DEST TAGs'!$B$2:$B$5,"--",0) -> -- | F16: L7GPCS-DXW2B-NSUS3D | G16: TONPXD-KPDZU-5WAK7C | H16: 44940.426 | I16: trade | K16: currency | L16: KFEE | M16: 0 | N16: 96.02 | O16: 7814.25 | P16: =_xlfn.XLOOKUP(G16,'Kraken Trades'!$A$2:$A$28,'Kraken Trades'!$A$2:$A$28,"--",0) -> TONPXD-KPDZU-5WAK7C | Q16: =_xlfn.XLOOKUP(G16,'Kraken Trades'!$A$2:$A$28,'Kraken Trades'!$B$2:$B$28,"--",0) -> OA5AQQ-YBGEA-2YGS2M | R16: =_xlfn.XLOOKUP(G16,'Kraken Trades'!$A$2:$A$28,'Kraken Trades'!$C$2:$C$28,"--",0) -> XRPGBP | S16: =_xlfn.XLOOKUP(G16,'Kraken Trades'!$A$2:$A$28,'Kraken Trades'!$D$2:$D$28,"--",0) -> 0.0096805556 | T16: =_xlfn.XLOOKUP(G16,'Kraken Trades'!$A$2:$A$28,'Kraken Trades'!$E$2:$E$28,"--",0) -> buy | U16: =_xlfn.XLOOKUP(G16,'Kraken Trades'!$A$2:$A$28,'Kraken Trades'!$F$2:$F$28,"--",0) -> market | V16: =_xlfn.XLOOKUP(G16,'Kraken Trades'!$A$2:$A$28,'Kraken Trades'!$G$2:$G$28,"--",0) -> 0.31800562 | W16: =_xlfn.XLOOKUP(G16,'Kraken Trades'!$A$2:$A$28,'Kraken Trades'!$H$2:$H$28,"--",0) -> 302.10534 | X16: =_xlfn.XLOOKUP(G16,'Kraken Trades'!$A$2:$A$28,'Kraken Trades'!$I$2:$I$28,"--",0) -> 0.78547389 | Y16: =_xlfn.XLOOKUP(G16,'Kraken Trades'!$A$2:$A$28,'Kraken Trades'!$J$2:$J$28,"--",0) -> 950 | Z16: =_xlfn.XLOOKUP(G16,'Kraken Trades'!$A$2:$A$28,'Kraken Trades'!$K$2:$K$28,"--",0) -> 0 | AA16: =_xlfn.XLOOKUP(G16,'Kraken Trades'!$A$2:$A$28,'Kraken Trades'!$L$2:$L$28,"--",0) -> initiated | AB16: =_xlfn.XLOOKUP(G16,'Kraken Trades'!$A$2:$A$28,'Kraken Trades'!$M$2:$M$28,"--",0) -> L7GPCS-DXW2B-NSUS3D,LJGS5J-JIVT5-2JPEC4,LAQ6TD-TG2HT-I27ECB
B17: yes | E17: =_xlfn.XLOOKUP(D17,'DEST TAGs'!$A$2:$A$5,'DEST TAGs'!$B$2:$B$5,"--",0) -> -- | G17: AIB5IWF-EUNVU3-TGM5OZ | H17: 44940.426 | I17: withdrawal | K17: currency | L17: XXRP | M17: -950 | N17: 0.02 | P17: =_xlfn.XLOOKUP(G17,'Kraken Trades'!$A$2:$A$28,'Kraken Trades'!$A$2:$A$28,"--",0) -> -- | Q17: =_xlfn.XLOOKUP(G17,'Kraken Trades'!$A$2:$A$28,'Kraken Trades'!$B$2:$B$28,"--",0) -> -- | R17: =_xlfn.XLOOKUP(G17,'Kraken Trades'!$A$2:$A$28,'Kraken Trades'!$C$2:$C$28,"--",0) -> -- | S17: =_xlfn.XLOOKUP(G17,'Kraken Trades'!$A$2:$A$28,'Kraken Trades'!$D$2:$D$28,"--",0) -> -- | T17: =_xlfn.XLOOKUP(G17,'Kraken Trades'!$A$2:$A$28,'Kraken Trades'!$E$2:$E$28,"--",0) -> -- | U17: =_xlfn.XLOOKUP(G17,'Kraken Trades'!$A$2:$A$28,'Kraken Trades'!$F$2:$F$28,"--",0) -> -- | V17: =_xlfn.XLOOKUP(G17,'Kraken Trades'!$A$2:$A$28,'Kraken Trades'!$G$2:$G$28,"--",0) -> -- | W17: =_xlfn.XLOOKUP(G17,'Kraken Trades'!$A$2:$A$28,'Kraken Trades'!$H$2:$H$28,"--",0) -> -- | X17: =_xlfn.XLOOKUP(G17,'Kraken Trades'!$A$2:$A$28,'Kraken Trades'!$I$2:$I$28,"--",0) -> -- | Y17: =_xlfn.XLOOKUP(G17,'Kraken Trades'!$A$2:$A$28,'Kraken Trades'!$J$2:$J$28,"--",0) -> -- | Z17: =_xlfn.XLOOKUP(G17,'Kraken Trades'!$A$2:$A$28,'Kraken Trades'!$K$2:$K$28,"--",0) -> -- | AA17: =_xlfn.XLOOKUP(G17,'Kraken Trades'!$A$2:$A$28,'Kraken Trades'!$L$2:$L$28,"--",0) -> -- | AB17: =_xlfn.XLOOKUP(G17,'Kraken Trades'!$A$2:$A$28,'Kraken Trades'!$M$2:$M$28,"--",0) -> --
B18: yes | E18: =_xlfn.XLOOKUP(D18,'DEST TAGs'!$A$2:$A$5,'DEST TAGs'!$B$2:$B$5,"--",0) -> -- | F18: LHORHY-JQ5AH-KIOIAE | G18: AIB5IWF-EUNVU3-TGM5OZ | H18: 44940.428 | I18: withdrawal | K18: currency | L18: XXRP | M18: -950 | N18: 0.02 | O18: 0.94944334 | P18: =_xlfn.XLOOKUP(G18,'Kraken Trades'!$A$2:$A$28,'Kraken Trades'!$A$2:$A$28,"--",0) -> -- | Q18: =_xlfn.XLOOKUP(G18,'Kraken Trades'!$A$2:$A$28,'Kraken Trades'!$B$2:$B$28,"--",0) -> -- | R18: =_xlfn.XLOOKUP(G18,'Kraken Trades'!$A$2:$A$28,'Kraken Trades'!$C$2:$C$28,"--",0) -> -- | S18: =_xlfn.XLOOKUP(G18,'Kraken Trades'!$A$2:$A$28,'Kraken Trades'!$D$2:$D$28,"--",0) -> -- | T18: =_xlfn.XLOOKUP(G18,'Kraken Trades'!$A$2:$A$28,'Kraken Trades'!$E$2:$E$28,"--",0) -> -- | U18: =_xlfn.XLOOKUP(G18,'Kraken Trades'!$A$2:$A$28,'Kraken Trades'!$F$2:$F$28,"--",0) -> -- | V18: =_xlfn.XLOOKUP(G18,'Kraken Trades'!$A$2:$A$28,'Kraken Trades'!$G$2:$G$28,"--",0) -> -- | W18: =_xlfn.XLOOKUP(G18,'Kraken Trades'!$A$2:$A$28,'Kraken Trades'!$H$2:$H$28,"--",0) -> -- | X18: =_xlfn.XLOOKUP(G18,'Kraken Trades'!$A$2:$A$28,'Kraken Trades'!$I$2:$I$28,"--",0) -> -- | Y18: =_xlfn.XLOOKUP(G18,'Kraken Trades'!$A$2:$A$28,'Kraken Trades'!$J$2:$J$28,"--",0) -> -- | Z18: =_xlfn.XLOOKUP(G18,'Kraken Trades'!$A$2:$A$28,'Kraken Trades'!$K$2:$K$28,"--",0) -> -- | AA18: =_xlfn.XLOOKUP(G18,'Kraken Trades'!$A$2:$A$28,'Kraken Trades'!$L$2:$L$28,"--",0) -> -- | AB18: =_xlfn.XLOOKUP(G18,'Kraken Trades'!$A$2:$A$28,'Kraken Trades'!$M$2:$M$28,"--",0) -> --
B19: yes | E19: =_xlfn.XLOOKUP(D19,'DEST TAGs'!$A$2:$A$5,'DEST TAGs'!$B$2:$B$5,"--",0) -> -- | G19: QYPHCEQ-52QCIX-MFW6DR | H19: 44945.444 | I19: deposit | K19: currency | L19: ZGBP | M19: 850 | N19: 0 | P19: =_xlfn.XLOOKUP(G19,'Kraken Trades'!$A$2:$A$28,'Kraken Trades'!$A$2:$A$28,"--",0) -> -- | Q19: =_xlfn.XLOOKUP(G19,'Kraken Trades'!$A$2:$A$28,'Kraken Trades'!$B$2:$B$28,"--",0) -> -- | R19: =_xlfn.XLOOKUP(G19,'Kraken Trades'!$A$2:$A$28,'Kraken Trades'!$C$2:$C$28,"--",0) -> -- | S19: =_xlfn.XLOOKUP(G19,'Kraken Trades'!$A$2:$A$28,'Kraken Trades'!$D$2:$D$28,"--",0) -> -- | T19: =_xlfn.XLOOKUP(G19,'Kraken Trades'!$A$2:$A$28,'Kraken Trades'!$E$2:$E$28,"--",0) -> -- | U19: =_xlfn.XLOOKUP(G19,'Kraken Trades'!$A$2:$A$28,'Kraken Trades'!$F$2:$F$28,"--",0) -> -- | V19: =_xlfn.XLOOKUP(G19,'Kraken Trades'!$A$2:$A$28,'Kraken Trades'!$G$2:$G$28,"--",0) -> -- | W19: =_xlfn.XLOOKUP(G19,'Kraken Trades'!$A$2:$A$28,'Kraken Trades'!$H$2:$H$28,"--",0) -> -- | X19: =_xlfn.XLOOKUP(G19,'Kraken Trades'!$A$2:$A$28,'Kraken Trades'!$I$2:$I$28,"--",0) -> -- | Y19: =_xlfn.XLOOKUP(G19,'Kraken Trades'!$A$2:$A$28,'Kraken Trades'!$J$2:$J$28,"--",0) -> -- | Z19: =_xlfn.XLOOKUP(G19,'Kraken Trades'!$A$2:$A$28,'Kraken Trades'!$K$2:$K$28,"--",0) -> -- | AA19: =_xlfn.XLOOKUP(G19,'Kraken Trades'!$A$2:$A$28,'Kraken Trades'!$L$2:$L$28,"--",0) -> -- | AB19: =_xlfn.XLOOKUP(G19,'Kraken Trades'!$A$2:$A$28,'Kraken Trades'!$M$2:$M$28,"--",0) -> --
B20: yes | E20: =_xlfn.XLOOKUP(D20,'DEST TAGs'!$A$2:$A$5,'DEST TAGs'!$B$2:$B$5,"--",0) -> -- | F20: LO7JZE-IQ7D6-HDBDJV | G20: QYPHCEQ-52QCIX-MFW6DR | H20: 44945.45 | I20: deposit | K20: currency | L20: ZGBP | M20: 850 | N20: 0 | O20: 851.7097 | P20: =_xlfn.XLOOKUP(G20,'Kraken Trades'!$A$2:$A$28,'Kraken Trades'!$A$2:$A$28,"--",0) -> -- | Q20: =_xlfn.XLOOKUP(G20,'Kraken Trades'!$A$2:$A$28,'Kraken Trades'!$B$2:$B$28,"--",0) -> -- | R20: =_xlfn.XLOOKUP(G20,'Kraken Trades'!$A$2:$A$28,'Kraken Trades'!$C$2:$C$28,"--",0) -> -- | S20: =_xlfn.XLOOKUP(G20,'Kraken Trades'!$A$2:$A$28,'Kraken Trades'!$D$2:$D$28,"--",0) -> -- | T20: =_xlfn.XLOOKUP(G20,'Kraken Trades'!$A$2:$A$28,'Kraken Trades'!$E$2:$E$28,"--",0) -> -- | U20: =_xlfn.XLOOKUP(G20,'Kraken Trades'!$A$2:$A$28,'Kraken Trades'!$F$2:$F$28,"--",0) -> -- | V20: =_xlfn.XLOOKUP(G20,'Kraken Trades'!$A$2:$A$28,'Kraken Trades'!$G$2:$G$28,"--",0) -> -- | W20: =_xlfn.XLOOKUP(G20,'Kraken Trades'!$A$2:$A$28,'Kraken Trades'!$H$2:$H$28,"--",0) -> -- | X20: =_xlfn.XLOOKUP(G20,'Kraken Trades'!$A$2:$A$28,'Kraken Trades'!$I$2:$I$28,"--",0) -> -- | Y20: =_xlfn.XLOOKUP(G20,'Kraken Trades'!$A$2:$A$28,'Kraken Trades'!$J$2:$J$28,"--",0) -> -- | Z20: =_xlfn.XLOOKUP(G20,'Kraken Trades'!$A$2:$A$28,'Kraken Trades'!$K$2:$K$28,"--",0) -> -- | AA20: =_xlfn.XLOOKUP(G20,'Kraken Trades'!$A$2:$A$28,'Kraken Trades'!$L$2:$L$28,"--",0) -> -- | AB20: =_xlfn.XLOOKUP(G20,'Kraken Trades'!$A$2:$A$28,'Kraken Trades'!$M$2:$M$28,"--",0) -> --
B21: yes | E21: =_xlfn.XLOOKUP(D21,'DEST TAGs'!$A$2:$A$5,'DEST TAGs'!$B$2:$B$5,"--",0) -> -- | F21: LQ5Y6F-GXLDN-OQIMCY | G21: TFUFLH-JICVN-QIRXBC | H21: 44945.452 | I21: trade | K21: currency | L21: ZGBP | M21: -850.2842 | N21: 0 | O21: 1.4255 | P21: =_xlfn.XLOOKUP(G21,'Kraken Trades'!$A$2:$A$28,'Kraken Trades'!$A$2:$A$28,"--",0) -> TFUFLH-JICVN-QIRXBC | Q21: =_xlfn.XLOOKUP(G21,'Kraken Trades'!$A$2:$A$28,'Kraken Trades'!$B$2:$B$28,"--",0) -> ON4G3V-EWYBS-PENEAQ | R21: =_xlfn.XLOOKUP(G21,'Kraken Trades'!$A$2:$A$28,'Kraken Trades'!$C$2:$C$28,"--",0) -> XRPGBP | S21: =_xlfn.XLOOKUP(G21,'Kraken Trades'!$A$2:$A$28,'Kraken Trades'!$D$2:$D$28,"--",0) -> 0.035511574 | T21: =_xlfn.XLOOKUP(G21,'Kraken Trades'!$A$2:$A$28,'Kraken Trades'!$E$2:$E$28,"--",0) -> buy | U21: =_xlfn.XLOOKUP(G21,'Kraken Trades'!$A$2:$A$28,'Kraken Trades'!$F$2:$F$28,"--",0) -> market | V21: =_xlfn.XLOOKUP(G21,'Kraken Trades'!$A$2:$A$28,'Kraken Trades'!$G$2:$G$28,"--",0) -> 0.31492011 | W21: =_xlfn.XLOOKUP(G21,'Kraken Trades'!$A$2:$A$28,'Kraken Trades'!$H$2:$H$28,"--",0) -> 850.28431 | X21: =_xlfn.XLOOKUP(G21,'Kraken Trades'!$A$2:$A$28,'Kraken Trades'!$I$2:$I$28,"--",0) -> 2.2107392 | Y21: =_xlfn.XLOOKUP(G21,'Kraken Trades'!$A$2:$A$28,'Kraken Trades'!$J$2:$J$28,"--",0) -> 2700 | Z21: =_xlfn.XLOOKUP(G21,'Kraken Trades'!$A$2:$A$28,'Kraken Trades'!$K$2:$K$28,"--",0) -> 0 | AA21: =_xlfn.XLOOKUP(G21,'Kraken Trades'!$A$2:$A$28,'Kraken Trades'!$L$2:$L$28,"--",0) -> initiated | AB21: =_xlfn.XLOOKUP(G21,'Kraken Trades'!$A$2:$A$28,'Kraken Trades'!$M$2:$M$28,"--",0) -> L2AZFP-MHOGI-Z6IC76,LQENTR-CXN3S-V2AFUZ,LQ5Y6F-GXLDN-OQIMCY
B22: yes | E22: =_xlfn.XLOOKUP(D22,'DEST TAGs'!$A$2:$A$5,'DEST TAGs'!$B$2:$B$5,"--",0) -> -- | F22: LQENTR-CXN3S-V2AFUZ | G22: TFUFLH-JICVN-QIRXBC | H22: 44945.452 | I22: trade | K22: currency | L22: XXRP | M22: 2700 | N22: 0 | O22: 2700.9494 | P22: =_xlfn.XLOOKUP(G22,'Kraken Trades'!$A$2:$A$28,'Kraken Trades'!$A$2:$A$28,"--",0) -> TFUFLH-JICVN-QIRXBC | Q22: =_xlfn.XLOOKUP(G22,'Kraken Trades'!$A$2:$A$28,'Kraken Trades'!$B$2:$B$28,"--",0) -> ON4G3V-EWYBS-PENEAQ | R22: =_xlfn.XLOOKUP(G22,'Kraken Trades'!$A$2:$A$28,'Kraken Trades'!$C$2:$C$28,"--",0) -> XRPGBP | S22: =_xlfn.XLOOKUP(G22,'Kraken Trades'!$A$2:$A$28,'Kraken Trades'!$D$2:$D$28,"--",0) -> 0.035511574 | T22: =_xlfn.XLOOKUP(G22,'Kraken Trades'!$A$2:$A$28,'Kraken Trades'!$E$2:$E$28,"--",0) -> buy | U22: =_xlfn.XLOOKUP(G22,'Kraken Trades'!$A$2:$A$28,'Kraken Trades'!$F$2:$F$28,"--",0) -> market | V22: =_xlfn.XLOOKUP(G22,'Kraken Trades'!$A$2:$A$28,'Kraken Trades'!$G$2:$G$28,"--",0) -> 0.31492011 | W22: =_xlfn.XLOOKUP(G22,'Kraken Trades'!$A$2:$A$28,'Kraken Trades'!$H$2:$H$28,"--",0) -> 850.28431 | X22: =_xlfn.XLOOKUP(G22,'Kraken Trades'!$A$2:$A$28,'Kraken Trades'!$I$2:$I$28,"--",0) -> 2.2107392 | Y22: =_xlfn.XLOOKUP(G22,'Kraken Trades'!$A$2:$A$28,'Kraken Trades'!$J$2:$J$28,"--",0) -> 2700 | Z22: =_xlfn.XLOOKUP(G22,'Kraken Trades'!$A$2:$A$28,'Kraken Trades'!$K$2:$K$28,"--",0) -> 0 | AA22: =_xlfn.XLOOKUP(G22,'Kraken Trades'!$A$2:$A$28,'Kraken Trades'!$L$2:$L$28,"--",0) -> initiated | AB22: =_xlfn.XLOOKUP(G22,'Kraken Trades'!$A$2:$A$28,'Kraken Trades'!$M$2:$M$28,"--",0) -> L2AZFP-MHOGI-Z6IC76,LQENTR-CXN3S-V2AFUZ,LQ5Y6F-GXLDN-OQIMCY
B23: yes | E23: =_xlfn.XLOOKUP(D23,'DEST TAGs'!$A$2:$A$5,'DEST TAGs'!$B$2:$B$5,"--",0) -> -- | F23: L2AZFP-MHOGI-Z6IC76 | G23: TFUFLH-JICVN-QIRXBC | H23: 44945.452 | I23: trade | K23: currency | L23: KFEE | M23: 0 | N23: 272.55 | O23: 7541.7 | P23: =_xlfn.XLOOKUP(G23,'Kraken Trades'!$A$2:$A$28,'Kraken Trades'!$A$2:$A$28,"--",0) -> TFUFLH-JICVN-QIRXBC | Q23: =_xlfn.XLOOKUP(G23,'Kraken Trades'!$A$2:$A$28,'Kraken Trades'!$B$2:$B$28,"--",0) -> ON4G3V-EWYBS-PENEAQ | R23: =_xlfn.XLOOKUP(G23,'Kraken Trades'!$A$2:$A$28,'Kraken Trades'!$C$2:$C$28,"--",0) -> XRPGBP | S23: =_xlfn.XLOOKUP(G23,'Kraken Trades'!$A$2:$A$28,'Kraken Trades'!$D$2:$D$28,"--",0) -> 0.035511574 | T23: =_xlfn.XLOOKUP(G23,'Kraken Trades'!$A$2:$A$28,'Kraken Trades'!$E$2:$E$28,"--",0) -> buy | U23: =_xlfn.XLOOKUP(G23,'Kraken Trades'!$A$2:$A$28,'Kraken Trades'!$F$2:$F$28,"--",0) -> market | V23: =_xlfn.XLOOKUP(G23,'Kraken Trades'!$A$2:$A$28,'Kraken Trades'!$G$2:$G$28,"--",0) -> 0.31492011 | W23: =_xlfn.XLOOKUP(G23,'Kraken Trades'!$A$2:$A$28,'Kraken Trades'!$H$2:$H$28,"--",0) -> 850.28431 | X23: =_xlfn.XLOOKUP(G23,'Kraken Trades'!$A$2:$A$28,'Kraken Trades'!$I$2:$I$28,"--",0) -> 2.2107392 | Y23: =_xlfn.XLOOKUP(G23,'Kraken Trades'!$A$2:$A$28,'Kraken Trades'!$J$2:$J$28,"--",0) -> 2700 | Z23: =_xlfn.XLOOKUP(G23,'Kraken Trades'!$A$2:$A$28,'Kraken Trades'!$K$2:$K$28,"--",0) -> 0 | AA23: =_xlfn.XLOOKUP(G23,'Kraken Trades'!$A$2:$A$28,'Kraken Trades'!$L$2:$L$28,"--",0) -> initiated | AB23: =_xlfn.XLOOKUP(G23,'Kraken Trades'!$A$2:$A$28,'Kraken Trades'!$M$2:$M$28,"--",0) -> L2AZFP-MHOGI-Z6IC76,LQENTR-CXN3S-V2AFUZ,LQ5Y6F-GXLDN-OQIMCY
B24: yes | E24: =_xlfn.XLOOKUP(D24,'DEST TAGs'!$A$2:$A$5,'DEST TAGs'!$B$2:$B$5,"--",0) -> -- | G24: AIBR3RN-RCA564-DEIYYX | H24: 44945.452 | I24: withdrawal | K24: currency | L24: XXRP | M24: -2700 | N24: 0.02 | P24: =_xlfn.XLOOKUP(G24,'Kraken Trades'!$A$2:$A$28,'Kraken Trades'!$A$2:$A$28,"--",0) -> -- | Q24: =_xlfn.XLOOKUP(G24,'Kraken Trades'!$A$2:$A$28,'Kraken Trades'!$B$2:$B$28,"--",0) -> -- | R24: =_xlfn.XLOOKUP(G24,'Kraken Trades'!$A$2:$A$28,'Kraken Trades'!$C$2:$C$28,"--",0) -> -- | S24: =_xlfn.XLOOKUP(G24,'Kraken Trades'!$A$2:$A$28,'Kraken Trades'!$D$2:$D$28,"--",0) -> -- | T24: =_xlfn.XLOOKUP(G24,'Kraken Trades'!$A$2:$A$28,'Kraken Trades'!$E$2:$E$28,"--",0) -> -- | U24: =_xlfn.XLOOKUP(G24,'Kraken Trades'!$A$2:$A$28,'Kraken Trades'!$F$2:$F$28,"--",0) -> -- | V24: =_xlfn.XLOOKUP(G24,'Kraken Trades'!$A$2:$A$28,'Kraken Trades'!$G$2:$G$28,"--",0) -> -- | W24: =_xlfn.XLOOKUP(G24,'Kraken Trades'!$A$2:$A$28,'Kraken Trades'!$H$2:$H$28,"--",0) -> -- | X24: =_xlfn.XLOOKUP(G24,'Kraken Trades'!$A$2:$A$28,'Kraken Trades'!$I$2:$I$28,"--",0) -> -- | Y24: =_xlfn.XLOOKUP(G24,'Kraken Trades'!$A$2:$A$28,'Kraken Trades'!$J$2:$J$28,"--",0) -> -- | Z24: =_xlfn.XLOOKUP(G24,'Kraken Trades'!$A$2:$A$28,'Kraken Trades'!$K$2:$K$28,"--",0) -> -- | AA24: =_xlfn.XLOOKUP(G24,'Kraken Trades'!$A$2:$A$28,'Kraken Trades'!$L$2:$L$28,"--",0) -> -- | AB24: =_xlfn.XLOOKUP(G24,'Kraken Trades'!$A$2:$A$28,'Kraken Trades'!$M$2:$M$28,"--",0) -> --
B25: yes | E25: =_xlfn.XLOOKUP(D25,'DEST TAGs'!$A$2:$A$5,'DEST TAGs'!$B$2:$B$5,"--",0) -> -- | F25: LB3VDZ-3XU4V-F5JKI3 | G25: AIBR3RN-RCA564-DEIYYX | H25: 44945.453 | I25: withdrawal | K25: currency | L25: XXRP | M25: -2700 | N25: 0.02 | O25: 0.92944334 | P25: =_xlfn.XLOOKUP(G25,'Kraken Trades'!$A$2:$A$28,'Kraken Trades'!$A$2:$A$28,"--",0) -> -- | Q25: =_xlfn.XLOOKUP(G25,'Kraken Trades'!$A$2:$A$28,'Kraken Trades'!$B$2:$B$28,"--",0) -> -- | R25: =_xlfn.XLOOKUP(G25,'Kraken Trades'!$A$2:$A$28,'Kraken Trades'!$C$2:$C$28,"--",0) -> -- | S25: =_xlfn.XLOOKUP(G25,'Kraken Trades'!$A$2:$A$28,'Kraken Trades'!$D$2:$D$28,"--",0) -> -- | T25: =_xlfn.XLOOKUP(G25,'Kraken Trades'!$A$2:$A$28,'Kraken Trades'!$E$2:$E$28,"--",0) -> -- | U25: =_xlfn.XLOOKUP(G25,'Kraken Trades'!$A$2:$A$28,'Kraken Trades'!$F$2:$F$28,"--",0) -> -- | V25: =_xlfn.XLOOKUP(G25,'Kraken Trades'!$A$2:$A$28,'Kraken Trades'!$G$2:$G$28,"--",0) -> -- | W25: =_xlfn.XLOOKUP(G25,'Kraken Trades'!$A$2:$A$28,'Kraken Trades'!$H$2:$H$28,"--",0) -> -- | X25: =_xlfn.XLOOKUP(G25,'Kraken Trades'!$A$2:$A$28,'Kraken Trades'!$I$2:$I$28,"--",0) -> -- | Y25: =_xlfn.XLOOKUP(G25,'Kraken Trades'!$A$2:$A$28,'Kraken Trades'!$J$2:$J$28,"--",0) -> -- | Z25: =_xlfn.XLOOKUP(G25,'Kraken Trades'!$A$2:$A$28,'Kraken Trades'!$K$2:$K$28,"--",0) -> -- | AA25: =_xlfn.XLOOKUP(G25,'Kraken Trades'!$A$2:$A$28,'Kraken Trades'!$L$2:$L$28,"--",0) -> -- | AB25: =_xlfn.XLOOKUP(G25,'Kraken Trades'!$A$2:$A$28,'Kraken Trades'!$M$2:$M$28,"--",0) -> --
B26: yes | E26: =_xlfn.XLOOKUP(D26,'DEST TAGs'!$A$2:$A$5,'DEST TAGs'!$B$2:$B$5,"--",0) -> -- | G26: QYPVSFN-YLYON6-TG7CCM | H26: 44954.46 | I26: deposit | K26: currency | L26: ZGBP | M26: 175 | N26: 0 | P26: =_xlfn.XLOOKUP(G26,'Kraken Trades'!$A$2:$A$28,'Kraken Trades'!$A$2:$A$28,"--",0) -> -- | Q26: =_xlfn.XLOOKUP(G26,'Kraken Trades'!$A$2:$A$28,'Kraken Trades'!$B$2:$B$28,"--",0) -> -- | R26: =_xlfn.XLOOKUP(G26,'Kraken Trades'!$A$2:$A$28,'Kraken Trades'!$C$2:$C$28,"--",0) -> -- | S26: =_xlfn.XLOOKUP(G26,'Kraken Trades'!$A$2:$A$28,'Kraken Trades'!$D$2:$D$28,"--",0) -> -- | T26: =_xlfn.XLOOKUP(G26,'Kraken Trades'!$A$2:$A$28,'Kraken Trades'!$E$2:$E$28,"--",0) -> -- | U26: =_xlfn.XLOOKUP(G26,'Kraken Trades'!$A$2:$A$28,'Kraken Trades'!$F$2:$F$28,"--",0) -> -- | V26: =_xlfn.XLOOKUP(G26,'Kraken Trades'!$A$2:$A$28,'Kraken Trades'!$G$2:$G$28,"--",0) -> -- | W26: =_xlfn.XLOOKUP(G26,'Kraken Trades'!$A$2:$A$28,'Kraken Trades'!$H$2:$H$28,"--",0) -> -- | X26: =_xlfn.XLOOKUP(G26,'Kraken Trades'!$A$2:$A$28,'Kraken Trades'!$I$2:$I$28,"--",0) -> -- | Y26: =_xlfn.XLOOKUP(G26,'Kraken Trades'!$A$2:$A$28,'Kraken Trades'!$J$2:$J$28,"--",0) -> -- | Z26: =_xlfn.XLOOKUP(G26,'Kraken Trades'!$A$2:$A$28,'Kraken Trades'!$K$2:$K$28,"--",0) -> -- | AA26: =_xlfn.XLOOKUP(G26,'Kraken Trades'!$A$2:$A$28,'Kraken Trades'!$L$2:$L$28,"--",0) -> -- | AB26: =_xlfn.XLOOKUP(G26,'Kraken Trades'!$A$2:$A$28,'Kraken Trades'!$M$2:$M$28,"--",0) -> --
B27: yes | E27: =_xlfn.XLOOKUP(D27,'DEST TAGs'!$A$2:$A$5,'DEST TAGs'!$B$2:$B$5,"--",0) -> -- | F27: LOE2FQ-X6PEM-AQH2PB | G27: QYPVSFN-YLYON6-TG7CCM | H27: 44954.501 | I27: deposit | K27: currency | L27: ZGBP | M27: 175 | N27: 0 | O27: 176.4255 | P27: =_xlfn.XLOOKUP(G27,'Kraken Trades'!$A$2:$A$28,'Kraken Trades'!$A$2:$A$28,"--",0) -> -- | Q27: =_xlfn.XLOOKUP(G27,'Kraken Trades'!$A$2:$A$28,'Kraken Trades'!$B$2:$B$28,"--",0) -> -- | R27: =_xlfn.XLOOKUP(G27,'Kraken Trades'!$A$2:$A$28,'Kraken Trades'!$C$2:$C$28,"--",0) -> -- | S27: =_xlfn.XLOOKUP(G27,'Kraken Trades'!$A$2:$A$28,'Kraken Trades'!$D$2:$D$28,"--",0) -> -- | T27: =_xlfn.XLOOKUP(G27,'Kraken Trades'!$A$2:$A$28,'Kraken Trades'!$E$2:$E$28,"--",0) -> -- | U27: =_xlfn.XLOOKUP(G27,'Kraken Trades'!$A$2:$A$28,'Kraken Trades'!$F$2:$F$28,"--",0) -> -- | V27: =_xlfn.XLOOKUP(G27,'Kraken Trades'!$A$2:$A$28,'Kraken Trades'!$G$2:$G$28,"--",0) -> -- | W27: =_xlfn.XLOOKUP(G27,'Kraken Trades'!$A$2:$A$28,'Kraken Trades'!$H$2:$H$28,"--",0) -> -- | X27: =_xlfn.XLOOKUP(G27,'Kraken Trades'!$A$2:$A$28,'Kraken Trades'!$I$2:$I$28,"--",0) -> -- | Y27: =_xlfn.XLOOKUP(G27,'Kraken Trades'!$A$2:$A$28,'Kraken Trades'!$J$2:$J$28,"--",0) -> -- | Z27: =_xlfn.XLOOKUP(G27,'Kraken Trades'!$A$2:$A$28,'Kraken Trades'!$K$2:$K$28,"--",0) -> -- | AA27: =_xlfn.XLOOKUP(G27,'Kraken Trades'!$A$2:$A$28,'Kraken Trades'!$L$2:$L$28,"--",0) -> -- | AB27: =_xlfn.XLOOKUP(G27,'Kraken Trades'!$A$2:$A$28,'Kraken Trades'!$M$2:$M$28,"--",0) -> --
B28: yes | E28: =_xlfn.XLOOKUP(D28,'DEST TAGs'!$A$2:$A$5,'DEST TAGs'!$B$2:$B$5,"--",0) -> -- | F28: LNTCL3-MS5IQ-JHFPLF | G28: TS6ESC-QJCTE-7REB62 | H28: 44954.504 | I28: trade | K28: currency | L28: ZGBP | M28: -175.3876 | N28: 0 | O28: 1.0379 | P28: =_xlfn.XLOOKUP(G28,'Kraken Trades'!$A$2:$A$28,'Kraken Trades'!$A$2:$A$28,"--",0) -> TS6ESC-QJCTE-7REB62 | Q28: =_xlfn.XLOOKUP(G28,'Kraken Trades'!$A$2:$A$28,'Kraken Trades'!$B$2:$B$28,"--",0) -> OVMH6P-VMU7P-E44AOJ | R28: =_xlfn.XLOOKUP(G28,'Kraken Trades'!$A$2:$A$28,'Kraken Trades'!$C$2:$C$28,"--",0) -> XRPGBP | S28: =_xlfn.XLOOKUP(G28,'Kraken Trades'!$A$2:$A$28,'Kraken Trades'!$D$2:$D$28,"--",0) -> 0.0046458333 | T28: =_xlfn.XLOOKUP(G28,'Kraken Trades'!$A$2:$A$28,'Kraken Trades'!$E$2:$E$28,"--",0) -> buy | U28: =_xlfn.XLOOKUP(G28,'Kraken Trades'!$A$2:$A$28,'Kraken Trades'!$F$2:$F$28,"--",0) -> market | V28: =_xlfn.XLOOKUP(G28,'Kraken Trades'!$A$2:$A$28,'Kraken Trades'!$G$2:$G$28,"--",0) -> 0.33092 | W28: =_xlfn.XLOOKUP(G28,'Kraken Trades'!$A$2:$A$28,'Kraken Trades'!$H$2:$H$28,"--",0) -> 175.3876 | X28: =_xlfn.XLOOKUP(G28,'Kraken Trades'!$A$2:$A$28,'Kraken Trades'!$I$2:$I$28,"--",0) -> 0.45600776 | Y28: =_xlfn.XLOOKUP(G28,'Kraken Trades'!$A$2:$A$28,'Kraken Trades'!$J$2:$J$28,"--",0) -> 530 | Z28: =_xlfn.XLOOKUP(G28,'Kraken Trades'!$A$2:$A$28,'Kraken Trades'!$K$2:$K$28,"--",0) -> 0 | AA28: =_xlfn.XLOOKUP(G28,'Kraken Trades'!$A$2:$A$28,'Kraken Trades'!$L$2:$L$28,"--",0) -> initiated | AB28: =_xlfn.XLOOKUP(G28,'Kraken Trades'!$A$2:$A$28,'Kraken Trades'!$M$2:$M$28,"--",0) -> L7JNEK-NXJOR-PGHOYD,LKUCJL-B6QP6-HVTZSZ,LNTCL3-MS5IQ-JHFPLF
B29: yes | E29: =_xlfn.XLOOKUP(D29,'DEST TAGs'!$A$2:$A$5,'DEST TAGs'!$B$2:$B$5,"--",0) -> -- | F29: LKUCJL-B6QP6-HVTZSZ | G29: TS6ESC-QJCTE-7REB62 | H29: 44954.504 | I29: trade | K29: currency | L29: XXRP | M29: 530 | N29: 0 | O29: 530.92944 | P29: =_xlfn.XLOOKUP(G29,'Kraken Trades'!$A$2:$A$28,'Kraken Trades'!$A$2:$A$28,"--",0) -> TS6ESC-QJCTE-7REB62 | Q29: =_xlfn.XLOOKUP(G29,'Kraken Trades'!$A$2:$A$28,'Kraken Trades'!$B$2:$B$28,"--",0) -> OVMH6P-VMU7P-E44AOJ | R29: =_xlfn.XLOOKUP(G29,'Kraken Trades'!$A$2:$A$28,'Kraken Trades'!$C$2:$C$28,"--",0) -> XRPGBP | S29: =_xlfn.XLOOKUP(G29,'Kraken Trades'!$A$2:$A$28,'Kraken Trades'!$D$2:$D$28,"--",0) -> 0.0046458333 | T29: =_xlfn.XLOOKUP(G29,'Kraken Trades'!$A$2:$A$28,'Kraken Trades'!$E$2:$E$28,"--",0) -> buy | U29: =_xlfn.XLOOKUP(G29,'Kraken Trades'!$A$2:$A$28,'Kraken Trades'!$F$2:$F$28,"--",0) -> market | V29: =_xlfn.XLOOKUP(G29,'Kraken Trades'!$A$2:$A$28,'Kraken Trades'!$G$2:$G$28,"--",0) -> 0.33092 | W29: =_xlfn.XLOOKUP(G29,'Kraken Trades'!$A$2:$A$28,'Kraken Trades'!$H$2:$H$28,"--",0) -> 175.3876 | X29: =_xlfn.XLOOKUP(G29,'Kraken Trades'!$A$2:$A$28,'Kraken Trades'!$I$2:$I$28,"--",0) -> 0.45600776 | Y29: =_xlfn.XLOOKUP(G29,'Kraken Trades'!$A$2:$A$28,'Kraken Trades'!$J$2:$J$28,"--",0) -> 530 | Z29: =_xlfn.XLOOKUP(G29,'Kraken Trades'!$A$2:$A$28,'Kraken Trades'!$K$2:$K$28,"--",0) -> 0 | AA29: =_xlfn.XLOOKUP(G29,'Kraken Trades'!$A$2:$A$28,'Kraken Trades'!$L$2:$L$28,"--",0) -> initiated | AB29: =_xlfn.XLOOKUP(G29,'Kraken Trades'!$A$2:$A$28,'Kraken Trades'!$M$2:$M$28,"--",0) -> L7JNEK-NXJOR-PGHOYD,LKUCJL-B6QP6-HVTZSZ,LNTCL3-MS5IQ-JHFPLF
B30: yes | E30: =_xlfn.XLOOKUP(D30,'DEST TAGs'!$A$2:$A$5,'DEST TAGs'!$B$2:$B$5,"--",0) -> -- | F30: L7JNEK-NXJOR-PGHOYD | G30: TS6ESC-QJCTE-7REB62 | H30: 44954.504 | I30: trade | K30: currency | L30: KFEE | M30: 0 | N30: 56.51 | O30: 7485.19 | P30: =_xlfn.XLOOKUP(G30,'Kraken Trades'!$A$2:$A$28,'Kraken Trades'!$A$2:$A$28,"--",0) -> TS6ESC-QJCTE-7REB62 | Q30: =_xlfn.XLOOKUP(G30,'Kraken Trades'!$A$2:$A$28,'Kraken Trades'!$B$2:$B$28,"--",0) -> OVMH6P-VMU7P-E44AOJ | R30: =_xlfn.XLOOKUP(G30,'Kraken Trades'!$A$2:$A$28,'Kraken Trades'!$C$2:$C$28,"--",0) -> XRPGBP | S30: =_xlfn.XLOOKUP(G30,'Kraken Trades'!$A$2:$A$28,'Kraken Trades'!$D$2:$D$28,"--",0) -> 0.0046458333 | T30: =_xlfn.XLOOKUP(G30,'Kraken Trades'!$A$2:$A$28,'Kraken Trades'!$E$2:$E$28,"--",0) -> buy | U30: =_xlfn.XLOOKUP(G30,'Kraken Trades'!$A$2:$A$28,'Kraken Trades'!$F$2:$F$28,"--",0) -> market | V30: =_xlfn.XLOOKUP(G30,'Kraken Trades'!$A$2:$A$28,'Kraken Trades'!$G$2:$G$28,"--",0) -> 0.33092 | W30: =_xlfn.XLOOKUP(G30,'Kraken Trades'!$A$2:$A$28,'Kraken Trades'!$H$2:$H$28,"--",0) -> 175.3876 | X30: =_xlfn.XLOOKUP(G30,'Kraken Trades'!$A$2:$A$28,'Kraken Trades'!$I$2:$I$28,"--",0) -> 0.45600776 | Y30: =_xlfn.XLOOKUP(G30,'Kraken Trades'!$A$2:$A$28,'Kraken Trades'!$J$2:$J$28,"--",0) -> 530 | Z30: =_xlfn.XLOOKUP(G30,'Kraken Trades'!$A$2:$A$28,'Kraken Trades'!$K$2:$K$28,"--",0) -> 0 | AA30: =_xlfn.XLOOKUP(G30,'Kraken Trades'!$A$2:$A$28,'Kraken Trades'!$L$2:$L$28,"--",0) -> initiated | AB30: =_xlfn.XLOOKUP(G30,'Kraken Trades'!$A$2:$A$28,'Kraken Trades'!$M$2:$M$28,"--",0) -> L7JNEK-NXJOR-PGHOYD,LKUCJL-B6QP6-HVTZSZ,LNTCL3-MS5IQ-JHFPLF
B31: yes | E31: =_xlfn.XLOOKUP(D31,'DEST TAGs'!$A$2:$A$5,'DEST TAGs'!$B$2:$B$5,"--",0) -> -- | G31: AIBFEVW-VQSPR2-XZQSSP | H31: 44954.505 | I31: withdrawal | K31: currency | L31: XXRP | M31: -530 | N31: 0.02 | P31: =_xlfn.XLOOKUP(G31,'Kraken Trades'!$A$2:$A$28,'Kraken Trades'!$A$2:$A$28,"--",0) -> -- | Q31: =_xlfn.XLOOKUP(G31,'Kraken Trades'!$A$2:$A$28,'Kraken Trades'!$B$2:$B$28,"--",0) -> -- | R31: =_xlfn.XLOOKUP(G31,'Kraken Trades'!$A$2:$A$28,'Kraken Trades'!$C$2:$C$28,"--",0) -> -- | S31: =_xlfn.XLOOKUP(G31,'Kraken Trades'!$A$2:$A$28,'Kraken Trades'!$D$2:$D$28,"--",0) -> -- | T31: =_xlfn.XLOOKUP(G31,'Kraken Trades'!$A$2:$A$28,'Kraken Trades'!$E$2:$E$28,"--",0) -> -- | U31: =_xlfn.XLOOKUP(G31,'Kraken Trades'!$A$2:$A$28,'Kraken Trades'!$F$2:$F$28,"--",0) -> -- | V31: =_xlfn.XLOOKUP(G31,'Kraken Trades'!$A$2:$A$28,'Kraken Trades'!$G$2:$G$28,"--",0) -> -- | W31: =_xlfn.XLOOKUP(G31,'Kraken Trades'!$A$2:$A$28,'Kraken Trades'!$H$2:$H$28,"--",0) -> -- | X31: =_xlfn.XLOOKUP(G31,'Kraken Trades'!$A$2:$A$28,'Kraken Trades'!$I$2:$I$28,"--",0) -> -- | Y31: =_xlfn.XLOOKUP(G31,'Kraken Trades'!$A$2:$A$28,'Kraken Trades'!$J$2:$J$28,"--",0) -> -- | Z31: =_xlfn.XLOOKUP(G31,'Kraken Trades'!$A$2:$A$28,'Kraken Trades'!$K$2:$K$28,"--",0) -> -- | AA31: =_xlfn.XLOOKUP(G31,'Kraken Trades'!$A$2:$A$28,'Kraken Trades'!$L$2:$L$28,"--",0) -> -- | AB31: =_xlfn.XLOOKUP(G31,'Kraken Trades'!$A$2:$A$28,'Kraken Trades'!$M$2:$M$28,"--",0) -> --
B32: yes | E32: =_xlfn.XLOOKUP(D32,'DEST TAGs'!$A$2:$A$5,'DEST TAGs'!$B$2:$B$5,"--",0) -> -- | F32: LPQTWZ-2JQVI-SCLWMP | G32: AIBFEVW-VQSPR2-XZQSSP | H32: 44954.506 | I32: withdrawal | K32: currency | L32: XXRP | M32: -530 | N32: 0.02 | O32: 0.90944334 | P32: =_xlfn.XLOOKUP(G32,'Kraken Trades'!$A$2:$A$28,'Kraken Trades'!$A$2:$A$28,"--",0) -> -- | Q32: =_xlfn.XLOOKUP(G32,'Kraken Trades'!$A$2:$A$28,'Kraken Trades'!$B$2:$B$28,"--",0) -> -- | R32: =_xlfn.XLOOKUP(G32,'Kraken Trades'!$A$2:$A$28,'Kraken Trades'!$C$2:$C$28,"--",0) -> -- | S32: =_xlfn.XLOOKUP(G32,'Kraken Trades'!$A$2:$A$28,'Kraken Trades'!$D$2:$D$28,"--",0) -> -- | T32: =_xlfn.XLOOKUP(G32,'Kraken Trades'!$A$2:$A$28,'Kraken Trades'!$E$2:$E$28,"--",0) -> -- | U32: =_xlfn.XLOOKUP(G32,'Kraken Trades'!$A$2:$A$28,'Kraken Trades'!$F$2:$F$28,"--",0) -> -- | V32: =_xlfn.XLOOKUP(G32,'Kraken Trades'!$A$2:$A$28,'Kraken Trades'!$G$2:$G$28,"--",0) -> -- | W32: =_xlfn.XLOOKUP(G32,'Kraken Trades'!$A$2:$A$28,'Kraken Trades'!$H$2:$H$28,"--",0) -> -- | X32: =_xlfn.XLOOKUP(G32,'Kraken Trades'!$A$2:$A$28,'Kraken Trades'!$I$2:$I$28,"--",0) -> -- | Y32: =_xlfn.XLOOKUP(G32,'Kraken Trades'!$A$2:$A$28,'Kraken Trades'!$J$2:$J$28,"--",0) -> -- | Z32: =_xlfn.XLOOKUP(G32,'Kraken Trades'!$A$2:$A$28,'Kraken Trades'!$K$2:$K$28,"--",0) -> -- | AA32: =_xlfn.XLOOKUP(G32,'Kraken Trades'!$A$2:$A$28,'Kraken Trades'!$L$2:$L$28,"--",0) -> -- | AB32: =_xlfn.XLOOKUP(G32,'Kraken Trades'!$A$2:$A$28,'Kraken Trades'!$M$2:$M$28,"--",0) -> --
B33: yes | E33: =_xlfn.XLOOKUP(D33,'DEST TAGs'!$A$2:$A$5,'DEST TAGs'!$B$2:$B$5,"--",0) -> -- | G33: QYPBDDK-QJQ5AO-UIAHOE | H33: 44971.647 | I33: deposit | K33: currency | L33: ZGBP | M33: 675 | N33: 0 | P33: =_xlfn.XLOOKUP(G33,'Kraken Trades'!$A$2:$A$28,'Kraken Trades'!$A$2:$A$28,"--",0) -> -- | Q33: =_xlfn.XLOOKUP(G33,'Kraken Trades'!$A$2:$A$28,'Kraken Trades'!$B$2:$B$28,"--",0) -> -- | R33: =_xlfn.XLOOKUP(G33,'Kraken Trades'!$A$2:$A$28,'Kraken Trades'!$C$2:$C$28,"--",0) -> -- | S33: =_xlfn.XLOOKUP(G33,'Kraken Trades'!$A$2:$A$28,'Kraken Trades'!$D$2:$D$28,"--",0) -> -- | T33: =_xlfn.XLOOKUP(G33,'Kraken Trades'!$A$2:$A$28,'Kraken Trades'!$E$2:$E$28,"--",0) -> -- | U33: =_xlfn.XLOOKUP(G33,'Kraken Trades'!$A$2:$A$28,'Kraken Trades'!$F$2:$F$28,"--",0) -> -- | V33: =_xlfn.XLOOKUP(G33,'Kraken Trades'!$A$2:$A$28,'Kraken Trades'!$G$2:$G$28,"--",0) -> -- | W33: =_xlfn.XLOOKUP(G33,'Kraken Trades'!$A$2:$A$28,'Kraken Trades'!$H$2:$H$28,"--",0) -> -- | X33: =_xlfn.XLOOKUP(G33,'Kraken Trades'!$A$2:$A$28,'Kraken Trades'!$I$2:$I$28,"--",0) -> -- | Y33: =_xlfn.XLOOKUP(G33,'Kraken Trades'!$A$2:$A$28,'Kraken Trades'!$J$2:$J$28,"--",0) -> -- | Z33: =_xlfn.XLOOKUP(G33,'Kraken Trades'!$A$2:$A$28,'Kraken Trades'!$K$2:$K$28,"--",0) -> -- | AA33: =_xlfn.XLOOKUP(G33,'Kraken Trades'!$A$2:$A$28,'Kraken Trades'!$L$2:$L$28,"--",0) -> -- | AB33: =_xlfn.XLOOKUP(G33,'Kraken Trades'!$A$2:$A$28,'Kraken Trades'!$M$2:$M$28,"--",0) -> --
B34: yes | E34: =_xlfn.XLOOKUP(D34,'DEST TAGs'!$A$2:$A$5,'DEST TAGs'!$B$2:$B$5,"--",0) -> -- | F34: LJDRTG-VVQ57-QCRY3G | G34: QYPBDDK-QJQ5AO-UIAHOE | H34: 44971.688 | I34: deposit | K34: currency | L34: ZGBP | M34: 675 | N34: 0 | O34: 676.0379 | P34: =_xlfn.XLOOKUP(G34,'Kraken Trades'!$A$2:$A$28,'Kraken Trades'!$A$2:$A$28,"--",0) -> -- | Q34: =_xlfn.XLOOKUP(G34,'Kraken Trades'!$A$2:$A$28,'Kraken Trades'!$B$2:$B$28,"--",0) -> -- | R34: =_xlfn.XLOOKUP(G34,'Kraken Trades'!$A$2:$A$28,'Kraken Trades'!$C$2:$C$28,"--",0) -> -- | S34: =_xlfn.XLOOKUP(G34,'Kraken Trades'!$A$2:$A$28,'Kraken Trades'!$D$2:$D$28,"--",0) -> -- | T34: =_xlfn.XLOOKUP(G34,'Kraken Trades'!$A$2:$A$28,'Kraken Trades'!$E$2:$E$28,"--",0) -> -- | U34: =_xlfn.XLOOKUP(G34,'Kraken Trades'!$A$2:$A$28,'Kraken Trades'!$F$2:$F$28,"--",0) -> -- | V34: =_xlfn.XLOOKUP(G34,'Kraken Trades'!$A$2:$A$28,'Kraken Trades'!$G$2:$G$28,"--",0) -> -- | W34: =_xlfn.XLOOKUP(G34,'Kraken Trades'!$A$2:$A$28,'Kraken Trades'!$H$2:$H$28,"--",0) -> -- | X34: =_xlfn.XLOOKUP(G34,'Kraken Trades'!$A$2:$A$28,'Kraken Trades'!$I$2:$I$28,"--",0) -> -- | Y34: =_xlfn.XLOOKUP(G34,'Kraken Trades'!$A$2:$A$28,'Kraken Trades'!$J$2:$J$28,"--",0) -> -- | Z34: =_xlfn.XLOOKUP(G34,'Kraken Trades'!$A$2:$A$28,'Kraken Trades'!$K$2:$K$28,"--",0) -> -- | AA34: =_xlfn.XLOOKUP(G34,'Kraken Trades'!$A$2:$A$28,'Kraken Trades'!$L$2:$L$28,"--",0) -> -- | AB34: =_xlfn.XLOOKUP(G34,'Kraken Trades'!$A$2:$A$28,'Kraken Trades'!$M$2:$M$28,"--",0) -> --
B35: yes | E35: =_xlfn.XLOOKUP(D35,'DEST TAGs'!$A$2:$A$5,'DEST TAGs'!$B$2:$B$5,"--",0) -> -- | F35: LP4NHA-4C2MD-2TNAQM | G35: T2M2QR-PKI5J-Y5JL6X | H35: 44971.699 | I35: trade | K35: currency | L35: ZGBP | M35: -675.476 | N35: 0 | O35: 0.5619 | P35: =_xlfn.XLOOKUP(G35,'Kraken Trades'!$A$2:$A$28,'Kraken Trades'!$A$2:$A$28,"--",0) -> T2M2QR-PKI5J-Y5JL6X | Q35: =_xlfn.XLOOKUP(G35,'Kraken Trades'!$A$2:$A$28,'Kraken Trades'!$B$2:$B$28,"--",0) -> OZ72GI-QOAPH-LJIKPV | R35: =_xlfn.XLOOKUP(G35,'Kraken Trades'!$A$2:$A$28,'Kraken Trades'!$C$2:$C$28,"--",0) -> XRPGBP | S35: =_xlfn.XLOOKUP(G35,'Kraken Trades'!$A$2:$A$28,'Kraken Trades'!$D$2:$D$28,"--",0) -> 0.0331875 | T35: =_xlfn.XLOOKUP(G35,'Kraken Trades'!$A$2:$A$28,'Kraken Trades'!$E$2:$E$28,"--",0) -> buy | U35: =_xlfn.XLOOKUP(G35,'Kraken Trades'!$A$2:$A$28,'Kraken Trades'!$F$2:$F$28,"--",0) -> market | V35: =_xlfn.XLOOKUP(G35,'Kraken Trades'!$A$2:$A$28,'Kraken Trades'!$G$2:$G$28,"--",0) -> 0.30773392 | W35: =_xlfn.XLOOKUP(G35,'Kraken Trades'!$A$2:$A$28,'Kraken Trades'!$H$2:$H$28,"--",0) -> 675.47596 | X35: =_xlfn.XLOOKUP(G35,'Kraken Trades'!$A$2:$A$28,'Kraken Trades'!$I$2:$I$28,"--",0) -> 1.7562375 | Y35: =_xlfn.XLOOKUP(G35,'Kraken Trades'!$A$2:$A$28,'Kraken Trades'!$J$2:$J$28,"--",0) -> 2195 | Z35: =_xlfn.XLOOKUP(G35,'Kraken Trades'!$A$2:$A$28,'Kraken Trades'!$K$2:$K$28,"--",0) -> 0 | AA35: =_xlfn.XLOOKUP(G35,'Kraken Trades'!$A$2:$A$28,'Kraken Trades'!$L$2:$L$28,"--",0) -> initiated | AB35: =_xlfn.XLOOKUP(G35,'Kraken Trades'!$A$2:$A$28,'Kraken Trades'!$M$2:$M$28,"--",0) -> LZGQC7-CBHKO-BKBP4U,LWHU3C-IQK4G-3GOKIF,LP4NHA-4C2MD-2TNAQM
B36: yes | E36: =_xlfn.XLOOKUP(D36,'DEST TAGs'!$A$2:$A$5,'DEST TAGs'!$B$2:$B$5,"--",0) -> -- | F36: LWHU3C-IQK4G-3GOKIF | G36: T2M2QR-PKI5J-Y5JL6X | H36: 44971.699 | I36: trade | K36: currency | L36: XXRP | M36: 2195 | N36: 0 | O36: 2195.9094 | P36: =_xlfn.XLOOKUP(G36,'Kraken Trades'!$A$2:$A$28,'Kraken Trades'!$A$2:$A$28,"--",0) -> T2M2QR-PKI5J-Y5JL6X | Q36: =_xlfn.XLOOKUP(G36,'Kraken Trades'!$A$2:$A$28,'Kraken Trades'!$B$2:$B$28,"--",0) -> OZ72GI-QOAPH-LJIKPV | R36: =_xlfn.XLOOKUP(G36,'Kraken Trades'!$A$2:$A$28,'Kraken Trades'!$C$2:$C$28,"--",0) -> XRPGBP | S36: =_xlfn.XLOOKUP(G36,'Kraken Trades'!$A$2:$A$28,'Kraken Trades'!$D$2:$D$28,"--",0) -> 0.0331875 | T36: =_xlfn.XLOOKUP(G36,'Kraken Trades'!$A$2:$A$28,'Kraken Trades'!$E$2:$E$28,"--",0) -> buy | U36: =_xlfn.XLOOKUP(G36,'Kraken Trades'!$A$2:$A$28,'Kraken Trades'!$F$2:$F$28,"--",0) -> market | V36: =_xlfn.XLOOKUP(G36,'Kraken Trades'!$A$2:$A$28,'Kraken Trades'!$G$2:$G$28,"--",0) -> 0.30773392 | W36: =_xlfn.XLOOKUP(G36,'Kraken Trades'!$A$2:$A$28,'Kraken Trades'!$H$2:$H$28,"--",0) -> 675.47596 | X36: =_xlfn.XLOOKUP(G36,'Kraken Trades'!$A$2:$A$28,'Kraken Trades'!$I$2:$I$28,"--",0) -> 1.7562375 | Y36: =_xlfn.XLOOKUP(G36,'Kraken Trades'!$A$2:$A$28,'Kraken Trades'!$J$2:$J$28,"--",0) -> 2195 | Z36: =_xlfn.XLOOKUP(G36,'Kraken Trades'!$A$2:$A$28,'Kraken Trades'!$K$2:$K$28,"--",0) -> 0 | AA36: =_xlfn.XLOOKUP(G36,'Kraken Trades'!$A$2:$A$28,'Kraken Trades'!$L$2:$L$28,"--",0) -> initiated | AB36: =_xlfn.XLOOKUP(G36,'Kraken Trades'!$A$2:$A$28,'Kraken Trades'!$M$2:$M$28,"--",0) -> LZGQC7-CBHKO-BKBP4U,LWHU3C-IQK4G-3GOKIF,LP4NHA-4C2MD-2TNAQM
B37: yes | E37: =_xlfn.XLOOKUP(D37,'DEST TAGs'!$A$2:$A$5,'DEST TAGs'!$B$2:$B$5,"--",0) -> -- | F37: LZGQC7-CBHKO-BKBP4U | G37: T2M2QR-PKI5J-Y5JL6X | H37: 44971.699 | I37: trade | K37: currency | L37: KFEE | M37: 0 | N37: 213.46 | O37: 7271.73 | P37: =_xlfn.XLOOKUP(G37,'Kraken Trades'!$A$2:$A$28,'Kraken Trades'!$A$2:$A$28,"--",0) -> T2M2QR-PKI5J-Y5JL6X | Q37: =_xlfn.XLOOKUP(G37,'Kraken Trades'!$A$2:$A$28,'Kraken Trades'!$B$2:$B$28,"--",0) -> OZ72GI-QOAPH-LJIKPV | R37: =_xlfn.XLOOKUP(G37,'Kraken Trades'!$A$2:$A$28,'Kraken Trades'!$C$2:$C$28,"--",0) -> XRPGBP | S37: =_xlfn.XLOOKUP(G37,'Kraken Trades'!$A$2:$A$28,'Kraken Trades'!$D$2:$D$28,"--",0) -> 0.0331875 | T37: =_xlfn.XLOOKUP(G37,'Kraken Trades'!$A$2:$A$28,'Kraken Trades'!$E$2:$E$28,"--",0) -> buy | U37: =_xlfn.XLOOKUP(G37,'Kraken Trades'!$A$2:$A$28,'Kraken Trades'!$F$2:$F$28,"--",0) -> market | V37: =_xlfn.XLOOKUP(G37,'Kraken Trades'!$A$2:$A$28,'Kraken Trades'!$G$2:$G$28,"--",0) -> 0.30773392 | W37: =_xlfn.XLOOKUP(G37,'Kraken Trades'!$A$2:$A$28,'Kraken Trades'!$H$2:$H$28,"--",0) -> 675.47596 | X37: =_xlfn.XLOOKUP(G37,'Kraken Trades'!$A$2:$A$28,'Kraken Trades'!$I$2:$I$28,"--",0) -> 1.7562375 | Y37: =_xlfn.XLOOKUP(G37,'Kraken Trades'!$A$2:$A$28,'Kraken Trades'!$J$2:$J$28,"--",0) -> 2195 | Z37: =_xlfn.XLOOKUP(G37,'Kraken Trades'!$A$2:$A$28,'Kraken Trades'!$K$2:$K$28,"--",0) -> 0 | AA37: =_xlfn.XLOOKUP(G37,'Kraken Trades'!$A$2:$A$28,'Kraken Trades'!$L$2:$L$28,"--",0) -> initiated | AB37: =_xlfn.XLOOKUP(G37,'Kraken Trades'!$A$2:$A$28,'Kraken Trades'!$M$2:$M$28,"--",0) -> LZGQC7-CBHKO-BKBP4U,LWHU3C-IQK4G-3GOKIF,LP4NHA-4C2MD-2TNAQM
B38: yes | E38: =_xlfn.XLOOKUP(D38,'DEST TAGs'!$A$2:$A$5,'DEST TAGs'!$B$2:$B$5,"--",0) -> -- | G38: AIBAXRI-XIDZXI-VHVAML | H38: 44971.7 | I38: withdrawal | K38: currency | L38: XXRP | M38: -2195 | N38: 0.02 | P38: =_xlfn.XLOOKUP(G38,'Kraken Trades'!$A$2:$A$28,'Kraken Trades'!$A$2:$A$28,"--",0) -> -- | Q38: =_xlfn.XLOOKUP(G38,'Kraken Trades'!$A$2:$A$28,'Kraken Trades'!$B$2:$B$28,"--",0) -> -- | R38: =_xlfn.XLOOKUP(G38,'Kraken Trades'!$A$2:$A$28,'Kraken Trades'!$C$2:$C$28,"--",0) -> -- | S38: =_xlfn.XLOOKUP(G38,'Kraken Trades'!$A$2:$A$28,'Kraken Trades'!$D$2:$D$28,"--",0) -> -- | T38: =_xlfn.XLOOKUP(G38,'Kraken Trades'!$A$2:$A$28,'Kraken Trades'!$E$2:$E$28,"--",0) -> -- | U38: =_xlfn.XLOOKUP(G38,'Kraken Trades'!$A$2:$A$28,'Kraken Trades'!$F$2:$F$28,"--",0) -> -- | V38: =_xlfn.XLOOKUP(G38,'Kraken Trades'!$A$2:$A$28,'Kraken Trades'!$G$2:$G$28,"--",0) -> -- | W38: =_xlfn.XLOOKUP(G38,'Kraken Trades'!$A$2:$A$28,'Kraken Trades'!$H$2:$H$28,"--",0) -> -- | X38: =_xlfn.XLOOKUP(G38,'Kraken Trades'!$A$2:$A$28,'Kraken Trades'!$I$2:$I$28,"--",0) -> -- | Y38: =_xlfn.XLOOKUP(G38,'Kraken Trades'!$A$2:$A$28,'Kraken Trades'!$J$2:$J$28,"--",0) -> -- | Z38: =_xlfn.XLOOKUP(G38,'Kraken Trades'!$A$2:$A$28,'Kraken Trades'!$K$2:$K$28,"--",0) -> -- | AA38: =_xlfn.XLOOKUP(G38,'Kraken Trades'!$A$2:$A$28,'Kraken Trades'!$L$2:$L$28,"--",0) -> -- | AB38: =_xlfn.XLOOKUP(G38,'Kraken Trades'!$A$2:$A$28,'Kraken Trades'!$M$2:$M$28,"--",0) -> --
B39: yes | E39: =_xlfn.XLOOKUP(D39,'DEST TAGs'!$A$2:$A$5,'DEST TAGs'!$B$2:$B$5,"--",0) -> -- | F39: LSYTBL-JAZYT-FCGPI5 | G39: AIBAXRI-XIDZXI-VHVAML | H39: 44971.701 | I39: withdrawal | K39: currency | L39: XXRP | M39: -2195 | N39: 0.02 | O39: 0.88944334 | P39: =_xlfn.XLOOKUP(G39,'Kraken Trades'!$A$2:$A$28,'Kraken Trades'!$A$2:$A$28,"--",0) -> -- | Q39: =_xlfn.XLOOKUP(G39,'Kraken Trades'!$A$2:$A$28,'Kraken Trades'!$B$2:$B$28,"--",0) -> -- | R39: =_xlfn.XLOOKUP(G39,'Kraken Trades'!$A$2:$A$28,'Kraken Trades'!$C$2:$C$28,"--",0) -> -- | S39: =_xlfn.XLOOKUP(G39,'Kraken Trades'!$A$2:$A$28,'Kraken Trades'!$D$2:$D$28,"--",0) -> -- | T39: =_xlfn.XLOOKUP(G39,'Kraken Trades'!$A$2:$A$28,'Kraken Trades'!$E$2:$E$28,"--",0) -> -- | U39: =_xlfn.XLOOKUP(G39,'Kraken Trades'!$A$2:$A$28,'Kraken Trades'!$F$2:$F$28,"--",0) -> -- | V39: =_xlfn.XLOOKUP(G39,'Kraken Trades'!$A$2:$A$28,'Kraken Trades'!$G$2:$G$28,"--",0) -> -- | W39: =_xlfn.XLOOKUP(G39,'Kraken Trades'!$A$2:$A$28,'Kraken Trades'!$H$2:$H$28,"--",0) -> -- | X39: =_xlfn.XLOOKUP(G39,'Kraken Trades'!$A$2:$A$28,'Kraken Trades'!$I$2:$I$28,"--",0) -> -- | Y39: =_xlfn.XLOOKUP(G39,'Kraken Trades'!$A$2:$A$28,'Kraken Trades'!$J$2:$J$28,"--",0) -> -- | Z39: =_xlfn.XLOOKUP(G39,'Kraken Trades'!$A$2:$A$28,'Kraken Trades'!$K$2:$K$28,"--",0) -> -- | AA39: =_xlfn.XLOOKUP(G39,'Kraken Trades'!$A$2:$A$28,'Kraken Trades'!$L$2:$L$28,"--",0) -> -- | AB39: =_xlfn.XLOOKUP(G39,'Kraken Trades'!$A$2:$A$28,'Kraken Trades'!$M$2:$M$28,"--",0) -> --
B40: yes | E40: =_xlfn.XLOOKUP(D40,'DEST TAGs'!$A$2:$A$5,'DEST TAGs'!$B$2:$B$5,"--",0) -> -- | G40: QYP5N2O-NUWNOF-TPFQUO | H40: 44986.366 | I40: deposit | K40: currency | L40: ZGBP | M40: 450 | N40: 0 | P40: =_xlfn.XLOOKUP(G40,'Kraken Trades'!$A$2:$A$28,'Kraken Trades'!$A$2:$A$28,"--",0) -> -- | Q40: =_xlfn.XLOOKUP(G40,'Kraken Trades'!$A$2:$A$28,'Kraken Trades'!$B$2:$B$28,"--",0) -> -- | R40: =_xlfn.XLOOKUP(G40,'Kraken Trades'!$A$2:$A$28,'Kraken Trades'!$C$2:$C$28,"--",0) -> -- | S40: =_xlfn.XLOOKUP(G40,'Kraken Trades'!$A$2:$A$28,'Kraken Trades'!$D$2:$D$28,"--",0) -> -- | T40: =_xlfn.XLOOKUP(G40,'Kraken Trades'!$A$2:$A$28,'Kraken Trades'!$E$2:$E$28,"--",0) -> -- | U40: =_xlfn.XLOOKUP(G40,'Kraken Trades'!$A$2:$A$28,'Kraken Trades'!$F$2:$F$28,"--",0) -> -- | V40: =_xlfn.XLOOKUP(G40,'Kraken Trades'!$A$2:$A$28,'Kraken Trades'!$G$2:$G$28,"--",0) -> -- | W40: =_xlfn.XLOOKUP(G40,'Kraken Trades'!$A$2:$A$28,'Kraken Trades'!$H$2:$H$28,"--",0) -> -- | X40: =_xlfn.XLOOKUP(G40,'Kraken Trades'!$A$2:$A$28,'Kraken Trades'!$I$2:$I$28,"--",0) -> -- | Y40: =_xlfn.XLOOKUP(G40,'Kraken Trades'!$A$2:$A$28,'Kraken Trades'!$J$2:$J$28,"--",0) -> -- | Z40: =_xlfn.XLOOKUP(G40,'Kraken Trades'!$A$2:$A$28,'Kraken Trades'!$K$2:$K$28,"--",0) -> -- | AA40: =_xlfn.XLOOKUP(G40,'Kraken Trades'!$A$2:$A$28,'Kraken Trades'!$L$2:$L$28,"--",0) -> -- | AB40: =_xlfn.XLOOKUP(G40,'Kraken Trades'!$A$2:$A$28,'Kraken Trades'!$M$2:$M$28,"--",0) -> --
B41: yes | E41: =_xlfn.XLOOKUP(D41,'DEST TAGs'!$A$2:$A$5,'DEST TAGs'!$B$2:$B$5,"--",0) -> -- | F41: L57AY5-KBEDW-ASROC6 | G41: QYP5N2O-NUWNOF-TPFQUO | H41: 44986.419 | I41: deposit | K41: currency | L41: ZGBP | M41: 450 | N41: 0 | O41: 450.5619 | P41: =_xlfn.XLOOKUP(G41,'Kraken Trades'!$A$2:$A$28,'Kraken Trades'!$A$2:$A$28,"--",0) -> -- | Q41: =_xlfn.XLOOKUP(G41,'Kraken Trades'!$A$2:$A$28,'Kraken Trades'!$B$2:$B$28,"--",0) -> -- | R41: =_xlfn.XLOOKUP(G41,'Kraken Trades'!$A$2:$A$28,'Kraken Trades'!$C$2:$C$28,"--",0) -> -- | S41: =_xlfn.XLOOKUP(G41,'Kraken Trades'!$A$2:$A$28,'Kraken Trades'!$D$2:$D$28,"--",0) -> -- | T41: =_xlfn.XLOOKUP(G41,'Kraken Trades'!$A$2:$A$28,'Kraken Trades'!$E$2:$E$28,"--",0) -> -- | U41: =_xlfn.XLOOKUP(G41,'Kraken Trades'!$A$2:$A$28,'Kraken Trades'!$F$2:$F$28,"--",0) -> -- | V41: =_xlfn.XLOOKUP(G41,'Kraken Trades'!$A$2:$A$28,'Kraken Trades'!$G$2:$G$28,"--",0) -> -- | W41: =_xlfn.XLOOKUP(G41,'Kraken Trades'!$A$2:$A$28,'Kraken Trades'!$H$2:$H$28,"--",0) -> -- | X41: =_xlfn.XLOOKUP(G41,'Kraken Trades'!$A$2:$A$28,'Kraken Trades'!$I$2:$I$28,"--",0) -> -- | Y41: =_xlfn.XLOOKUP(G41,'Kraken Trades'!$A$2:$A$28,'Kraken Trades'!$J$2:$J$28,"--",0) -> -- | Z41: =_xlfn.XLOOKUP(G41,'Kraken Trades'!$A$2:$A$28,'Kraken Trades'!$K$2:$K$28,"--",0) -> -- | AA41: =_xlfn.XLOOKUP(G41,'Kraken Trades'!$A$2:$A$28,'Kraken Trades'!$L$2:$L$28,"--",0) -> -- | AB41: =_xlfn.XLOOKUP(G41,'Kraken Trades'!$A$2:$A$28,'Kraken Trades'!$M$2:$M$28,"--",0) -> --
B42: yes | E42: =_xlfn.XLOOKUP(D42,'DEST TAGs'!$A$2:$A$5,'DEST TAGs'!$B$2:$B$5,"--",0) -> -- | F42: LQG5LY-EWTI6-RSHFAR | G42: TWTDYI-ASIKO-VCFX6I | H42: 44986.467 | I42: trade | K42: currency | L42: ZGBP | M42: -235.4498 | N42: 0 | O42: 215.1121 | P42: =_xlfn.XLOOKUP(G42,'Kraken Trades'!$A$2:$A$28,'Kraken Trades'!$A$2:$A$28,"--",0) -> TWTDYI-ASIKO-VCFX6I | Q42: =_xlfn.XLOOKUP(G42,'Kraken Trades'!$A$2:$A$28,'Kraken Trades'!$B$2:$B$28,"--",0) -> ORTVJB-TAVRW-O7R7BW | R42: =_xlfn.XLOOKUP(G42,'Kraken Trades'!$A$2:$A$28,'Kraken Trades'!$C$2:$C$28,"--",0) -> XRPGBP | S42: =_xlfn.XLOOKUP(G42,'Kraken Trades'!$A$2:$A$28,'Kraken Trades'!$D$2:$D$28,"--",0) -> 0.0086203704 | T42: =_xlfn.XLOOKUP(G42,'Kraken Trades'!$A$2:$A$28,'Kraken Trades'!$E$2:$E$28,"--",0) -> buy | U42: =_xlfn.XLOOKUP(G42,'Kraken Trades'!$A$2:$A$28,'Kraken Trades'!$F$2:$F$28,"--",0) -> market | V42: =_xlfn.XLOOKUP(G42,'Kraken Trades'!$A$2:$A$28,'Kraken Trades'!$G$2:$G$28,"--",0) -> 0.31604 | W42: =_xlfn.XLOOKUP(G42,'Kraken Trades'!$A$2:$A$28,'Kraken Trades'!$H$2:$H$28,"--",0) -> 235.4498 | X42: =_xlfn.XLOOKUP(G42,'Kraken Trades'!$A$2:$A$28,'Kraken Trades'!$I$2:$I$28,"--",0) -> 0.61216948 | Y42: =_xlfn.XLOOKUP(G42,'Kraken Trades'!$A$2:$A$28,'Kraken Trades'!$J$2:$J$28,"--",0) -> 745 | Z42: =_xlfn.XLOOKUP(G42,'Kraken Trades'!$A$2:$A$28,'Kraken Trades'!$K$2:$K$28,"--",0) -> 0 | AA42: =_xlfn.XLOOKUP(G42,'Kraken Trades'!$A$2:$A$28,'Kraken Trades'!$L$2:$L$28,"--",0) -> initiated | AB42: =_xlfn.XLOOKUP(G42,'Kraken Trades'!$A$2:$A$28,'Kraken Trades'!$M$2:$M$28,"--",0) -> LRNHWZ-57VHX-HWWRUW,LPEDUI-QCVOM-6NRCON,LQG5LY-EWTI6-RSHFAR
B43: yes | E43: =_xlfn.XLOOKUP(D43,'DEST TAGs'!$A$2:$A$5,'DEST TAGs'!$B$2:$B$5,"--",0) -> -- | F43: LPEDUI-QCVOM-6NRCON | G43: TWTDYI-ASIKO-VCFX6I | H43: 44986.467 | I43: trade | K43: currency | L43: XXRP | M43: 745 | N43: 0 | O43: 745.88944 | P43: =_xlfn.XLOOKUP(G43,'Kraken Trades'!$A$2:$A$28,'Kraken Trades'!$A$2:$A$28,"--",0) -> TWTDYI-ASIKO-VCFX6I | Q43: =_xlfn.XLOOKUP(G43,'Kraken Trades'!$A$2:$A$28,'Kraken Trades'!$B$2:$B$28,"--",0) -> ORTVJB-TAVRW-O7R7BW | R43: =_xlfn.XLOOKUP(G43,'Kraken Trades'!$A$2:$A$28,'Kraken Trades'!$C$2:$C$28,"--",0) -> XRPGBP | S43: =_xlfn.XLOOKUP(G43,'Kraken Trades'!$A$2:$A$28,'Kraken Trades'!$D$2:$D$28,"--",0) -> 0.0086203704 | T43: =_xlfn.XLOOKUP(G43,'Kraken Trades'!$A$2:$A$28,'Kraken Trades'!$E$2:$E$28,"--",0) -> buy | U43: =_xlfn.XLOOKUP(G43,'Kraken Trades'!$A$2:$A$28,'Kraken Trades'!$F$2:$F$28,"--",0) -> market | V43: =_xlfn.XLOOKUP(G43,'Kraken Trades'!$A$2:$A$28,'Kraken Trades'!$G$2:$G$28,"--",0) -> 0.31604 | W43: =_xlfn.XLOOKUP(G43,'Kraken Trades'!$A$2:$A$28,'Kraken Trades'!$H$2:$H$28,"--",0) -> 235.4498 | X43: =_xlfn.XLOOKUP(G43,'Kraken Trades'!$A$2:$A$28,'Kraken Trades'!$I$2:$I$28,"--",0) -> 0.61216948 | Y43: =_xlfn.XLOOKUP(G43,'Kraken Trades'!$A$2:$A$28,'Kraken Trades'!$J$2:$J$28,"--",0) -> 745 | Z43: =_xlfn.XLOOKUP(G43,'Kraken Trades'!$A$2:$A$28,'Kraken Trades'!$K$2:$K$28,"--",0) -> 0 | AA43: =_xlfn.XLOOKUP(G43,'Kraken Trades'!$A$2:$A$28,'Kraken Trades'!$L$2:$L$28,"--",0) -> initiated | AB43: =_xlfn.XLOOKUP(G43,'Kraken Trades'!$A$2:$A$28,'Kraken Trades'!$M$2:$M$28,"--",0) -> LRNHWZ-57VHX-HWWRUW,LPEDUI-QCVOM-6NRCON,LQG5LY-EWTI6-RSHFAR
B44: yes | E44: =_xlfn.XLOOKUP(D44,'DEST TAGs'!$A$2:$A$5,'DEST TAGs'!$B$2:$B$5,"--",0) -> -- | F44: LRNHWZ-57VHX-HWWRUW | G44: TWTDYI-ASIKO-VCFX6I | H44: 44986.467 | I44: trade | K44: currency | L44: KFEE | M44: 0 | N44: 73.72 | O44: 7198.01 | P44: =_xlfn.XLOOKUP(G44,'Kraken Trades'!$A$2:$A$28,'Kraken Trades'!$A$2:$A$28,"--",0) -> TWTDYI-ASIKO-VCFX6I | Q44: =_xlfn.XLOOKUP(G44,'Kraken Trades'!$A$2:$A$28,'Kraken Trades'!$B$2:$B$28,"--",0) -> ORTVJB-TAVRW-O7R7BW | R44: =_xlfn.XLOOKUP(G44,'Kraken Trades'!$A$2:$A$28,'Kraken Trades'!$C$2:$C$28,"--",0) -> XRPGBP | S44: =_xlfn.XLOOKUP(G44,'Kraken Trades'!$A$2:$A$28,'Kraken Trades'!$D$2:$D$28,"--",0) -> 0.0086203704 | T44: =_xlfn.XLOOKUP(G44,'Kraken Trades'!$A$2:$A$28,'Kraken Trades'!$E$2:$E$28,"--",0) -> buy | U44: =_xlfn.XLOOKUP(G44,'Kraken Trades'!$A$2:$A$28,'Kraken Trades'!$F$2:$F$28,"--",0) -> market | V44: =_xlfn.XLOOKUP(G44,'Kraken Trades'!$A$2:$A$28,'Kraken Trades'!$G$2:$G$28,"--",0) -> 0.31604 | W44: =_xlfn.XLOOKUP(G44,'Kraken Trades'!$A$2:$A$28,'Kraken Trades'!$H$2:$H$28,"--",0) -> 235.4498 | X44: =_xlfn.XLOOKUP(G44,'Kraken Trades'!$A$2:$A$28,'Kraken Trades'!$I$2:$I$28,"--",0) -> 0.61216948 | Y44: =_xlfn.XLOOKUP(G44,'Kraken Trades'!$A$2:$A$28,'Kraken Trades'!$J$2:$J$28,"--",0) -> 745 | Z44: =_xlfn.XLOOKUP(G44,'Kraken Trades'!$A$2:$A$28,'Kraken Trades'!$K$2:$K$28,"--",0) -> 0 | AA44: =_xlfn.XLOOKUP(G44,'Kraken Trades'!$A$2:$A$28,'Kraken Trades'!$L$2:$L$28,"--",0) -> initiated | AB44: =_xlfn.XLOOKUP(G44,'Kraken Trades'!$A$2:$A$28,'Kraken Trades'!$M$2:$M$28,"--",0) -> LRNHWZ-57VHX-HWWRUW,LPEDUI-QCVOM-6NRCON,LQG5LY-EWTI6-RSHFAR
B45: yes | E45: =_xlfn.XLOOKUP(D45,'DEST TAGs'!$A$2:$A$5,'DEST TAGs'!$B$2:$B$5,"--",0) -> -- | G45: AIBC2MA-37RPHW-GIAWXM | H45: 44986.468 | I45: withdrawal | K45: currency | L45: XXRP | M45: -745 | N45: 0.02 | P45: =_xlfn.XLOOKUP(G45,'Kraken Trades'!$A$2:$A$28,'Kraken Trades'!$A$2:$A$28,"--",0) -> -- | Q45: =_xlfn.XLOOKUP(G45,'Kraken Trades'!$A$2:$A$28,'Kraken Trades'!$B$2:$B$28,"--",0) -> -- | R45: =_xlfn.XLOOKUP(G45,'Kraken Trades'!$A$2:$A$28,'Kraken Trades'!$C$2:$C$28,"--",0) -> -- | S45: =_xlfn.XLOOKUP(G45,'Kraken Trades'!$A$2:$A$28,'Kraken Trades'!$D$2:$D$28,"--",0) -> -- | T45: =_xlfn.XLOOKUP(G45,'Kraken Trades'!$A$2:$A$28,'Kraken Trades'!$E$2:$E$28,"--",0) -> -- | U45: =_xlfn.XLOOKUP(G45,'Kraken Trades'!$A$2:$A$28,'Kraken Trades'!$F$2:$F$28,"--",0) -> -- | V45: =_xlfn.XLOOKUP(G45,'Kraken Trades'!$A$2:$A$28,'Kraken Trades'!$G$2:$G$28,"--",0) -> -- | W45: =_xlfn.XLOOKUP(G45,'Kraken Trades'!$A$2:$A$28,'Kraken Trades'!$H$2:$H$28,"--",0) -> -- | X45: =_xlfn.XLOOKUP(G45,'Kraken Trades'!$A$2:$A$28,'Kraken Trades'!$I$2:$I$28,"--",0) -> -- | Y45: =_xlfn.XLOOKUP(G45,'Kraken Trades'!$A$2:$A$28,'Kraken Trades'!$J$2:$J$28,"--",0) -> -- | Z45: =_xlfn.XLOOKUP(G45,'Kraken Trades'!$A$2:$A$28,'Kraken Trades'!$K$2:$K$28,"--",0) -> -- | AA45: =_xlfn.XLOOKUP(G45,'Kraken Trades'!$A$2:$A$28,'Kraken Trades'!$L$2:$L$28,"--",0) -> -- | AB45: =_xlfn.XLOOKUP(G45,'Kraken Trades'!$A$2:$A$28,'Kraken Trades'!$M$2:$M$28,"--",0) -> --
B46: yes | E46: =_xlfn.XLOOKUP(D46,'DEST TAGs'!$A$2:$A$5,'DEST TAGs'!$B$2:$B$5,"--",0) -> -- | F46: L6CQJL-6WC7R-HFAEGK | G46: TC3PHC-GCMVA-E6STJY | H46: 44986.468 | I46: trade | K46: currency | L46: ZGBP | M46: -215.0432 | N46: 0 | O46: 0.0689 | P46: =_xlfn.XLOOKUP(G46,'Kraken Trades'!$A$2:$A$28,'Kraken Trades'!$A$2:$A$28,"--",0) -> TC3PHC-GCMVA-E6STJY | Q46: =_xlfn.XLOOKUP(G46,'Kraken Trades'!$A$2:$A$28,'Kraken Trades'!$B$2:$B$28,"--",0) -> O3NVLB-QN7EY-FMQ6CE | R46: =_xlfn.XLOOKUP(G46,'Kraken Trades'!$A$2:$A$28,'Kraken Trades'!$C$2:$C$28,"--",0) -> XRPGBP | S46: =_xlfn.XLOOKUP(G46,'Kraken Trades'!$A$2:$A$28,'Kraken Trades'!$D$2:$D$28,"--",0) -> 0.010349537 | T46: =_xlfn.XLOOKUP(G46,'Kraken Trades'!$A$2:$A$28,'Kraken Trades'!$E$2:$E$28,"--",0) -> buy | U46: =_xlfn.XLOOKUP(G46,'Kraken Trades'!$A$2:$A$28,'Kraken Trades'!$F$2:$F$28,"--",0) -> market | V46: =_xlfn.XLOOKUP(G46,'Kraken Trades'!$A$2:$A$28,'Kraken Trades'!$G$2:$G$28,"--",0) -> 0.31624 | W46: =_xlfn.XLOOKUP(G46,'Kraken Trades'!$A$2:$A$28,'Kraken Trades'!$H$2:$H$28,"--",0) -> 215.0432 | X46: =_xlfn.XLOOKUP(G46,'Kraken Trades'!$A$2:$A$28,'Kraken Trades'!$I$2:$I$28,"--",0) -> 0.55911232 | Y46: =_xlfn.XLOOKUP(G46,'Kraken Trades'!$A$2:$A$28,'Kraken Trades'!$J$2:$J$28,"--",0) -> 680 | Z46: =_xlfn.XLOOKUP(G46,'Kraken Trades'!$A$2:$A$28,'Kraken Trades'!$K$2:$K$28,"--",0) -> 0 | AA46: =_xlfn.XLOOKUP(G46,'Kraken Trades'!$A$2:$A$28,'Kraken Trades'!$L$2:$L$28,"--",0) -> initiated | AB46: =_xlfn.XLOOKUP(G46,'Kraken Trades'!$A$2:$A$28,'Kraken Trades'!$M$2:$M$28,"--",0) -> LVPZY3-Q45Q7-LMRC3C,LWLOFX-MMUGN-TTVA5O,L6CQJL-6WC7R-HFAEGK
B47: yes | E47: =_xlfn.XLOOKUP(D47,'DEST TAGs'!$A$2:$A$5,'DEST TAGs'!$B$2:$B$5,"--",0) -> -- | F47: LWLOFX-MMUGN-TTVA5O | G47: TC3PHC-GCMVA-E6STJY | H47: 44986.468 | I47: trade | K47: currency | L47: XXRP | M47: 680 | N47: 0 | O47: 1425.8894 | P47: =_xlfn.XLOOKUP(G47,'Kraken Trades'!$A$2:$A$28,'Kraken Trades'!$A$2:$A$28,"--",0) -> TC3PHC-GCMVA-E6STJY | Q47: =_xlfn.XLOOKUP(G47,'Kraken Trades'!$A$2:$A$28,'Kraken Trades'!$B$2:$B$28,"--",0) -> O3NVLB-QN7EY-FMQ6CE | R47: =_xlfn.XLOOKUP(G47,'Kraken Trades'!$A$2:$A$28,'Kraken Trades'!$C$2:$C$28,"--",0) -> XRPGBP | S47: =_xlfn.XLOOKUP(G47,'Kraken Trades'!$A$2:$A$28,'Kraken Trades'!$D$2:$D$28,"--",0) -> 0.010349537 | T47: =_xlfn.XLOOKUP(G47,'Kraken Trades'!$A$2:$A$28,'Kraken Trades'!$E$2:$E$28,"--",0) -> buy | U47: =_xlfn.XLOOKUP(G47,'Kraken Trades'!$A$2:$A$28,'Kraken Trades'!$F$2:$F$28,"--",0) -> market | V47: =_xlfn.XLOOKUP(G47,'Kraken Trades'!$A$2:$A$28,'Kraken Trades'!$G$2:$G$28,"--",0) -> 0.31624 | W47: =_xlfn.XLOOKUP(G47,'Kraken Trades'!$A$2:$A$28,'Kraken Trades'!$H$2:$H$28,"--",0) -> 215.0432 | X47: =_xlfn.XLOOKUP(G47,'Kraken Trades'!$A$2:$A$28,'Kraken Trades'!$I$2:$I$28,"--",0) -> 0.55911232 | Y47: =_xlfn.XLOOKUP(G47,'Kraken Trades'!$A$2:$A$28,'Kraken Trades'!$J$2:$J$28,"--",0) -> 680 | Z47: =_xlfn.XLOOKUP(G47,'Kraken Trades'!$A$2:$A$28,'Kraken Trades'!$K$2:$K$28,"--",0) -> 0 | AA47: =_xlfn.XLOOKUP(G47,'Kraken Trades'!$A$2:$A$28,'Kraken Trades'!$L$2:$L$28,"--",0) -> initiated | AB47: =_xlfn.XLOOKUP(G47,'Kraken Trades'!$A$2:$A$28,'Kraken Trades'!$M$2:$M$28,"--",0) -> LVPZY3-Q45Q7-LMRC3C,LWLOFX-MMUGN-TTVA5O,L6CQJL-6WC7R-HFAEGK
B48: yes | E48: =_xlfn.XLOOKUP(D48,'DEST TAGs'!$A$2:$A$5,'DEST TAGs'!$B$2:$B$5,"--",0) -> -- | F48: LVPZY3-Q45Q7-LMRC3C | G48: TC3PHC-GCMVA-E6STJY | H48: 44986.468 | I48: trade | K48: currency | L48: KFEE | M48: 0 | N48: 67.32 | O48: 7130.69 | P48: =_xlfn.XLOOKUP(G48,'Kraken Trades'!$A$2:$A$28,'Kraken Trades'!$A$2:$A$28,"--",0) -> TC3PHC-GCMVA-E6STJY | Q48: =_xlfn.XLOOKUP(G48,'Kraken Trades'!$A$2:$A$28,'Kraken Trades'!$B$2:$B$28,"--",0) -> O3NVLB-QN7EY-FMQ6CE | R48: =_xlfn.XLOOKUP(G48,'Kraken Trades'!$A$2:$A$28,'Kraken Trades'!$C$2:$C$28,"--",0) -> XRPGBP | S48: =_xlfn.XLOOKUP(G48,'Kraken Trades'!$A$2:$A$28,'Kraken Trades'!$D$2:$D$28,"--",0) -> 0.010349537 | T48: =_xlfn.XLOOKUP(G48,'Kraken Trades'!$A$2:$A$28,'Kraken Trades'!$E$2:$E$28,"--",0) -> buy | U48: =_xlfn.XLOOKUP(G48,'Kraken Trades'!$A$2:$A$28,'Kraken Trades'!$F$2:$F$28,"--",0) -> market | V48: =_xlfn.XLOOKUP(G48,'Kraken Trades'!$A$2:$A$28,'Kraken Trades'!$G$2:$G$28,"--",0) -> 0.31624 | W48: =_xlfn.XLOOKUP(G48,'Kraken Trades'!$A$2:$A$28,'Kraken Trades'!$H$2:$H$28,"--",0) -> 215.0432 | X48: =_xlfn.XLOOKUP(G48,'Kraken Trades'!$A$2:$A$28,'Kraken Trades'!$I$2:$I$28,"--",0) -> 0.55911232 | Y48: =_xlfn.XLOOKUP(G48,'Kraken Trades'!$A$2:$A$28,'Kraken Trades'!$J$2:$J$28,"--",0) -> 680 | Z48: =_xlfn.XLOOKUP(G48,'Kraken Trades'!$A$2:$A$28,'Kraken Trades'!$K$2:$K$28,"--",0) -> 0 | AA48: =_xlfn.XLOOKUP(G48,'Kraken Trades'!$A$2:$A$28,'Kraken Trades'!$L$2:$L$28,"--",0) -> initiated | AB48: =_xlfn.XLOOKUP(G48,'Kraken Trades'!$A$2:$A$28,'Kraken Trades'!$M$2:$M$28,"--",0) -> LVPZY3-Q45Q7-LMRC3C,LWLOFX-MMUGN-TTVA5O,L6CQJL-6WC7R-HFAEGK
B49: yes | E49: =_xlfn.XLOOKUP(D49,'DEST TAGs'!$A$2:$A$5,'DEST TAGs'!$B$2:$B$5,"--",0) -> -- | F49: LOTO4K-2SA36-26QNON | G49: AIBC2MA-37RPHW-GIAWXM | H49: 44986.469 | I49: withdrawal | K49: currency | L49: XXRP | M49: -745 | N49: 0.02 | O49: 680.86944 | P49: =_xlfn.XLOOKUP(G49,'Kraken Trades'!$A$2:$A$28,'Kraken Trades'!$A$2:$A$28,"--",0) -> -- | Q49: =_xlfn.XLOOKUP(G49,'Kraken Trades'!$A$2:$A$28,'Kraken Trades'!$B$2:$B$28,"--",0) -> -- | R49: =_xlfn.XLOOKUP(G49,'Kraken Trades'!$A$2:$A$28,'Kraken Trades'!$C$2:$C$28,"--",0) -> -- | S49: =_xlfn.XLOOKUP(G49,'Kraken Trades'!$A$2:$A$28,'Kraken Trades'!$D$2:$D$28,"--",0) -> -- | T49: =_xlfn.XLOOKUP(G49,'Kraken Trades'!$A$2:$A$28,'Kraken Trades'!$E$2:$E$28,"--",0) -> -- | U49: =_xlfn.XLOOKUP(G49,'Kraken Trades'!$A$2:$A$28,'Kraken Trades'!$F$2:$F$28,"--",0) -> -- | V49: =_xlfn.XLOOKUP(G49,'Kraken Trades'!$A$2:$A$28,'Kraken Trades'!$G$2:$G$28,"--",0) -> -- | W49: =_xlfn.XLOOKUP(G49,'Kraken Trades'!$A$2:$A$28,'Kraken Trades'!$H$2:$H$28,"--",0) -> -- | X49: =_xlfn.XLOOKUP(G49,'Kraken Trades'!$A$2:$A$28,'Kraken Trades'!$I$2:$I$28,"--",0) -> -- | Y49: =_xlfn.XLOOKUP(G49,'Kraken Trades'!$A$2:$A$28,'Kraken Trades'!$J$2:$J$28,"--",0) -> -- | Z49: =_xlfn.XLOOKUP(G49,'Kraken Trades'!$A$2:$A$28,'Kraken Trades'!$K$2:$K$28,"--",0) -> -- | AA49: =_xlfn.XLOOKUP(G49,'Kraken Trades'!$A$2:$A$28,'Kraken Trades'!$L$2:$L$28,"--",0) -> -- | AB49: =_xlfn.XLOOKUP(G49,'Kraken Trades'!$A$2:$A$28,'Kraken Trades'!$M$2:$M$28,"--",0) -> --
B50: yes | E50: =_xlfn.XLOOKUP(D50,'DEST TAGs'!$A$2:$A$5,'DEST TAGs'!$B$2:$B$5,"--",0) -> -- | G50: AIBDOTP-KYL6H4-OQKQUY | H50: 44986.469 | I50: withdrawal | K50: currency | L50: XXRP | M50: -680 | N50: 0.02 | P50: =_xlfn.XLOOKUP(G50,'Kraken Trades'!$A$2:$A$28,'Kraken Trades'!$A$2:$A$28,"--",0) -> -- | Q50: =_xlfn.XLOOKUP(G50,'Kraken Trades'!$A$2:$A$28,'Kraken Trades'!$B$2:$B$28,"--",0) -> -- | R50: =_xlfn.XLOOKUP(G50,'Kraken Trades'!$A$2:$A$28,'Kraken Trades'!$C$2:$C$28,"--",0) -> -- | S50: =_xlfn.XLOOKUP(G50,'Kraken Trades'!$A$2:$A$28,'Kraken Trades'!$D$2:$D$28,"--",0) -> -- | T50: =_xlfn.XLOOKUP(G50,'Kraken Trades'!$A$2:$A$28,'Kraken Trades'!$E$2:$E$28,"--",0) -> -- | U50: =_xlfn.XLOOKUP(G50,'Kraken Trades'!$A$2:$A$28,'Kraken Trades'!$F$2:$F$28,"--",0) -> -- | V50: =_xlfn.XLOOKUP(G50,'Kraken Trades'!$A$2:$A$28,'Kraken Trades'!$G$2:$G$28,"--",0) -> -- | W50: =_xlfn.XLOOKUP(G50,'Kraken Trades'!$A$2:$A$28,'Kraken Trades'!$H$2:$H$28,"--",0) -> -- | X50: =_xlfn.XLOOKUP(G50,'Kraken Trades'!$A$2:$A$28,'Kraken Trades'!$I$2:$I$28,"--",0) -> -- | Y50: =_xlfn.XLOOKUP(G50,'Kraken Trades'!$A$2:$A$28,'Kraken Trades'!$J$2:$J$28,"--",0) -> -- | Z50: =_xlfn.XLOOKUP(G50,'Kraken Trades'!$A$2:$A$28,'Kraken Trades'!$K$2:$K$28,"--",0) -> -- | AA50: =_xlfn.XLOOKUP(G50,'Kraken Trades'!$A$2:$A$28,'Kraken Trades'!$L$2:$L$28,"--",0) -> -- | AB50: =_xlfn.XLOOKUP(G50,'Kraken Trades'!$A$2:$A$28,'Kraken Trades'!$M$2:$M$28,"--",0) -> --
B51: yes | E51: =_xlfn.XLOOKUP(D51,'DEST TAGs'!$A$2:$A$5,'DEST TAGs'!$B$2:$B$5,"--",0) -> -- | F51: LRVDN3-JGHXS-KBPY44 | G51: AIBDOTP-KYL6H4-OQKQUY | H51: 44986.471 | I51: withdrawal | K51: currency | L51: XXRP | M51: -680 | N51: 0.02 | O51: 0.84944334 | P51: =_xlfn.XLOOKUP(G51,'Kraken Trades'!$A$2:$A$28,'Kraken Trades'!$A$2:$A$28,"--",0) -> -- | Q51: =_xlfn.XLOOKUP(G51,'Kraken Trades'!$A$2:$A$28,'Kraken Trades'!$B$2:$B$28,"--",0) -> -- | R51: =_xlfn.XLOOKUP(G51,'Kraken Trades'!$A$2:$A$28,'Kraken Trades'!$C$2:$C$28,"--",0) -> -- | S51: =_xlfn.XLOOKUP(G51,'Kraken Trades'!$A$2:$A$28,'Kraken Trades'!$D$2:$D$28,"--",0) -> -- | T51: =_xlfn.XLOOKUP(G51,'Kraken Trades'!$A$2:$A$28,'Kraken Trades'!$E$2:$E$28,"--",0) -> -- | U51: =_xlfn.XLOOKUP(G51,'Kraken Trades'!$A$2:$A$28,'Kraken Trades'!$F$2:$F$28,"--",0) -> -- | V51: =_xlfn.XLOOKUP(G51,'Kraken Trades'!$A$2:$A$28,'Kraken Trades'!$G$2:$G$28,"--",0) -> -- | W51: =_xlfn.XLOOKUP(G51,'Kraken Trades'!$A$2:$A$28,'Kraken Trades'!$H$2:$H$28,"--",0) -> -- | X51: =_xlfn.XLOOKUP(G51,'Kraken Trades'!$A$2:$A$28,'Kraken Trades'!$I$2:$I$28,"--",0) -> -- | Y51: =_xlfn.XLOOKUP(G51,'Kraken Trades'!$A$2:$A$28,'Kraken Trades'!$J$2:$J$28,"--",0) -> -- | Z51: =_xlfn.XLOOKUP(G51,'Kraken Trades'!$A$2:$A$28,'Kraken Trades'!$K$2:$K$28,"--",0) -> -- | AA51: =_xlfn.XLOOKUP(G51,'Kraken Trades'!$A$2:$A$28,'Kraken Trades'!$L$2:$L$28,"--",0) -> -- | AB51: =_xlfn.XLOOKUP(G51,'Kraken Trades'!$A$2:$A$28,'Kraken Trades'!$M$2:$M$28,"--",0) -> --
B52: yes | E52: =_xlfn.XLOOKUP(D52,'DEST TAGs'!$A$2:$A$5,'DEST TAGs'!$B$2:$B$5,"--",0) -> -- | G52: QYPL44W-HZSE2I-FTE6ZH | H52: 45007.421 | I52: deposit | K52: currency | L52: ZGBP | M52: 275 | N52: 0 | P52: =_xlfn.XLOOKUP(G52,'Kraken Trades'!$A$2:$A$28,'Kraken Trades'!$A$2:$A$28,"--",0) -> -- | Q52: =_xlfn.XLOOKUP(G52,'Kraken Trades'!$A$2:$A$28,'Kraken Trades'!$B$2:$B$28,"--",0) -> -- | R52: =_xlfn.XLOOKUP(G52,'Kraken Trades'!$A$2:$A$28,'Kraken Trades'!$C$2:$C$28,"--",0) -> -- | S52: =_xlfn.XLOOKUP(G52,'Kraken Trades'!$A$2:$A$28,'Kraken Trades'!$D$2:$D$28,"--",0) -> -- | T52: =_xlfn.XLOOKUP(G52,'Kraken Trades'!$A$2:$A$28,'Kraken Trades'!$E$2:$E$28,"--",0) -> -- | U52: =_xlfn.XLOOKUP(G52,'Kraken Trades'!$A$2:$A$28,'Kraken Trades'!$F$2:$F$28,"--",0) -> -- | V52: =_xlfn.XLOOKUP(G52,'Kraken Trades'!$A$2:$A$28,'Kraken Trades'!$G$2:$G$28,"--",0) -> -- | W52: =_xlfn.XLOOKUP(G52,'Kraken Trades'!$A$2:$A$28,'Kraken Trades'!$H$2:$H$28,"--",0) -> -- | X52: =_xlfn.XLOOKUP(G52,'Kraken Trades'!$A$2:$A$28,'Kraken Trades'!$I$2:$I$28,"--",0) -> -- | Y52: =_xlfn.XLOOKUP(G52,'Kraken Trades'!$A$2:$A$28,'Kraken Trades'!$J$2:$J$28,"--",0) -> -- | Z52: =_xlfn.XLOOKUP(G52,'Kraken Trades'!$A$2:$A$28,'Kraken Trades'!$K$2:$K$28,"--",0) -> -- | AA52: =_xlfn.XLOOKUP(G52,'Kraken Trades'!$A$2:$A$28,'Kraken Trades'!$L$2:$L$28,"--",0) -> -- | AB52: =_xlfn.XLOOKUP(G52,'Kraken Trades'!$A$2:$A$28,'Kraken Trades'!$M$2:$M$28,"--",0) -> --
B53: yes | E53: =_xlfn.XLOOKUP(D53,'DEST TAGs'!$A$2:$A$5,'DEST TAGs'!$B$2:$B$5,"--",0) -> -- | F53: LTQODH-YQW3U-JDR6XB | G53: QYPL44W-HZSE2I-FTE6ZH | H53: 45007.436 | I53: deposit | K53: currency | L53: ZGBP | M53: 275 | N53: 0 | O53: 275.0689 | P53: =_xlfn.XLOOKUP(G53,'Kraken Trades'!$A$2:$A$28,'Kraken Trades'!$A$2:$A$28,"--",0) -> -- | Q53: =_xlfn.XLOOKUP(G53,'Kraken Trades'!$A$2:$A$28,'Kraken Trades'!$B$2:$B$28,"--",0) -> -- | R53: =_xlfn.XLOOKUP(G53,'Kraken Trades'!$A$2:$A$28,'Kraken Trades'!$C$2:$C$28,"--",0) -> -- | S53: =_xlfn.XLOOKUP(G53,'Kraken Trades'!$A$2:$A$28,'Kraken Trades'!$D$2:$D$28,"--",0) -> -- | T53: =_xlfn.XLOOKUP(G53,'Kraken Trades'!$A$2:$A$28,'Kraken Trades'!$E$2:$E$28,"--",0) -> -- | U53: =_xlfn.XLOOKUP(G53,'Kraken Trades'!$A$2:$A$28,'Kraken Trades'!$F$2:$F$28,"--",0) -> -- | V53: =_xlfn.XLOOKUP(G53,'Kraken Trades'!$A$2:$A$28,'Kraken Trades'!$G$2:$G$28,"--",0) -> -- | W53: =_xlfn.XLOOKUP(G53,'Kraken Trades'!$A$2:$A$28,'Kraken Trades'!$H$2:$H$28,"--",0) -> -- | X53: =_xlfn.XLOOKUP(G53,'Kraken Trades'!$A$2:$A$28,'Kraken Trades'!$I$2:$I$28,"--",0) -> -- | Y53: =_xlfn.XLOOKUP(G53,'Kraken Trades'!$A$2:$A$28,'Kraken Trades'!$J$2:$J$28,"--",0) -> -- | Z53: =_xlfn.XLOOKUP(G53,'Kraken Trades'!$A$2:$A$28,'Kraken Trades'!$K$2:$K$28,"--",0) -> -- | AA53: =_xlfn.XLOOKUP(G53,'Kraken Trades'!$A$2:$A$28,'Kraken Trades'!$L$2:$L$28,"--",0) -> -- | AB53: =_xlfn.XLOOKUP(G53,'Kraken Trades'!$A$2:$A$28,'Kraken Trades'!$M$2:$M$28,"--",0) -> --
B54: yes | E54: =_xlfn.XLOOKUP(D54,'DEST TAGs'!$A$2:$A$5,'DEST TAGs'!$B$2:$B$5,"--",0) -> -- | F54: LKTWBH-PHKLE-CC24C2 | G54: TVEO4I-KY7HQ-QBBWUM | H54: 45007.446 | I54: trade | K54: currency | L54: ZGBP | M54: -256.9455 | N54: 0 | O54: 18.1234 | P54: =_xlfn.XLOOKUP(G54,'Kraken Trades'!$A$2:$A$28,'Kraken Trades'!$A$2:$A$28,"--",0) -> TVEO4I-KY7HQ-QBBWUM | Q54: =_xlfn.XLOOKUP(G54,'Kraken Trades'!$A$2:$A$28,'Kraken Trades'!$B$2:$B$28,"--",0) -> OXYUXG-MWUSN-R5UQHK | R54: =_xlfn.XLOOKUP(G54,'Kraken Trades'!$A$2:$A$28,'Kraken Trades'!$C$2:$C$28,"--",0) -> XRPGBP | S54: =_xlfn.XLOOKUP(G54,'Kraken Trades'!$A$2:$A$28,'Kraken Trades'!$D$2:$D$28,"--",0) -> 0.029686343 | T54: =_xlfn.XLOOKUP(G54,'Kraken Trades'!$A$2:$A$28,'Kraken Trades'!$E$2:$E$28,"--",0) -> buy | U54: =_xlfn.XLOOKUP(G54,'Kraken Trades'!$A$2:$A$28,'Kraken Trades'!$F$2:$F$28,"--",0) -> market | V54: =_xlfn.XLOOKUP(G54,'Kraken Trades'!$A$2:$A$28,'Kraken Trades'!$G$2:$G$28,"--",0) -> 0.36706496 | W54: =_xlfn.XLOOKUP(G54,'Kraken Trades'!$A$2:$A$28,'Kraken Trades'!$H$2:$H$28,"--",0) -> 256.94547 | X54: =_xlfn.XLOOKUP(G54,'Kraken Trades'!$A$2:$A$28,'Kraken Trades'!$I$2:$I$28,"--",0) -> 0.66805822 | Y54: =_xlfn.XLOOKUP(G54,'Kraken Trades'!$A$2:$A$28,'Kraken Trades'!$J$2:$J$28,"--",0) -> 700 | Z54: =_xlfn.XLOOKUP(G54,'Kraken Trades'!$A$2:$A$28,'Kraken Trades'!$K$2:$K$28,"--",0) -> 0 | AA54: =_xlfn.XLOOKUP(G54,'Kraken Trades'!$A$2:$A$28,'Kraken Trades'!$L$2:$L$28,"--",0) -> initiated | AB54: =_xlfn.XLOOKUP(G54,'Kraken Trades'!$A$2:$A$28,'Kraken Trades'!$M$2:$M$28,"--",0) -> L6SMP6-NDAWR-2UIRQZ,LJDYPI-R6LH7-E2EA6H,LKTWBH-PHKLE-CC24C2
B55: yes | E55: =_xlfn.XLOOKUP(D55,'DEST TAGs'!$A$2:$A$5,'DEST TAGs'!$B$2:$B$5,"--",0) -> -- | F55: LJDYPI-R6LH7-E2EA6H | G55: TVEO4I-KY7HQ-QBBWUM | H55: 45007.446 | I55: trade | K55: currency | L55: XXRP | M55: 700 | N55: 0 | O55: 700.84944 | P55: =_xlfn.XLOOKUP(G55,'Kraken Trades'!$A$2:$A$28,'Kraken Trades'!$A$2:$A$28,"--",0) -> TVEO4I-KY7HQ-QBBWUM | Q55: =_xlfn.XLOOKUP(G55,'Kraken Trades'!$A$2:$A$28,'Kraken Trades'!$B$2:$B$28,"--",0) -> OXYUXG-MWUSN-R5UQHK | R55: =_xlfn.XLOOKUP(G55,'Kraken Trades'!$A$2:$A$28,'Kraken Trades'!$C$2:$C$28,"--",0) -> XRPGBP | S55: =_xlfn.XLOOKUP(G55,'Kraken Trades'!$A$2:$A$28,'Kraken Trades'!$D$2:$D$28,"--",0) -> 0.029686343 | T55: =_xlfn.XLOOKUP(G55,'Kraken Trades'!$A$2:$A$28,'Kraken Trades'!$E$2:$E$28,"--",0) -> buy | U55: =_xlfn.XLOOKUP(G55,'Kraken Trades'!$A$2:$A$28,'Kraken Trades'!$F$2:$F$28,"--",0) -> market | V55: =_xlfn.XLOOKUP(G55,'Kraken Trades'!$A$2:$A$28,'Kraken Trades'!$G$2:$G$28,"--",0) -> 0.36706496 | W55: =_xlfn.XLOOKUP(G55,'Kraken Trades'!$A$2:$A$28,'Kraken Trades'!$H$2:$H$28,"--",0) -> 256.94547 | X55: =_xlfn.XLOOKUP(G55,'Kraken Trades'!$A$2:$A$28,'Kraken Trades'!$I$2:$I$28,"--",0) -> 0.66805822 | Y55: =_xlfn.XLOOKUP(G55,'Kraken Trades'!$A$2:$A$28,'Kraken Trades'!$J$2:$J$28,"--",0) -> 700 | Z55: =_xlfn.XLOOKUP(G55,'Kraken Trades'!$A$2:$A$28,'Kraken Trades'!$K$2:$K$28,"--",0) -> 0 | AA55: =_xlfn.XLOOKUP(G55,'Kraken Trades'!$A$2:$A$28,'Kraken Trades'!$L$2:$L$28,"--",0) -> initiated | AB55: =_xlfn.XLOOKUP(G55,'Kraken Trades'!$A$2:$A$28,'Kraken Trades'!$M$2:$M$28,"--",0) -> L6SMP6-NDAWR-2UIRQZ,LJDYPI-R6LH7-E2EA6H,LKTWBH-PHKLE-CC24C2
B56: yes | E56: =_xlfn.XLOOKUP(D56,'DEST TAGs'!$A$2:$A$5,'DEST TAGs'!$B$2:$B$5,"--",0) -> -- | F56: L6SMP6-NDAWR-2UIRQZ | G56: TVEO4I-KY7HQ-QBBWUM | H56: 45007.446 | I56: trade | K56: currency | L56: KFEE | M56: 0 | N56: 82.09 | O56: 7048.6 | P56: =_xlfn.XLOOKUP(G56,'Kraken Trades'!$A$2:$A$28,'Kraken Trades'!$A$2:$A$28,"--",0) -> TVEO4I-KY7HQ-QBBWUM | Q56: =_xlfn.XLOOKUP(G56,'Kraken Trades'!$A$2:$A$28,'Kraken Trades'!$B$2:$B$28,"--",0) -> OXYUXG-MWUSN-R5UQHK | R56: =_xlfn.XLOOKUP(G56,'Kraken Trades'!$A$2:$A$28,'Kraken Trades'!$C$2:$C$28,"--",0) -> XRPGBP | S56: =_xlfn.XLOOKUP(G56,'Kraken Trades'!$A$2:$A$28,'Kraken Trades'!$D$2:$D$28,"--",0) -> 0.029686343 | T56: =_xlfn.XLOOKUP(G56,'Kraken Trades'!$A$2:$A$28,'Kraken Trades'!$E$2:$E$28,"--",0) -> buy | U56: =_xlfn.XLOOKUP(G56,'Kraken Trades'!$A$2:$A$28,'Kraken Trades'!$F$2:$F$28,"--",0) -> market | V56: =_xlfn.XLOOKUP(G56,'Kraken Trades'!$A$2:$A$28,'Kraken Trades'!$G$2:$G$28,"--",0) -> 0.36706496 | W56: =_xlfn.XLOOKUP(G56,'Kraken Trades'!$A$2:$A$28,'Kraken Trades'!$H$2:$H$28,"--",0) -> 256.94547 | X56: =_xlfn.XLOOKUP(G56,'Kraken Trades'!$A$2:$A$28,'Kraken Trades'!$I$2:$I$28,"--",0) -> 0.66805822 | Y56: =_xlfn.XLOOKUP(G56,'Kraken Trades'!$A$2:$A$28,'Kraken Trades'!$J$2:$J$28,"--",0) -> 700 | Z56: =_xlfn.XLOOKUP(G56,'Kraken Trades'!$A$2:$A$28,'Kraken Trades'!$K$2:$K$28,"--",0) -> 0 | AA56: =_xlfn.XLOOKUP(G56,'Kraken Trades'!$A$2:$A$28,'Kraken Trades'!$L$2:$L$28,"--",0) -> initiated | AB56: =_xlfn.XLOOKUP(G56,'Kraken Trades'!$A$2:$A$28,'Kraken Trades'!$M$2:$M$28,"--",0) -> L6SMP6-NDAWR-2UIRQZ,LJDYPI-R6LH7-E2EA6H,LKTWBH-PHKLE-CC24C2
B57: yes | E57: =_xlfn.XLOOKUP(D57,'DEST TAGs'!$A$2:$A$5,'DEST TAGs'!$B$2:$B$5,"--",0) -> -- | G57: AIBHZOD-I7PFAV-4SY3IO | H57: 45007.447 | I57: withdrawal | K57: currency | L57: XXRP | M57: -700 | N57: 0.02 | P57: =_xlfn.XLOOKUP(G57,'Kraken Trades'!$A$2:$A$28,'Kraken Trades'!$A$2:$A$28,"--",0) -> -- | Q57: =_xlfn.XLOOKUP(G57,'Kraken Trades'!$A$2:$A$28,'Kraken Trades'!$B$2:$B$28,"--",0) -> -- | R57: =_xlfn.XLOOKUP(G57,'Kraken Trades'!$A$2:$A$28,'Kraken Trades'!$C$2:$C$28,"--",0) -> -- | S57: =_xlfn.XLOOKUP(G57,'Kraken Trades'!$A$2:$A$28,'Kraken Trades'!$D$2:$D$28,"--",0) -> -- | T57: =_xlfn.XLOOKUP(G57,'Kraken Trades'!$A$2:$A$28,'Kraken Trades'!$E$2:$E$28,"--",0) -> -- | U57: =_xlfn.XLOOKUP(G57,'Kraken Trades'!$A$2:$A$28,'Kraken Trades'!$F$2:$F$28,"--",0) -> -- | V57: =_xlfn.XLOOKUP(G57,'Kraken Trades'!$A$2:$A$28,'Kraken Trades'!$G$2:$G$28,"--",0) -> -- | W57: =_xlfn.XLOOKUP(G57,'Kraken Trades'!$A$2:$A$28,'Kraken Trades'!$H$2:$H$28,"--",0) -> -- | X57: =_xlfn.XLOOKUP(G57,'Kraken Trades'!$A$2:$A$28,'Kraken Trades'!$I$2:$I$28,"--",0) -> -- | Y57: =_xlfn.XLOOKUP(G57,'Kraken Trades'!$A$2:$A$28,'Kraken Trades'!$J$2:$J$28,"--",0) -> -- | Z57: =_xlfn.XLOOKUP(G57,'Kraken Trades'!$A$2:$A$28,'Kraken Trades'!$K$2:$K$28,"--",0) -> -- | AA57: =_xlfn.XLOOKUP(G57,'Kraken Trades'!$A$2:$A$28,'Kraken Trades'!$L$2:$L$28,"--",0) -> -- | AB57: =_xlfn.XLOOKUP(G57,'Kraken Trades'!$A$2:$A$28,'Kraken Trades'!$M$2:$M$28,"--",0) -> --
B58: yes | E58: =_xlfn.XLOOKUP(D58,'DEST TAGs'!$A$2:$A$5,'DEST TAGs'!$B$2:$B$5,"--",0) -> -- | F58: LAXSRN-QWV4Z-NSURDN | G58: AIBHZOD-I7PFAV-4SY3IO | H58: 45007.448 | I58: withdrawal | K58: currency | L58: XXRP | M58: -700 | N58: 0.02 | O58: 0.82944334 | P58: =_xlfn.XLOOKUP(G58,'Kraken Trades'!$A$2:$A$28,'Kraken Trades'!$A$2:$A$28,"--",0) -> -- | Q58: =_xlfn.XLOOKUP(G58,'Kraken Trades'!$A$2:$A$28,'Kraken Trades'!$B$2:$B$28,"--",0) -> -- | R58: =_xlfn.XLOOKUP(G58,'Kraken Trades'!$A$2:$A$28,'Kraken Trades'!$C$2:$C$28,"--",0) -> -- | S58: =_xlfn.XLOOKUP(G58,'Kraken Trades'!$A$2:$A$28,'Kraken Trades'!$D$2:$D$28,"--",0) -> -- | T58: =_xlfn.XLOOKUP(G58,'Kraken Trades'!$A$2:$A$28,'Kraken Trades'!$E$2:$E$28,"--",0) -> -- | U58: =_xlfn.XLOOKUP(G58,'Kraken Trades'!$A$2:$A$28,'Kraken Trades'!$F$2:$F$28,"--",0) -> -- | V58: =_xlfn.XLOOKUP(G58,'Kraken Trades'!$A$2:$A$28,'Kraken Trades'!$G$2:$G$28,"--",0) -> -- | W58: =_xlfn.XLOOKUP(G58,'Kraken Trades'!$A$2:$A$28,'Kraken Trades'!$H$2:$H$28,"--",0) -> -- | X58: =_xlfn.XLOOKUP(G58,'Kraken Trades'!$A$2:$A$28,'Kraken Trades'!$I$2:$I$28,"--",0) -> -- | Y58: =_xlfn.XLOOKUP(G58,'Kraken Trades'!$A$2:$A$28,'Kraken Trades'!$J$2:$J$28,"--",0) -> -- | Z58: =_xlfn.XLOOKUP(G58,'Kraken Trades'!$A$2:$A$28,'Kraken Trades'!$K$2:$K$28,"--",0) -> -- | AA58: =_xlfn.XLOOKUP(G58,'Kraken Trades'!$A$2:$A$28,'Kraken Trades'!$L$2:$L$28,"--",0) -> -- | AB58: =_xlfn.XLOOKUP(G58,'Kraken Trades'!$A$2:$A$28,'Kraken Trades'!$M$2:$M$28,"--",0) -> --
B59: yes | E59: =_xlfn.XLOOKUP(D59,'DEST TAGs'!$A$2:$A$5,'DEST TAGs'!$B$2:$B$5,"--",0) -> -- | G59: QYP2WRH-UELOAR-4AKP24 | H59: 45010.383 | I59: deposit | K59: currency | L59: ZGBP | M59: 1500 | N59: 0 | P59: =_xlfn.XLOOKUP(G59,'Kraken Trades'!$A$2:$A$28,'Kraken Trades'!$A$2:$A$28,"--",0) -> -- | Q59: =_xlfn.XLOOKUP(G59,'Kraken Trades'!$A$2:$A$28,'Kraken Trades'!$B$2:$B$28,"--",0) -> -- | R59: =_xlfn.XLOOKUP(G59,'Kraken Trades'!$A$2:$A$28,'Kraken Trades'!$C$2:$C$28,"--",0) -> -- | S59: =_xlfn.XLOOKUP(G59,'Kraken Trades'!$A$2:$A$28,'Kraken Trades'!$D$2:$D$28,"--",0) -> -- | T59: =_xlfn.XLOOKUP(G59,'Kraken Trades'!$A$2:$A$28,'Kraken Trades'!$E$2:$E$28,"--",0) -> -- | U59: =_xlfn.XLOOKUP(G59,'Kraken Trades'!$A$2:$A$28,'Kraken Trades'!$F$2:$F$28,"--",0) -> -- | V59: =_xlfn.XLOOKUP(G59,'Kraken Trades'!$A$2:$A$28,'Kraken Trades'!$G$2:$G$28,"--",0) -> -- | W59: =_xlfn.XLOOKUP(G59,'Kraken Trades'!$A$2:$A$28,'Kraken Trades'!$H$2:$H$28,"--",0) -> -- | X59: =_xlfn.XLOOKUP(G59,'Kraken Trades'!$A$2:$A$28,'Kraken Trades'!$I$2:$I$28,"--",0) -> -- | Y59: =_xlfn.XLOOKUP(G59,'Kraken Trades'!$A$2:$A$28,'Kraken Trades'!$J$2:$J$28,"--",0) -> -- | Z59: =_xlfn.XLOOKUP(G59,'Kraken Trades'!$A$2:$A$28,'Kraken Trades'!$K$2:$K$28,"--",0) -> -- | AA59: =_xlfn.XLOOKUP(G59,'Kraken Trades'!$A$2:$A$28,'Kraken Trades'!$L$2:$L$28,"--",0) -> -- | AB59: =_xlfn.XLOOKUP(G59,'Kraken Trades'!$A$2:$A$28,'Kraken Trades'!$M$2:$M$28,"--",0) -> --
B60: yes | E60: =_xlfn.XLOOKUP(D60,'DEST TAGs'!$A$2:$A$5,'DEST TAGs'!$B$2:$B$5,"--",0) -> -- | F60: LPB43Z-X5Y2P-IZTPWC | G60: QYP2WRH-UELOAR-4AKP24 | H60: 45010.529 | I60: deposit | K60: currency | L60: ZGBP | M60: 1500 | N60: 0 | O60: 1518.1234 | P60: =_xlfn.XLOOKUP(G60,'Kraken Trades'!$A$2:$A$28,'Kraken Trades'!$A$2:$A$28,"--",0) -> -- | Q60: =_xlfn.XLOOKUP(G60,'Kraken Trades'!$A$2:$A$28,'Kraken Trades'!$B$2:$B$28,"--",0) -> -- | R60: =_xlfn.XLOOKUP(G60,'Kraken Trades'!$A$2:$A$28,'Kraken Trades'!$C$2:$C$28,"--",0) -> -- | S60: =_xlfn.XLOOKUP(G60,'Kraken Trades'!$A$2:$A$28,'Kraken Trades'!$D$2:$D$28,"--",0) -> -- | T60: =_xlfn.XLOOKUP(G60,'Kraken Trades'!$A$2:$A$28,'Kraken Trades'!$E$2:$E$28,"--",0) -> -- | U60: =_xlfn.XLOOKUP(G60,'Kraken Trades'!$A$2:$A$28,'Kraken Trades'!$F$2:$F$28,"--",0) -> -- | V60: =_xlfn.XLOOKUP(G60,'Kraken Trades'!$A$2:$A$28,'Kraken Trades'!$G$2:$G$28,"--",0) -> -- | W60: =_xlfn.XLOOKUP(G60,'Kraken Trades'!$A$2:$A$28,'Kraken Trades'!$H$2:$H$28,"--",0) -> -- | X60: =_xlfn.XLOOKUP(G60,'Kraken Trades'!$A$2:$A$28,'Kraken Trades'!$I$2:$I$28,"--",0) -> -- | Y60: =_xlfn.XLOOKUP(G60,'Kraken Trades'!$A$2:$A$28,'Kraken Trades'!$J$2:$J$28,"--",0) -> -- | Z60: =_xlfn.XLOOKUP(G60,'Kraken Trades'!$A$2:$A$28,'Kraken Trades'!$K$2:$K$28,"--",0) -> -- | AA60: =_xlfn.XLOOKUP(G60,'Kraken Trades'!$A$2:$A$28,'Kraken Trades'!$L$2:$L$28,"--",0) -> -- | AB60: =_xlfn.XLOOKUP(G60,'Kraken Trades'!$A$2:$A$28,'Kraken Trades'!$M$2:$M$28,"--",0) -> --
B61: yes | E61: =_xlfn.XLOOKUP(D61,'DEST TAGs'!$A$2:$A$5,'DEST TAGs'!$B$2:$B$5,"--",0) -> -- | F61: LBOVA7-4FOSU-VDWKFU | G61: TDGV6W-7Q63J-E4QJW6 | H61: 45010.544 | I61: trade | K61: currency | L61: ZGBP | M61: -1327.7607 | N61: 0 | O61: 190.3627 | P61: =_xlfn.XLOOKUP(G61,'Kraken Trades'!$A$2:$A$28,'Kraken Trades'!$A$2:$A$28,"--",0) -> TDGV6W-7Q63J-E4QJW6 | Q61: =_xlfn.XLOOKUP(G61,'Kraken Trades'!$A$2:$A$28,'Kraken Trades'!$B$2:$B$28,"--",0) -> O3ZHGF-QQMXC-EVF2YX | R61: =_xlfn.XLOOKUP(G61,'Kraken Trades'!$A$2:$A$28,'Kraken Trades'!$C$2:$C$28,"--",0) -> XRPGBP | S61: =_xlfn.XLOOKUP(G61,'Kraken Trades'!$A$2:$A$28,'Kraken Trades'!$D$2:$D$28,"--",0) -> 0.002775463 | T61: =_xlfn.XLOOKUP(G61,'Kraken Trades'!$A$2:$A$28,'Kraken Trades'!$E$2:$E$28,"--",0) -> buy | U61: =_xlfn.XLOOKUP(G61,'Kraken Trades'!$A$2:$A$28,'Kraken Trades'!$F$2:$F$28,"--",0) -> market | V61: =_xlfn.XLOOKUP(G61,'Kraken Trades'!$A$2:$A$28,'Kraken Trades'!$G$2:$G$28,"--",0) -> 0.36426906 | W61: =_xlfn.XLOOKUP(G61,'Kraken Trades'!$A$2:$A$28,'Kraken Trades'!$H$2:$H$28,"--",0) -> 1327.7607 | X61: =_xlfn.XLOOKUP(G61,'Kraken Trades'!$A$2:$A$28,'Kraken Trades'!$I$2:$I$28,"--",0) -> 3.4521778 | Y61: =_xlfn.XLOOKUP(G61,'Kraken Trades'!$A$2:$A$28,'Kraken Trades'!$J$2:$J$28,"--",0) -> 3645 | Z61: =_xlfn.XLOOKUP(G61,'Kraken Trades'!$A$2:$A$28,'Kraken Trades'!$K$2:$K$28,"--",0) -> 0 | AA61: =_xlfn.XLOOKUP(G61,'Kraken Trades'!$A$2:$A$28,'Kraken Trades'!$L$2:$L$28,"--",0) -> initiated | AB61: =_xlfn.XLOOKUP(G61,'Kraken Trades'!$A$2:$A$28,'Kraken Trades'!$M$2:$M$28,"--",0) -> L6W2JN-Z6XBJ-36ZUNE,LU2EIK-LAETH-JD4F56,LBOVA7-4FOSU-VDWKFU
B62: yes | E62: =_xlfn.XLOOKUP(D62,'DEST TAGs'!$A$2:$A$5,'DEST TAGs'!$B$2:$B$5,"--",0) -> -- | F62: LU2EIK-LAETH-JD4F56 | G62: TDGV6W-7Q63J-E4QJW6 | H62: 45010.544 | I62: trade | K62: currency | L62: XXRP | M62: 3645 | N62: 0 | O62: 3645.8294 | P62: =_xlfn.XLOOKUP(G62,'Kraken Trades'!$A$2:$A$28,'Kraken Trades'!$A$2:$A$28,"--",0) -> TDGV6W-7Q63J-E4QJW6 | Q62: =_xlfn.XLOOKUP(G62,'Kraken Trades'!$A$2:$A$28,'Kraken Trades'!$B$2:$B$28,"--",0) -> O3ZHGF-QQMXC-EVF2YX | R62: =_xlfn.XLOOKUP(G62,'Kraken Trades'!$A$2:$A$28,'Kraken Trades'!$C$2:$C$28,"--",0) -> XRPGBP | S62: =_xlfn.XLOOKUP(G62,'Kraken Trades'!$A$2:$A$28,'Kraken Trades'!$D$2:$D$28,"--",0) -> 0.002775463 | T62: =_xlfn.XLOOKUP(G62,'Kraken Trades'!$A$2:$A$28,'Kraken Trades'!$E$2:$E$28,"--",0) -> buy | U62: =_xlfn.XLOOKUP(G62,'Kraken Trades'!$A$2:$A$28,'Kraken Trades'!$F$2:$F$28,"--",0) -> market | V62: =_xlfn.XLOOKUP(G62,'Kraken Trades'!$A$2:$A$28,'Kraken Trades'!$G$2:$G$28,"--",0) -> 0.36426906 | W62: =_xlfn.XLOOKUP(G62,'Kraken Trades'!$A$2:$A$28,'Kraken Trades'!$H$2:$H$28,"--",0) -> 1327.7607 | X62: =_xlfn.XLOOKUP(G62,'Kraken Trades'!$A$2:$A$28,'Kraken Trades'!$I$2:$I$28,"--",0) -> 3.4521778 | Y62: =_xlfn.XLOOKUP(G62,'Kraken Trades'!$A$2:$A$28,'Kraken Trades'!$J$2:$J$28,"--",0) -> 3645 | Z62: =_xlfn.XLOOKUP(G62,'Kraken Trades'!$A$2:$A$28,'Kraken Trades'!$K$2:$K$28,"--",0) -> 0 | AA62: =_xlfn.XLOOKUP(G62,'Kraken Trades'!$A$2:$A$28,'Kraken Trades'!$L$2:$L$28,"--",0) -> initiated | AB62: =_xlfn.XLOOKUP(G62,'Kraken Trades'!$A$2:$A$28,'Kraken Trades'!$M$2:$M$28,"--",0) -> L6W2JN-Z6XBJ-36ZUNE,LU2EIK-LAETH-JD4F56,LBOVA7-4FOSU-VDWKFU
B63: yes | E63: =_xlfn.XLOOKUP(D63,'DEST TAGs'!$A$2:$A$5,'DEST TAGs'!$B$2:$B$5,"--",0) -> -- | F63: L6W2JN-Z6XBJ-36ZUNE | G63: TDGV6W-7Q63J-E4QJW6 | H63: 45010.544 | I63: trade | K63: currency | L63: KFEE | M63: 0 | N63: 422.23 | O63: 6626.37 | P63: =_xlfn.XLOOKUP(G63,'Kraken Trades'!$A$2:$A$28,'Kraken Trades'!$A$2:$A$28,"--",0) -> TDGV6W-7Q63J-E4QJW6 | Q63: =_xlfn.XLOOKUP(G63,'Kraken Trades'!$A$2:$A$28,'Kraken Trades'!$B$2:$B$28,"--",0) -> O3ZHGF-QQMXC-EVF2YX | R63: =_xlfn.XLOOKUP(G63,'Kraken Trades'!$A$2:$A$28,'Kraken Trades'!$C$2:$C$28,"--",0) -> XRPGBP | S63: =_xlfn.XLOOKUP(G63,'Kraken Trades'!$A$2:$A$28,'Kraken Trades'!$D$2:$D$28,"--",0) -> 0.002775463 | T63: =_xlfn.XLOOKUP(G63,'Kraken Trades'!$A$2:$A$28,'Kraken Trades'!$E$2:$E$28,"--",0) -> buy | U63: =_xlfn.XLOOKUP(G63,'Kraken Trades'!$A$2:$A$28,'Kraken Trades'!$F$2:$F$28,"--",0) -> market | V63: =_xlfn.XLOOKUP(G63,'Kraken Trades'!$A$2:$A$28,'Kraken Trades'!$G$2:$G$28,"--",0) -> 0.36426906 | W63: =_xlfn.XLOOKUP(G63,'Kraken Trades'!$A$2:$A$28,'Kraken Trades'!$H$2:$H$28,"--",0) -> 1327.7607 | X63: =_xlfn.XLOOKUP(G63,'Kraken Trades'!$A$2:$A$28,'Kraken Trades'!$I$2:$I$28,"--",0) -> 3.4521778 | Y63: =_xlfn.XLOOKUP(G63,'Kraken Trades'!$A$2:$A$28,'Kraken Trades'!$J$2:$J$28,"--",0) -> 3645 | Z63: =_xlfn.XLOOKUP(G63,'Kraken Trades'!$A$2:$A$28,'Kraken Trades'!$K$2:$K$28,"--",0) -> 0 | AA63: =_xlfn.XLOOKUP(G63,'Kraken Trades'!$A$2:$A$28,'Kraken Trades'!$L$2:$L$28,"--",0) -> initiated | AB63: =_xlfn.XLOOKUP(G63,'Kraken Trades'!$A$2:$A$28,'Kraken Trades'!$M$2:$M$28,"--",0) -> L6W2JN-Z6XBJ-36ZUNE,LU2EIK-LAETH-JD4F56,LBOVA7-4FOSU-VDWKFU
B64: yes | E64: =_xlfn.XLOOKUP(D64,'DEST TAGs'!$A$2:$A$5,'DEST TAGs'!$B$2:$B$5,"--",0) -> -- | G64: AIB3USJ-Q3YFJY-K6Y6SG | H64: 45010.544 | I64: withdrawal | K64: currency | L64: XXRP | M64: -3645 | N64: 0.02 | P64: =_xlfn.XLOOKUP(G64,'Kraken Trades'!$A$2:$A$28,'Kraken Trades'!$A$2:$A$28,"--",0) -> -- | Q64: =_xlfn.XLOOKUP(G64,'Kraken Trades'!$A$2:$A$28,'Kraken Trades'!$B$2:$B$28,"--",0) -> -- | R64: =_xlfn.XLOOKUP(G64,'Kraken Trades'!$A$2:$A$28,'Kraken Trades'!$C$2:$C$28,"--",0) -> -- | S64: =_xlfn.XLOOKUP(G64,'Kraken Trades'!$A$2:$A$28,'Kraken Trades'!$D$2:$D$28,"--",0) -> -- | T64: =_xlfn.XLOOKUP(G64,'Kraken Trades'!$A$2:$A$28,'Kraken Trades'!$E$2:$E$28,"--",0) -> -- | U64: =_xlfn.XLOOKUP(G64,'Kraken Trades'!$A$2:$A$28,'Kraken Trades'!$F$2:$F$28,"--",0) -> -- | V64: =_xlfn.XLOOKUP(G64,'Kraken Trades'!$A$2:$A$28,'Kraken Trades'!$G$2:$G$28,"--",0) -> -- | W64: =_xlfn.XLOOKUP(G64,'Kraken Trades'!$A$2:$A$28,'Kraken Trades'!$H$2:$H$28,"--",0) -> -- | X64: =_xlfn.XLOOKUP(G64,'Kraken Trades'!$A$2:$A$28,'Kraken Trades'!$I$2:$I$28,"--",0) -> -- | Y64: =_xlfn.XLOOKUP(G64,'Kraken Trades'!$A$2:$A$28,'Kraken Trades'!$J$2:$J$28,"--",0) -> -- | Z64: =_xlfn.XLOOKUP(G64,'Kraken Trades'!$A$2:$A$28,'Kraken Trades'!$K$2:$K$28,"--",0) -> -- | AA64: =_xlfn.XLOOKUP(G64,'Kraken Trades'!$A$2:$A$28,'Kraken Trades'!$L$2:$L$28,"--",0) -> -- | AB64: =_xlfn.XLOOKUP(G64,'Kraken Trades'!$A$2:$A$28,'Kraken Trades'!$M$2:$M$28,"--",0) -> --
B65: yes | E65: =_xlfn.XLOOKUP(D65,'DEST TAGs'!$A$2:$A$5,'DEST TAGs'!$B$2:$B$5,"--",0) -> -- | F65: LH7VVX-R2E6V-GY5BUB | G65: AIB3USJ-Q3YFJY-K6Y6SG | H65: 45010.546 | I65: withdrawal | K65: currency | L65: XXRP | M65: -3645 | N65: 0.02 | O65: 0.80944334 | P65: =_xlfn.XLOOKUP(G65,'Kraken Trades'!$A$2:$A$28,'Kraken Trades'!$A$2:$A$28,"--",0) -> -- | Q65: =_xlfn.XLOOKUP(G65,'Kraken Trades'!$A$2:$A$28,'Kraken Trades'!$B$2:$B$28,"--",0) -> -- | R65: =_xlfn.XLOOKUP(G65,'Kraken Trades'!$A$2:$A$28,'Kraken Trades'!$C$2:$C$28,"--",0) -> -- | S65: =_xlfn.XLOOKUP(G65,'Kraken Trades'!$A$2:$A$28,'Kraken Trades'!$D$2:$D$28,"--",0) -> -- | T65: =_xlfn.XLOOKUP(G65,'Kraken Trades'!$A$2:$A$28,'Kraken Trades'!$E$2:$E$28,"--",0) -> -- | U65: =_xlfn.XLOOKUP(G65,'Kraken Trades'!$A$2:$A$28,'Kraken Trades'!$F$2:$F$28,"--",0) -> -- | V65: =_xlfn.XLOOKUP(G65,'Kraken Trades'!$A$2:$A$28,'Kraken Trades'!$G$2:$G$28,"--",0) -> -- | W65: =_xlfn.XLOOKUP(G65,'Kraken Trades'!$A$2:$A$28,'Kraken Trades'!$H$2:$H$28,"--",0) -> -- | X65: =_xlfn.XLOOKUP(G65,'Kraken Trades'!$A$2:$A$28,'Kraken Trades'!$I$2:$I$28,"--",0) -> -- | Y65: =_xlfn.XLOOKUP(G65,'Kraken Trades'!$A$2:$A$28,'Kraken Trades'!$J$2:$J$28,"--",0) -> -- | Z65: =_xlfn.XLOOKUP(G65,'Kraken Trades'!$A$2:$A$28,'Kraken Trades'!$K$2:$K$28,"--",0) -> -- | AA65: =_xlfn.XLOOKUP(G65,'Kraken Trades'!$A$2:$A$28,'Kraken Trades'!$L$2:$L$28,"--",0) -> -- | AB65: =_xlfn.XLOOKUP(G65,'Kraken Trades'!$A$2:$A$28,'Kraken Trades'!$M$2:$M$28,"--",0) -> --
A66: 45104 | B66: yes | E66: =_xlfn.XLOOKUP(D66,'DEST TAGs'!$A$2:$A$5,'DEST TAGs'!$B$2:$B$5,"--",0) -> -- | G66: QYP75F5-7D6LWD-ZDWEUH | H66: 45019.453 | I66: deposit | K66: currency | L66: ZGBP | M66: 1550 | N66: 0 | P66: =_xlfn.XLOOKUP(G66,'Kraken Trades'!$A$2:$A$28,'Kraken Trades'!$A$2:$A$28,"--",0) -> -- | Q66: =_xlfn.XLOOKUP(G66,'Kraken Trades'!$A$2:$A$28,'Kraken Trades'!$B$2:$B$28,"--",0) -> -- | R66: =_xlfn.XLOOKUP(G66,'Kraken Trades'!$A$2:$A$28,'Kraken Trades'!$C$2:$C$28,"--",0) -> -- | S66: =_xlfn.XLOOKUP(G66,'Kraken Trades'!$A$2:$A$28,'Kraken Trades'!$D$2:$D$28,"--",0) -> -- | T66: =_xlfn.XLOOKUP(G66,'Kraken Trades'!$A$2:$A$28,'Kraken Trades'!$E$2:$E$28,"--",0) -> -- | U66: =_xlfn.XLOOKUP(G66,'Kraken Trades'!$A$2:$A$28,'Kraken Trades'!$F$2:$F$28,"--",0) -> -- | V66: =_xlfn.XLOOKUP(G66,'Kraken Trades'!$A$2:$A$28,'Kraken Trades'!$G$2:$G$28,"--",0) -> -- | W66: =_xlfn.XLOOKUP(G66,'Kraken Trades'!$A$2:$A$28,'Kraken Trades'!$H$2:$H$28,"--",0) -> -- | X66: =_xlfn.XLOOKUP(G66,'Kraken Trades'!$A$2:$A$28,'Kraken Trades'!$I$2:$I$28,"--",0) -> -- | Y66: =_xlfn.XLOOKUP(G66,'Kraken Trades'!$A$2:$A$28,'Kraken Trades'!$J$2:$J$28,"--",0) -> -- | Z66: =_xlfn.XLOOKUP(G66,'Kraken Trades'!$A$2:$A$28,'Kraken Trades'!$K$2:$K$28,"--",0) -> -- | AA66: =_xlfn.XLOOKUP(G66,'Kraken Trades'!$A$2:$A$28,'Kraken Trades'!$L$2:$L$28,"--",0) -> -- | AB66: =_xlfn.XLOOKUP(G66,'Kraken Trades'!$A$2:$A$28,'Kraken Trades'!$M$2:$M$28,"--",0) -> --
A67: 45104 | B67: yes | E67: =_xlfn.XLOOKUP(D67,'DEST TAGs'!$A$2:$A$5,'DEST TAGs'!$B$2:$B$5,"--",0) -> -- | F67: LYXK6H-OS7NU-UQ3EFX | G67: QYP75F5-7D6LWD-ZDWEUH | H67: 45019.479 | I67: deposit | K67: currency | L67: ZGBP | M67: 1550 | N67: 0 | O67: 1740.3627 | P67: =_xlfn.XLOOKUP(G67,'Kraken Trades'!$A$2:$A$28,'Kraken Trades'!$A$2:$A$28,"--",0) -> -- | Q67: =_xlfn.XLOOKUP(G67,'Kraken Trades'!$A$2:$A$28,'Kraken Trades'!$B$2:$B$28,"--",0) -> -- | R67: =_xlfn.XLOOKUP(G67,'Kraken Trades'!$A$2:$A$28,'Kraken Trades'!$C$2:$C$28,"--",0) -> -- | S67: =_xlfn.XLOOKUP(G67,'Kraken Trades'!$A$2:$A$28,'Kraken Trades'!$D$2:$D$28,"--",0) -> -- | T67: =_xlfn.XLOOKUP(G67,'Kraken Trades'!$A$2:$A$28,'Kraken Trades'!$E$2:$E$28,"--",0) -> -- | U67: =_xlfn.XLOOKUP(G67,'Kraken Trades'!$A$2:$A$28,'Kraken Trades'!$F$2:$F$28,"--",0) -> -- | V67: =_xlfn.XLOOKUP(G67,'Kraken Trades'!$A$2:$A$28,'Kraken Trades'!$G$2:$G$28,"--",0) -> -- | W67: =_xlfn.XLOOKUP(G67,'Kraken Trades'!$A$2:$A$28,'Kraken Trades'!$H$2:$H$28,"--",0) -> -- | X67: =_xlfn.XLOOKUP(G67,'Kraken Trades'!$A$2:$A$28,'Kraken Trades'!$I$2:$I$28,"--",0) -> -- | Y67: =_xlfn.XLOOKUP(G67,'Kraken Trades'!$A$2:$A$28,'Kraken Trades'!$J$2:$J$28,"--",0) -> -- | Z67: =_xlfn.XLOOKUP(G67,'Kraken Trades'!$A$2:$A$28,'Kraken Trades'!$K$2:$K$28,"--",0) -> -- | AA67: =_xlfn.XLOOKUP(G67,'Kraken Trades'!$A$2:$A$28,'Kraken Trades'!$L$2:$L$28,"--",0) -> -- | AB67: =_xlfn.XLOOKUP(G67,'Kraken Trades'!$A$2:$A$28,'Kraken Trades'!$M$2:$M$28,"--",0) -> --
A68: 45104 | B68: yes | E68: =_xlfn.XLOOKUP(D68,'DEST TAGs'!$A$2:$A$5,'DEST TAGs'!$B$2:$B$5,"--",0) -> -- | F68: LCCMR6-CUGBS-OVGXI6 | G68: T2SYNS-QPPLR-RWCR6N | H68: 45019.502 | I68: trade | K68: currency | L68: ZGBP | M68: -1536.5425 | N68: 0 | O68: 203.8202 | P68: =_xlfn.XLOOKUP(G68,'Kraken Trades'!$A$2:$A$28,'Kraken Trades'!$A$2:$A$28,"--",0) -> T2SYNS-QPPLR-RWCR6N | Q68: =_xlfn.XLOOKUP(G68,'Kraken Trades'!$A$2:$A$28,'Kraken Trades'!$B$2:$B$28,"--",0) -> OKJB6I-BNMCX-D6SSRD | R68: =_xlfn.XLOOKUP(G68,'Kraken Trades'!$A$2:$A$28,'Kraken Trades'!$C$2:$C$28,"--",0) -> XRPGBP | S68: =_xlfn.XLOOKUP(G68,'Kraken Trades'!$A$2:$A$28,'Kraken Trades'!$D$2:$D$28,"--",0) -> 0.002130787 | T68: =_xlfn.XLOOKUP(G68,'Kraken Trades'!$A$2:$A$28,'Kraken Trades'!$E$2:$E$28,"--",0) -> buy | U68: =_xlfn.XLOOKUP(G68,'Kraken Trades'!$A$2:$A$28,'Kraken Trades'!$F$2:$F$28,"--",0) -> market | V68: =_xlfn.XLOOKUP(G68,'Kraken Trades'!$A$2:$A$28,'Kraken Trades'!$G$2:$G$28,"--",0) -> 0.41528174 | W68: =_xlfn.XLOOKUP(G68,'Kraken Trades'!$A$2:$A$28,'Kraken Trades'!$H$2:$H$28,"--",0) -> 1536.5424 | X68: =_xlfn.XLOOKUP(G68,'Kraken Trades'!$A$2:$A$28,'Kraken Trades'!$I$2:$I$28,"--",0) -> 3.9950103 | Y68: =_xlfn.XLOOKUP(G68,'Kraken Trades'!$A$2:$A$28,'Kraken Trades'!$J$2:$J$28,"--",0) -> 3700 | Z68: =_xlfn.XLOOKUP(G68,'Kraken Trades'!$A$2:$A$28,'Kraken Trades'!$K$2:$K$28,"--",0) -> 0 | AA68: =_xlfn.XLOOKUP(G68,'Kraken Trades'!$A$2:$A$28,'Kraken Trades'!$L$2:$L$28,"--",0) -> initiated | AB68: =_xlfn.XLOOKUP(G68,'Kraken Trades'!$A$2:$A$28,'Kraken Trades'!$M$2:$M$28,"--",0) -> LR74IH-UWJYR-KCPT4I,LZCKOU-6WH7Y-OAOCFE,LCCMR6-CUGBS-OVGXI6
A69: 45104 | B69: yes | E69: =_xlfn.XLOOKUP(D69,'DEST TAGs'!$A$2:$A$5,'DEST TAGs'!$B$2:$B$5,"--",0) -> -- | F69: LZCKOU-6WH7Y-OAOCFE | G69: T2SYNS-QPPLR-RWCR6N | H69: 45019.502 | I69: trade | K69: currency | L69: XXRP | M69: 3700 | N69: 0 | O69: 3700.8094 | P69: =_xlfn.XLOOKUP(G69,'Kraken Trades'!$A$2:$A$28,'Kraken Trades'!$A$2:$A$28,"--",0) -> T2SYNS-QPPLR-RWCR6N | Q69: =_xlfn.XLOOKUP(G69,'Kraken Trades'!$A$2:$A$28,'Kraken Trades'!$B$2:$B$28,"--",0) -> OKJB6I-BNMCX-D6SSRD | R69: =_xlfn.XLOOKUP(G69,'Kraken Trades'!$A$2:$A$28,'Kraken Trades'!$C$2:$C$28,"--",0) -> XRPGBP | S69: =_xlfn.XLOOKUP(G69,'Kraken Trades'!$A$2:$A$28,'Kraken Trades'!$D$2:$D$28,"--",0) -> 0.002130787 | T69: =_xlfn.XLOOKUP(G69,'Kraken Trades'!$A$2:$A$28,'Kraken Trades'!$E$2:$E$28,"--",0) -> buy | U69: =_xlfn.XLOOKUP(G69,'Kraken Trades'!$A$2:$A$28,'Kraken Trades'!$F$2:$F$28,"--",0) -> market | V69: =_xlfn.XLOOKUP(G69,'Kraken Trades'!$A$2:$A$28,'Kraken Trades'!$G$2:$G$28,"--",0) -> 0.41528174 | W69: =_xlfn.XLOOKUP(G69,'Kraken Trades'!$A$2:$A$28,'Kraken Trades'!$H$2:$H$28,"--",0) -> 1536.5424 | X69: =_xlfn.XLOOKUP(G69,'Kraken Trades'!$A$2:$A$28,'Kraken Trades'!$I$2:$I$28,"--",0) -> 3.9950103 | Y69: =_xlfn.XLOOKUP(G69,'Kraken Trades'!$A$2:$A$28,'Kraken Trades'!$J$2:$J$28,"--",0) -> 3700 | Z69: =_xlfn.XLOOKUP(G69,'Kraken Trades'!$A$2:$A$28,'Kraken Trades'!$K$2:$K$28,"--",0) -> 0 | AA69: =_xlfn.XLOOKUP(G69,'Kraken Trades'!$A$2:$A$28,'Kraken Trades'!$L$2:$L$28,"--",0) -> initiated | AB69: =_xlfn.XLOOKUP(G69,'Kraken Trades'!$A$2:$A$28,'Kraken Trades'!$M$2:$M$28,"--",0) -> LR74IH-UWJYR-KCPT4I,LZCKOU-6WH7Y-OAOCFE,LCCMR6-CUGBS-OVGXI6
A70: 45104 | B70: yes | E70: =_xlfn.XLOOKUP(D70,'DEST TAGs'!$A$2:$A$5,'DEST TAGs'!$B$2:$B$5,"--",0) -> -- | F70: LR74IH-UWJYR-KCPT4I | G70: T2SYNS-QPPLR-RWCR6N | H70: 45019.502 | I70: trade | K70: currency | L70: KFEE | M70: 0 | N70: 494.46 | O70: 6131.91 | P70: =_xlfn.XLOOKUP(G70,'Kraken Trades'!$A$2:$A$28,'Kraken Trades'!$A$2:$A$28,"--",0) -> T2SYNS-QPPLR-RWCR6N | Q70: =_xlfn.XLOOKUP(G70,'Kraken Trades'!$A$2:$A$28,'Kraken Trades'!$B$2:$B$28,"--",0) -> OKJB6I-BNMCX-D6SSRD | R70: =_xlfn.XLOOKUP(G70,'Kraken Trades'!$A$2:$A$28,'Kraken Trades'!$C$2:$C$28,"--",0) -> XRPGBP | S70: =_xlfn.XLOOKUP(G70,'Kraken Trades'!$A$2:$A$28,'Kraken Trades'!$D$2:$D$28,"--",0) -> 0.002130787 | T70: =_xlfn.XLOOKUP(G70,'Kraken Trades'!$A$2:$A$28,'Kraken Trades'!$E$2:$E$28,"--",0) -> buy | U70: =_xlfn.XLOOKUP(G70,'Kraken Trades'!$A$2:$A$28,'Kraken Trades'!$F$2:$F$28,"--",0) -> market | V70: =_xlfn.XLOOKUP(G70,'Kraken Trades'!$A$2:$A$28,'Kraken Trades'!$G$2:$G$28,"--",0) -> 0.41528174 | W70: =_xlfn.XLOOKUP(G70,'Kraken Trades'!$A$2:$A$28,'Kraken Trades'!$H$2:$H$28,"--",0) -> 1536.5424 | X70: =_xlfn.XLOOKUP(G70,'Kraken Trades'!$A$2:$A$28,'Kraken Trades'!$I$2:$I$28,"--",0) -> 3.9950103 | Y70: =_xlfn.XLOOKUP(G70,'Kraken Trades'!$A$2:$A$28,'Kraken Trades'!$J$2:$J$28,"--",0) -> 3700 | Z70: =_xlfn.XLOOKUP(G70,'Kraken Trades'!$A$2:$A$28,'Kraken Trades'!$K$2:$K$28,"--",0) -> 0 | AA70: =_xlfn.XLOOKUP(G70,'Kraken Trades'!$A$2:$A$28,'Kraken Trades'!$L$2:$L$28,"--",0) -> initiated | AB70: =_xlfn.XLOOKUP(G70,'Kraken Trades'!$A$2:$A$28,'Kraken Trades'!$M$2:$M$28,"--",0) -> LR74IH-UWJYR-KCPT4I,LZCKOU-6WH7Y-OAOCFE,LCCMR6-CUGBS-OVGXI6
A71: 45104 | B71: yes | E71: =_xlfn.XLOOKUP(D71,'DEST TAGs'!$A$2:$A$5,'DEST TAGs'!$B$2:$B$5,"--",0) -> -- | G71: AIBPXHS-TSESUY-HV7VQM | H71: 45019.511 | I71: withdrawal | K71: currency | L71: XXRP | M71: -3700 | N71: 0.02 | P71: =_xlfn.XLOOKUP(G71,'Kraken Trades'!$A$2:$A$28,'Kraken Trades'!$A$2:$A$28,"--",0) -> -- | Q71: =_xlfn.XLOOKUP(G71,'Kraken Trades'!$A$2:$A$28,'Kraken Trades'!$B$2:$B$28,"--",0) -> -- | R71: =_xlfn.XLOOKUP(G71,'Kraken Trades'!$A$2:$A$28,'Kraken Trades'!$C$2:$C$28,"--",0) -> -- | S71: =_xlfn.XLOOKUP(G71,'Kraken Trades'!$A$2:$A$28,'Kraken Trades'!$D$2:$D$28,"--",0) -> -- | T71: =_xlfn.XLOOKUP(G71,'Kraken Trades'!$A$2:$A$28,'Kraken Trades'!$E$2:$E$28,"--",0) -> -- | U71: =_xlfn.XLOOKUP(G71,'Kraken Trades'!$A$2:$A$28,'Kraken Trades'!$F$2:$F$28,"--",0) -> -- | V71: =_xlfn.XLOOKUP(G71,'Kraken Trades'!$A$2:$A$28,'Kraken Trades'!$G$2:$G$28,"--",0) -> -- | W71: =_xlfn.XLOOKUP(G71,'Kraken Trades'!$A$2:$A$28,'Kraken Trades'!$H$2:$H$28,"--",0) -> -- | X71: =_xlfn.XLOOKUP(G71,'Kraken Trades'!$A$2:$A$28,'Kraken Trades'!$I$2:$I$28,"--",0) -> -- | Y71: =_xlfn.XLOOKUP(G71,'Kraken Trades'!$A$2:$A$28,'Kraken Trades'!$J$2:$J$28,"--",0) -> -- | Z71: =_xlfn.XLOOKUP(G71,'Kraken Trades'!$A$2:$A$28,'Kraken Trades'!$K$2:$K$28,"--",0) -> -- | AA71: =_xlfn.XLOOKUP(G71,'Kraken Trades'!$A$2:$A$28,'Kraken Trades'!$L$2:$L$28,"--",0) -> -- | AB71: =_xlfn.XLOOKUP(G71,'Kraken Trades'!$A$2:$A$28,'Kraken Trades'!$M$2:$M$28,"--",0) -> --
A72: 45104 | B72: yes | C72: https://bithomp.com/explorer/89DA6E0506E88DEFB02147D8E2E7C4E531A429CF2C0F17FBF6B4D4A4431648A3 | D72: 518294827 | E72: =_xlfn.XLOOKUP(D72,'DEST TAGs'!$A$2:$A$5,'DEST TAGs'!$B$2:$B$5,"--",0) -> Alex Smirnov | F72: LQDQTC-NRO35-7XLSNS | G72: AIBPXHS-TSESUY-HV7VQM | H72: 45019.512 | I72: withdrawal | K72: currency | L72: XXRP | M72: -3700 | N72: 0.02 | O72: 0.78944334 | P72: =_xlfn.XLOOKUP(G72,'Kraken Trades'!$A$2:$A$28,'Kraken Trades'!$A$2:$A$28,"--",0) -> -- | Q72: =_xlfn.XLOOKUP(G72,'Kraken Trades'!$A$2:$A$28,'Kraken Trades'!$B$2:$B$28,"--",0) -> -- | R72: =_xlfn.XLOOKUP(G72,'Kraken Trades'!$A$2:$A$28,'Kraken Trades'!$C$2:$C$28,"--",0) -> -- | S72: =_xlfn.XLOOKUP(G72,'Kraken Trades'!$A$2:$A$28,'Kraken Trades'!$D$2:$D$28,"--",0) -> -- | T72: =_xlfn.XLOOKUP(G72,'Kraken Trades'!$A$2:$A$28,'Kraken Trades'!$E$2:$E$28,"--",0) -> -- | U72: =_xlfn.XLOOKUP(G72,'Kraken Trades'!$A$2:$A$28,'Kraken Trades'!$F$2:$F$28,"--",0) -> -- | V72: =_xlfn.XLOOKUP(G72,'Kraken Trades'!$A$2:$A$28,'Kraken Trades'!$G$2:$G$28,"--",0) -> -- | W72: =_xlfn.XLOOKUP(G72,'Kraken Trades'!$A$2:$A$28,'Kraken Trades'!$H$2:$H$28,"--",0) -> -- | X72: =_xlfn.XLOOKUP(G72,'Kraken Trades'!$A$2:$A$28,'Kraken Trades'!$I$2:$I$28,"--",0) -> -- | Y72: =_xlfn.XLOOKUP(G72,'Kraken Trades'!$A$2:$A$28,'Kraken Trades'!$J$2:$J$28,"--",0) -> -- | Z72: =_xlfn.XLOOKUP(G72,'Kraken Trades'!$A$2:$A$28,'Kraken Trades'!$K$2:$K$28,"--",0) -> -- | AA72: =_xlfn.XLOOKUP(G72,'Kraken Trades'!$A$2:$A$28,'Kraken Trades'!$L$2:$L$28,"--",0) -> -- | AB72: =_xlfn.XLOOKUP(G72,'Kraken Trades'!$A$2:$A$28,'Kraken Trades'!$M$2:$M$28,"--",0) -> --
A73: 45104 | B73: yes | E73: =_xlfn.XLOOKUP(D73,'DEST TAGs'!$A$2:$A$5,'DEST TAGs'!$B$2:$B$5,"--",0) -> -- | G73: QYPZJCI-NGXRPJ-YY5I73 | H73: 45028.464 | I73: deposit | K73: currency | L73: ZGBP | M73: 800 | N73: 0 | P73: =_xlfn.XLOOKUP(G73,'Kraken Trades'!$A$2:$A$28,'Kraken Trades'!$A$2:$A$28,"--",0) -> -- | Q73: =_xlfn.XLOOKUP(G73,'Kraken Trades'!$A$2:$A$28,'Kraken Trades'!$B$2:$B$28,"--",0) -> -- | R73: =_xlfn.XLOOKUP(G73,'Kraken Trades'!$A$2:$A$28,'Kraken Trades'!$C$2:$C$28,"--",0) -> -- | S73: =_xlfn.XLOOKUP(G73,'Kraken Trades'!$A$2:$A$28,'Kraken Trades'!$D$2:$D$28,"--",0) -> -- | T73: =_xlfn.XLOOKUP(G73,'Kraken Trades'!$A$2:$A$28,'Kraken Trades'!$E$2:$E$28,"--",0) -> -- | U73: =_xlfn.XLOOKUP(G73,'Kraken Trades'!$A$2:$A$28,'Kraken Trades'!$F$2:$F$28,"--",0) -> -- | V73: =_xlfn.XLOOKUP(G73,'Kraken Trades'!$A$2:$A$28,'Kraken Trades'!$G$2:$G$28,"--",0) -> -- | W73: =_xlfn.XLOOKUP(G73,'Kraken Trades'!$A$2:$A$28,'Kraken Trades'!$H$2:$H$28,"--",0) -> -- | X73: =_xlfn.XLOOKUP(G73,'Kraken Trades'!$A$2:$A$28,'Kraken Trades'!$I$2:$I$28,"--",0) -> -- | Y73: =_xlfn.XLOOKUP(G73,'Kraken Trades'!$A$2:$A$28,'Kraken Trades'!$J$2:$J$28,"--",0) -> -- | Z73: =_xlfn.XLOOKUP(G73,'Kraken Trades'!$A$2:$A$28,'Kraken Trades'!$K$2:$K$28,"--",0) -> -- | AA73: =_xlfn.XLOOKUP(G73,'Kraken Trades'!$A$2:$A$28,'Kraken Trades'!$L$2:$L$28,"--",0) -> -- | AB73: =_xlfn.XLOOKUP(G73,'Kraken Trades'!$A$2:$A$28,'Kraken Trades'!$M$2:$M$28,"--",0) -> --
A74: 45104 | B74: yes | E74: =_xlfn.XLOOKUP(D74,'DEST TAGs'!$A$2:$A$5,'DEST TAGs'!$B$2:$B$5,"--",0) -> -- | F74: LKXLOW-4MTVZ-NQ47LP | G74: QYPZJCI-NGXRPJ-YY5I73 | H74: 45028.498 | I74: deposit | K74: currency | L74: ZGBP | M74: 800 | N74: 0 | O74: 1003.8202 | P74: =_xlfn.XLOOKUP(G74,'Kraken Trades'!$A$2:$A$28,'Kraken Trades'!$A$2:$A$28,"--",0) -> -- | Q74: =_xlfn.XLOOKUP(G74,'Kraken Trades'!$A$2:$A$28,'Kraken Trades'!$B$2:$B$28,"--",0) -> -- | R74: =_xlfn.XLOOKUP(G74,'Kraken Trades'!$A$2:$A$28,'Kraken Trades'!$C$2:$C$28,"--",0) -> -- | S74: =_xlfn.XLOOKUP(G74,'Kraken Trades'!$A$2:$A$28,'Kraken Trades'!$D$2:$D$28,"--",0) -> -- | T74: =_xlfn.XLOOKUP(G74,'Kraken Trades'!$A$2:$A$28,'Kraken Trades'!$E$2:$E$28,"--",0) -> -- | U74: =_xlfn.XLOOKUP(G74,'Kraken Trades'!$A$2:$A$28,'Kraken Trades'!$F$2:$F$28,"--",0) -> -- | V74: =_xlfn.XLOOKUP(G74,'Kraken Trades'!$A$2:$A$28,'Kraken Trades'!$G$2:$G$28,"--",0) -> -- | W74: =_xlfn.XLOOKUP(G74,'Kraken Trades'!$A$2:$A$28,'Kraken Trades'!$H$2:$H$28,"--",0) -> -- | X74: =_xlfn.XLOOKUP(G74,'Kraken Trades'!$A$2:$A$28,'Kraken Trades'!$I$2:$I$28,"--",0) -> -- | Y74: =_xlfn.XLOOKUP(G74,'Kraken Trades'!$A$2:$A$28,'Kraken Trades'!$J$2:$J$28,"--",0) -> -- | Z74: =_xlfn.XLOOKUP(G74,'Kraken Trades'!$A$2:$A$28,'Kraken Trades'!$K$2:$K$28,"--",0) -> -- | AA74: =_xlfn.XLOOKUP(G74,'Kraken Trades'!$A$2:$A$28,'Kraken Trades'!$L$2:$L$28,"--",0) -> -- | AB74: =_xlfn.XLOOKUP(G74,'Kraken Trades'!$A$2:$A$28,'Kraken Trades'!$M$2:$M$28,"--",0) -> --
A75: 45104 | B75: yes | E75: =_xlfn.XLOOKUP(D75,'DEST TAGs'!$A$2:$A$5,'DEST TAGs'!$B$2:$B$5,"--",0) -> -- | F75: L4UFCK-RHGHP-4I25WP | G75: TYKAIB-CIGAO-B5OBU6 | H75: 45028.513 | I75: trade | K75: currency | L75: ZGBP | M75: -800.5605 | N75: 0 | O75: 203.2597 | P75: =_xlfn.XLOOKUP(G75,'Kraken Trades'!$A$2:$A$28,'Kraken Trades'!$A$2:$A$28,"--",0) -> TYKAIB-CIGAO-B5OBU6 | Q75: =_xlfn.XLOOKUP(G75,'Kraken Trades'!$A$2:$A$28,'Kraken Trades'!$B$2:$B$28,"--",0) -> OY7NWP-OJ4KS-EHEOGI | R75: =_xlfn.XLOOKUP(G75,'Kraken Trades'!$A$2:$A$28,'Kraken Trades'!$C$2:$C$28,"--",0) -> XRPGBP | S75: =_xlfn.XLOOKUP(G75,'Kraken Trades'!$A$2:$A$28,'Kraken Trades'!$D$2:$D$28,"--",0) -> 0.013769676 | T75: =_xlfn.XLOOKUP(G75,'Kraken Trades'!$A$2:$A$28,'Kraken Trades'!$E$2:$E$28,"--",0) -> buy | U75: =_xlfn.XLOOKUP(G75,'Kraken Trades'!$A$2:$A$28,'Kraken Trades'!$F$2:$F$28,"--",0) -> market | V75: =_xlfn.XLOOKUP(G75,'Kraken Trades'!$A$2:$A$28,'Kraken Trades'!$G$2:$G$28,"--",0) -> 0.40534709 | W75: =_xlfn.XLOOKUP(G75,'Kraken Trades'!$A$2:$A$28,'Kraken Trades'!$H$2:$H$28,"--",0) -> 800.56051 | X75: =_xlfn.XLOOKUP(G75,'Kraken Trades'!$A$2:$A$28,'Kraken Trades'!$I$2:$I$28,"--",0) -> 2.0814573 | Y75: =_xlfn.XLOOKUP(G75,'Kraken Trades'!$A$2:$A$28,'Kraken Trades'!$J$2:$J$28,"--",0) -> 1975 | Z75: =_xlfn.XLOOKUP(G75,'Kraken Trades'!$A$2:$A$28,'Kraken Trades'!$K$2:$K$28,"--",0) -> 0 | AA75: =_xlfn.XLOOKUP(G75,'Kraken Trades'!$A$2:$A$28,'Kraken Trades'!$L$2:$L$28,"--",0) -> initiated | AB75: =_xlfn.XLOOKUP(G75,'Kraken Trades'!$A$2:$A$28,'Kraken Trades'!$M$2:$M$28,"--",0) -> LIGGLP-ATT37-DVOVHS,LXNJSC-GVZ6M-MTAFRA,L4UFCK-RHGHP-4I25WP
A76: 45104 | B76: yes | E76: =_xlfn.XLOOKUP(D76,'DEST TAGs'!$A$2:$A$5,'DEST TAGs'!$B$2:$B$5,"--",0) -> -- | F76: LXNJSC-GVZ6M-MTAFRA | G76: TYKAIB-CIGAO-B5OBU6 | H76: 45028.513 | I76: trade | K76: currency | L76: XXRP | M76: 1975 | N76: 0 | O76: 1975.7894 | P76: =_xlfn.XLOOKUP(G76,'Kraken Trades'!$A$2:$A$28,'Kraken Trades'!$A$2:$A$28,"--",0) -> TYKAIB-CIGAO-B5OBU6 | Q76: =_xlfn.XLOOKUP(G76,'Kraken Trades'!$A$2:$A$28,'Kraken Trades'!$B$2:$B$28,"--",0) -> OY7NWP-OJ4KS-EHEOGI | R76: =_xlfn.XLOOKUP(G76,'Kraken Trades'!$A$2:$A$28,'Kraken Trades'!$C$2:$C$28,"--",0) -> XRPGBP | S76: =_xlfn.XLOOKUP(G76,'Kraken Trades'!$A$2:$A$28,'Kraken Trades'!$D$2:$D$28,"--",0) -> 0.013769676 | T76: =_xlfn.XLOOKUP(G76,'Kraken Trades'!$A$2:$A$28,'Kraken Trades'!$E$2:$E$28,"--",0) -> buy | U76: =_xlfn.XLOOKUP(G76,'Kraken Trades'!$A$2:$A$28,'Kraken Trades'!$F$2:$F$28,"--",0) -> market | V76: =_xlfn.XLOOKUP(G76,'Kraken Trades'!$A$2:$A$28,'Kraken Trades'!$G$2:$G$28,"--",0) -> 0.40534709 | W76: =_xlfn.XLOOKUP(G76,'Kraken Trades'!$A$2:$A$28,'Kraken Trades'!$H$2:$H$28,"--",0) -> 800.56051 | X76: =_xlfn.XLOOKUP(G76,'Kraken Trades'!$A$2:$A$28,'Kraken Trades'!$I$2:$I$28,"--",0) -> 2.0814573 | Y76: =_xlfn.XLOOKUP(G76,'Kraken Trades'!$A$2:$A$28,'Kraken Trades'!$J$2:$J$28,"--",0) -> 1975 | Z76: =_xlfn.XLOOKUP(G76,'Kraken Trades'!$A$2:$A$28,'Kraken Trades'!$K$2:$K$28,"--",0) -> 0 | AA76: =_xlfn.XLOOKUP(G76,'Kraken Trades'!$A$2:$A$28,'Kraken Trades'!$L$2:$L$28,"--",0) -> initiated | AB76: =_xlfn.XLOOKUP(G76,'Kraken Trades'!$A$2:$A$28,'Kraken Trades'!$M$2:$M$28,"--",0) -> LIGGLP-ATT37-DVOVHS,LXNJSC-GVZ6M-MTAFRA,L4UFCK-RHGHP-4I25WP
A77: 45104 | B77: yes | E77: =_xlfn.XLOOKUP(D77,'DEST TAGs'!$A$2:$A$5,'DEST TAGs'!$B$2:$B$5,"--",0) -> -- | F77: LIGGLP-ATT37-DVOVHS | G77: TYKAIB-CIGAO-B5OBU6 | H77: 45028.513 | I77: trade | K77: currency | L77: KFEE | M77: 0 | N77: 258.2 | O77: 5873.71 | P77: =_xlfn.XLOOKUP(G77,'Kraken Trades'!$A$2:$A$28,'Kraken Trades'!$A$2:$A$28,"--",0) -> TYKAIB-CIGAO-B5OBU6 | Q77: =_xlfn.XLOOKUP(G77,'Kraken Trades'!$A$2:$A$28,'Kraken Trades'!$B$2:$B$28,"--",0) -> OY7NWP-OJ4KS-EHEOGI | R77: =_xlfn.XLOOKUP(G77,'Kraken Trades'!$A$2:$A$28,'Kraken Trades'!$C$2:$C$28,"--",0) -> XRPGBP | S77: =_xlfn.XLOOKUP(G77,'Kraken Trades'!$A$2:$A$28,'Kraken Trades'!$D$2:$D$28,"--",0) -> 0.013769676 | T77: =_xlfn.XLOOKUP(G77,'Kraken Trades'!$A$2:$A$28,'Kraken Trades'!$E$2:$E$28,"--",0) -> buy | U77: =_xlfn.XLOOKUP(G77,'Kraken Trades'!$A$2:$A$28,'Kraken Trades'!$F$2:$F$28,"--",0) -> market | V77: =_xlfn.XLOOKUP(G77,'Kraken Trades'!$A$2:$A$28,'Kraken Trades'!$G$2:$G$28,"--",0) -> 0.40534709 | W77: =_xlfn.XLOOKUP(G77,'Kraken Trades'!$A$2:$A$28,'Kraken Trades'!$H$2:$H$28,"--",0) -> 800.56051 | X77: =_xlfn.XLOOKUP(G77,'Kraken Trades'!$A$2:$A$28,'Kraken Trades'!$I$2:$I$28,"--",0) -> 2.0814573 | Y77: =_xlfn.XLOOKUP(G77,'Kraken Trades'!$A$2:$A$28,'Kraken Trades'!$J$2:$J$28,"--",0) -> 1975 | Z77: =_xlfn.XLOOKUP(G77,'Kraken Trades'!$A$2:$A$28,'Kraken Trades'!$K$2:$K$28,"--",0) -> 0 | AA77: =_xlfn.XLOOKUP(G77,'Kraken Trades'!$A$2:$A$28,'Kraken Trades'!$L$2:$L$28,"--",0) -> initiated | AB77: =_xlfn.XLOOKUP(G77,'Kraken Trades'!$A$2:$A$28,'Kraken Trades'!$M$2:$M$28,"--",0) -> LIGGLP-ATT37-DVOVHS,LXNJSC-GVZ6M-MTAFRA,L4UFCK-RHGHP-4I25WP
A78: 45104 | B78: yes | E78: =_xlfn.XLOOKUP(D78,'DEST TAGs'!$A$2:$A$5,'DEST TAGs'!$B$2:$B$5,"--",0) -> -- | G78: AIB62NF-ZLE33W-OVK7MF | H78: 45028.514 | I78: withdrawal | K78: currency | L78: XXRP | M78: -1975 | N78: 0.02 | P78: =_xlfn.XLOOKUP(G78,'Kraken Trades'!$A$2:$A$28,'Kraken Trades'!$A$2:$A$28,"--",0) -> -- | Q78: =_xlfn.XLOOKUP(G78,'Kraken Trades'!$A$2:$A$28,'Kraken Trades'!$B$2:$B$28,"--",0) -> -- | R78: =_xlfn.XLOOKUP(G78,'Kraken Trades'!$A$2:$A$28,'Kraken Trades'!$C$2:$C$28,"--",0) -> -- | S78: =_xlfn.XLOOKUP(G78,'Kraken Trades'!$A$2:$A$28,'Kraken Trades'!$D$2:$D$28,"--",0) -> -- | T78: =_xlfn.XLOOKUP(G78,'Kraken Trades'!$A$2:$A$28,'Kraken Trades'!$E$2:$E$28,"--",0) -> -- | U78: =_xlfn.XLOOKUP(G78,'Kraken Trades'!$A$2:$A$28,'Kraken Trades'!$F$2:$F$28,"--",0) -> -- | V78: =_xlfn.XLOOKUP(G78,'Kraken Trades'!$A$2:$A$28,'Kraken Trades'!$G$2:$G$28,"--",0) -> -- | W78: =_xlfn.XLOOKUP(G78,'Kraken Trades'!$A$2:$A$28,'Kraken Trades'!$H$2:$H$28,"--",0) -> -- | X78: =_xlfn.XLOOKUP(G78,'Kraken Trades'!$A$2:$A$28,'Kraken Trades'!$I$2:$I$28,"--",0) -> -- | Y78: =_xlfn.XLOOKUP(G78,'Kraken Trades'!$A$2:$A$28,'Kraken Trades'!$J$2:$J$28,"--",0) -> -- | Z78: =_xlfn.XLOOKUP(G78,'Kraken Trades'!$A$2:$A$28,'Kraken Trades'!$K$2:$K$28,"--",0) -> -- | AA78: =_xlfn.XLOOKUP(G78,'Kraken Trades'!$A$2:$A$28,'Kraken Trades'!$L$2:$L$28,"--",0) -> -- | AB78: =_xlfn.XLOOKUP(G78,'Kraken Trades'!$A$2:$A$28,'Kraken Trades'!$M$2:$M$28,"--",0) -> --
A79: 45104 | B79: yes | C79: https://bithomp.com/explorer/183EDFFF6925D95DC65C5D0CB5D48F4EEC77B7304AD0D56DBAD0FE6A2082092F | D79: 547786843 | E79: =_xlfn.XLOOKUP(D79,'DEST TAGs'!$A$2:$A$5,'DEST TAGs'!$B$2:$B$5,"--",0) -> Aleksey Trofimov | F79: LUYDL4-3IESW-3NOXWF | G79: AIB62NF-ZLE33W-OVK7MF | H79: 45028.515 | I79: withdrawal | K79: currency | L79: XXRP | M79: -1975 | N79: 0.02 | O79: 0.76944334 | P79: =_xlfn.XLOOKUP(G79,'Kraken Trades'!$A$2:$A$28,'Kraken Trades'!$A$2:$A$28,"--",0) -> -- | Q79: =_xlfn.XLOOKUP(G79,'Kraken Trades'!$A$2:$A$28,'Kraken Trades'!$B$2:$B$28,"--",0) -> -- | R79: =_xlfn.XLOOKUP(G79,'Kraken Trades'!$A$2:$A$28,'Kraken Trades'!$C$2:$C$28,"--",0) -> -- | S79: =_xlfn.XLOOKUP(G79,'Kraken Trades'!$A$2:$A$28,'Kraken Trades'!$D$2:$D$28,"--",0) -> -- | T79: =_xlfn.XLOOKUP(G79,'Kraken Trades'!$A$2:$A$28,'Kraken Trades'!$E$2:$E$28,"--",0) -> -- | U79: =_xlfn.XLOOKUP(G79,'Kraken Trades'!$A$2:$A$28,'Kraken Trades'!$F$2:$F$28,"--",0) -> -- | V79: =_xlfn.XLOOKUP(G79,'Kraken Trades'!$A$2:$A$28,'Kraken Trades'!$G$2:$G$28,"--",0) -> -- | W79: =_xlfn.XLOOKUP(G79,'Kraken Trades'!$A$2:$A$28,'Kraken Trades'!$H$2:$H$28,"--",0) -> -- | X79: =_xlfn.XLOOKUP(G79,'Kraken Trades'!$A$2:$A$28,'Kraken Trades'!$I$2:$I$28,"--",0) -> -- | Y79: =_xlfn.XLOOKUP(G79,'Kraken Trades'!$A$2:$A$28,'Kraken Trades'!$J$2:$J$28,"--",0) -> -- | Z79: =_xlfn.XLOOKUP(G79,'Kraken Trades'!$A$2:$A$28,'Kraken Trades'!$K$2:$K$28,"--",0) -> -- | AA79: =_xlfn.XLOOKUP(G79,'Kraken Trades'!$A$2:$A$28,'Kraken Trades'!$L$2:$L$28,"--",0) -> -- | AB79: =_xlfn.XLOOKUP(G79,'Kraken Trades'!$A$2:$A$28,'Kraken Trades'!$M$2:$M$28,"--",0) -> --
A80: 45104 | B80: yes | E80: =_xlfn.XLOOKUP(D80,'DEST TAGs'!$A$2:$A$5,'DEST TAGs'!$B$2:$B$5,"--",0) -> -- | F80: LWSASC-3X4CP-OD5E5A | G80: TABUT2-6TCYQ-U2OQ3G | H80: 45032.735 | I80: trade | K80: currency | L80: ZGBP | M80: -98.8575 | N80: 0 | O80: 104.4022 | P80: =_xlfn.XLOOKUP(G80,'Kraken Trades'!$A$2:$A$28,'Kraken Trades'!$A$2:$A$28,"--",0) -> TABUT2-6TCYQ-U2OQ3G | Q80: =_xlfn.XLOOKUP(G80,'Kraken Trades'!$A$2:$A$28,'Kraken Trades'!$B$2:$B$28,"--",0) -> OJFZRV-MR4H3-OT5OQC | R80: =_xlfn.XLOOKUP(G80,'Kraken Trades'!$A$2:$A$28,'Kraken Trades'!$C$2:$C$28,"--",0) -> XRPGBP | S80: =_xlfn.XLOOKUP(G80,'Kraken Trades'!$A$2:$A$28,'Kraken Trades'!$D$2:$D$28,"--",0) -> 0.02658912 | T80: =_xlfn.XLOOKUP(G80,'Kraken Trades'!$A$2:$A$28,'Kraken Trades'!$E$2:$E$28,"--",0) -> buy | U80: =_xlfn.XLOOKUP(G80,'Kraken Trades'!$A$2:$A$28,'Kraken Trades'!$F$2:$F$28,"--",0) -> market | V80: =_xlfn.XLOOKUP(G80,'Kraken Trades'!$A$2:$A$28,'Kraken Trades'!$G$2:$G$28,"--",0) -> 0.42067 | W80: =_xlfn.XLOOKUP(G80,'Kraken Trades'!$A$2:$A$28,'Kraken Trades'!$H$2:$H$28,"--",0) -> 98.85745 | X80: =_xlfn.XLOOKUP(G80,'Kraken Trades'!$A$2:$A$28,'Kraken Trades'!$I$2:$I$28,"--",0) -> 0.25702937 | Y80: =_xlfn.XLOOKUP(G80,'Kraken Trades'!$A$2:$A$28,'Kraken Trades'!$J$2:$J$28,"--",0) -> 235 | Z80: =_xlfn.XLOOKUP(G80,'Kraken Trades'!$A$2:$A$28,'Kraken Trades'!$K$2:$K$28,"--",0) -> 0 | AA80: =_xlfn.XLOOKUP(G80,'Kraken Trades'!$A$2:$A$28,'Kraken Trades'!$L$2:$L$28,"--",0) -> initiated | AB80: =_xlfn.XLOOKUP(G80,'Kraken Trades'!$A$2:$A$28,'Kraken Trades'!$M$2:$M$28,"--",0) -> LSRT4P-ZF56G-DOKHCB,LET3FK-M2Y2E-OFAZFN,LWSASC-3X4CP-OD5E5A
A81: 45104 | B81: yes | E81: =_xlfn.XLOOKUP(D81,'DEST TAGs'!$A$2:$A$5,'DEST TAGs'!$B$2:$B$5,"--",0) -> -- | F81: LET3FK-M2Y2E-OFAZFN | G81: TABUT2-6TCYQ-U2OQ3G | H81: 45032.735 | I81: trade | K81: currency | L81: XXRP | M81: 235 | N81: 0 | O81: 235.76944 | P81: =_xlfn.XLOOKUP(G81,'Kraken Trades'!$A$2:$A$28,'Kraken Trades'!$A$2:$A$28,"--",0) -> TABUT2-6TCYQ-U2OQ3G | Q81: =_xlfn.XLOOKUP(G81,'Kraken Trades'!$A$2:$A$28,'Kraken Trades'!$B$2:$B$28,"--",0) -> OJFZRV-MR4H3-OT5OQC | R81: =_xlfn.XLOOKUP(G81,'Kraken Trades'!$A$2:$A$28,'Kraken Trades'!$C$2:$C$28,"--",0) -> XRPGBP | S81: =_xlfn.XLOOKUP(G81,'Kraken Trades'!$A$2:$A$28,'Kraken Trades'!$D$2:$D$28,"--",0) -> 0.02658912 | T81: =_xlfn.XLOOKUP(G81,'Kraken Trades'!$A$2:$A$28,'Kraken Trades'!$E$2:$E$28,"--",0) -> buy | U81: =_xlfn.XLOOKUP(G81,'Kraken Trades'!$A$2:$A$28,'Kraken Trades'!$F$2:$F$28,"--",0) -> market | V81: =_xlfn.XLOOKUP(G81,'Kraken Trades'!$A$2:$A$28,'Kraken Trades'!$G$2:$G$28,"--",0) -> 0.42067 | W81: =_xlfn.XLOOKUP(G81,'Kraken Trades'!$A$2:$A$28,'Kraken Trades'!$H$2:$H$28,"--",0) -> 98.85745 | X81: =_xlfn.XLOOKUP(G81,'Kraken Trades'!$A$2:$A$28,'Kraken Trades'!$I$2:$I$28,"--",0) -> 0.25702937 | Y81: =_xlfn.XLOOKUP(G81,'Kraken Trades'!$A$2:$A$28,'Kraken Trades'!$J$2:$J$28,"--",0) -> 235 | Z81: =_xlfn.XLOOKUP(G81,'Kraken Trades'!$A$2:$A$28,'Kraken Trades'!$K$2:$K$28,"--",0) -> 0 | AA81: =_xlfn.XLOOKUP(G81,'Kraken Trades'!$A$2:$A$28,'Kraken Trades'!$L$2:$L$28,"--",0) -> initiated | AB81: =_xlfn.XLOOKUP(G81,'Kraken Trades'!$A$2:$A$28,'Kraken Trades'!$M$2:$M$28,"--",0) -> LSRT4P-ZF56G-DOKHCB,LET3FK-M2Y2E-OFAZFN,LWSASC-3X4CP-OD5E5A
A82: 45104 | B82: yes | E82: =_xlfn.XLOOKUP(D82,'DEST TAGs'!$A$2:$A$5,'DEST TAGs'!$B$2:$B$5,"--",0) -> -- | F82: LSRT4P-ZF56G-DOKHCB | G82: TABUT2-6TCYQ-U2OQ3G | H82: 45032.735 | I82: trade | K82: currency | L82: KFEE | M82: 0 | N82: 31.91 | O82: 5841.8 | P82: =_xlfn.XLOOKUP(G82,'Kraken Trades'!$A$2:$A$28,'Kraken Trades'!$A$2:$A$28,"--",0) -> TABUT2-6TCYQ-U2OQ3G | Q82: =_xlfn.XLOOKUP(G82,'Kraken Trades'!$A$2:$A$28,'Kraken Trades'!$B$2:$B$28,"--",0) -> OJFZRV-MR4H3-OT5OQC | R82: =_xlfn.XLOOKUP(G82,'Kraken Trades'!$A$2:$A$28,'Kraken Trades'!$C$2:$C$28,"--",0) -> XRPGBP | S82: =_xlfn.XLOOKUP(G82,'Kraken Trades'!$A$2:$A$28,'Kraken Trades'!$D$2:$D$28,"--",0) -> 0.02658912 | T82: =_xlfn.XLOOKUP(G82,'Kraken Trades'!$A$2:$A$28,'Kraken Trades'!$E$2:$E$28,"--",0) -> buy | U82: =_xlfn.XLOOKUP(G82,'Kraken Trades'!$A$2:$A$28,'Kraken Trades'!$F$2:$F$28,"--",0) -> market | V82: =_xlfn.XLOOKUP(G82,'Kraken Trades'!$A$2:$A$28,'Kraken Trades'!$G$2:$G$28,"--",0) -> 0.42067 | W82: =_xlfn.XLOOKUP(G82,'Kraken Trades'!$A$2:$A$28,'Kraken Trades'!$H$2:$H$28,"--",0) -> 98.85745 | X82: =_xlfn.XLOOKUP(G82,'Kraken Trades'!$A$2:$A$28,'Kraken Trades'!$I$2:$I$28,"--",0) -> 0.25702937 | Y82: =_xlfn.XLOOKUP(G82,'Kraken Trades'!$A$2:$A$28,'Kraken Trades'!$J$2:$J$28,"--",0) -> 235 | Z82: =_xlfn.XLOOKUP(G82,'Kraken Trades'!$A$2:$A$28,'Kraken Trades'!$K$2:$K$28,"--",0) -> 0 | AA82: =_xlfn.XLOOKUP(G82,'Kraken Trades'!$A$2:$A$28,'Kraken Trades'!$L$2:$L$28,"--",0) -> initiated | AB82: =_xlfn.XLOOKUP(G82,'Kraken Trades'!$A$2:$A$28,'Kraken Trades'!$M$2:$M$28,"--",0) -> LSRT4P-ZF56G-DOKHCB,LET3FK-M2Y2E-OFAZFN,LWSASC-3X4CP-OD5E5A
A83: 45104 | B83: yes | E83: =_xlfn.XLOOKUP(D83,'DEST TAGs'!$A$2:$A$5,'DEST TAGs'!$B$2:$B$5,"--",0) -> -- | G83: AIBAO6K-JP5OE5-AHUHE7 | H83: 45032.735 | I83: withdrawal | K83: currency | L83: XXRP | M83: -235 | N83: 0.02 | P83: =_xlfn.XLOOKUP(G83,'Kraken Trades'!$A$2:$A$28,'Kraken Trades'!$A$2:$A$28,"--",0) -> -- | Q83: =_xlfn.XLOOKUP(G83,'Kraken Trades'!$A$2:$A$28,'Kraken Trades'!$B$2:$B$28,"--",0) -> -- | R83: =_xlfn.XLOOKUP(G83,'Kraken Trades'!$A$2:$A$28,'Kraken Trades'!$C$2:$C$28,"--",0) -> -- | S83: =_xlfn.XLOOKUP(G83,'Kraken Trades'!$A$2:$A$28,'Kraken Trades'!$D$2:$D$28,"--",0) -> -- | T83: =_xlfn.XLOOKUP(G83,'Kraken Trades'!$A$2:$A$28,'Kraken Trades'!$E$2:$E$28,"--",0) -> -- | U83: =_xlfn.XLOOKUP(G83,'Kraken Trades'!$A$2:$A$28,'Kraken Trades'!$F$2:$F$28,"--",0) -> -- | V83: =_xlfn.XLOOKUP(G83,'Kraken Trades'!$A$2:$A$28,'Kraken Trades'!$G$2:$G$28,"--",0) -> -- | W83: =_xlfn.XLOOKUP(G83,'Kraken Trades'!$A$2:$A$28,'Kraken Trades'!$H$2:$H$28,"--",0) -> -- | X83: =_xlfn.XLOOKUP(G83,'Kraken Trades'!$A$2:$A$28,'Kraken Trades'!$I$2:$I$28,"--",0) -> -- | Y83: =_xlfn.XLOOKUP(G83,'Kraken Trades'!$A$2:$A$28,'Kraken Trades'!$J$2:$J$28,"--",0) -> -- | Z83: =_xlfn.XLOOKUP(G83,'Kraken Trades'!$A$2:$A$28,'Kraken Trades'!$K$2:$K$28,"--",0) -> -- | AA83: =_xlfn.XLOOKUP(G83,'Kraken Trades'!$A$2:$A$28,'Kraken Trades'!$L$2:$L$28,"--",0) -> -- | AB83: =_xlfn.XLOOKUP(G83,'Kraken Trades'!$A$2:$A$28,'Kraken Trades'!$M$2:$M$28,"--",0) -> --
A84: 45104 | B84: yes | C84: https://bithomp.com/explorer/8F2873BFE79F71897C41F309842C424029A574E5868A0731EEB8B760454C43C4 | D84: 442734179 | E84: =_xlfn.XLOOKUP(D84,'DEST TAGs'!$A$2:$A$5,'DEST TAGs'!$B$2:$B$5,"--",0) -> Evgeniy Ulyukin | F84: LYVFXF-SZJYQ-US4RFL | G84: AIBAO6K-JP5OE5-AHUHE7 | H84: 45032.737 | I84: withdrawal | K84: currency | L84: XXRP | M84: -235 | N84: 0.02 | O84: 0.74944334 | P84: =_xlfn.XLOOKUP(G84,'Kraken Trades'!$A$2:$A$28,'Kraken Trades'!$A$2:$A$28,"--",0) -> -- | Q84: =_xlfn.XLOOKUP(G84,'Kraken Trades'!$A$2:$A$28,'Kraken Trades'!$B$2:$B$28,"--",0) -> -- | R84: =_xlfn.XLOOKUP(G84,'Kraken Trades'!$A$2:$A$28,'Kraken Trades'!$C$2:$C$28,"--",0) -> -- | S84: =_xlfn.XLOOKUP(G84,'Kraken Trades'!$A$2:$A$28,'Kraken Trades'!$D$2:$D$28,"--",0) -> -- | T84: =_xlfn.XLOOKUP(G84,'Kraken Trades'!$A$2:$A$28,'Kraken Trades'!$E$2:$E$28,"--",0) -> -- | U84: =_xlfn.XLOOKUP(G84,'Kraken Trades'!$A$2:$A$28,'Kraken Trades'!$F$2:$F$28,"--",0) -> -- | V84: =_xlfn.XLOOKUP(G84,'Kraken Trades'!$A$2:$A$28,'Kraken Trades'!$G$2:$G$28,"--",0) -> -- | W84: =_xlfn.XLOOKUP(G84,'Kraken Trades'!$A$2:$A$28,'Kraken Trades'!$H$2:$H$28,"--",0) -> -- | X84: =_xlfn.XLOOKUP(G84,'Kraken Trades'!$A$2:$A$28,'Kraken Trades'!$I$2:$I$28,"--",0) -> -- | Y84: =_xlfn.XLOOKUP(G84,'Kraken Trades'!$A$2:$A$28,'Kraken Trades'!$J$2:$J$28,"--",0) -> -- | Z84: =_xlfn.XLOOKUP(G84,'Kraken Trades'!$A$2:$A$28,'Kraken Trades'!$K$2:$K$28,"--",0) -> -- | AA84: =_xlfn.XLOOKUP(G84,'Kraken Trades'!$A$2:$A$28,'Kraken Trades'!$L$2:$L$28,"--",0) -> -- | AB84: =_xlfn.XLOOKUP(G84,'Kraken Trades'!$A$2:$A$28,'Kraken Trades'!$M$2:$M$28,"--",0) -> --
A85: 45104 | B85: yes | E85: =_xlfn.XLOOKUP(D85,'DEST TAGs'!$A$2:$A$5,'DEST TAGs'!$B$2:$B$5,"--",0) -> -- | G85: QYP53N2-OBD4GP-74M5B2 | H85: 45037.418 | I85: deposit | K85: currency | L85: ZGBP | M85: 3500 | N85: 0 | P85: =_xlfn.XLOOKUP(G85,'Kraken Trades'!$A$2:$A$28,'Kraken Trades'!$A$2:$A$28,"--",0) -> -- | Q85: =_xlfn.XLOOKUP(G85,'Kraken Trades'!$A$2:$A$28,'Kraken Trades'!$B$2:$B$28,"--",0) -> -- | R85: =_xlfn.XLOOKUP(G85,'Kraken Trades'!$A$2:$A$28,'Kraken Trades'!$C$2:$C$28,"--",0) -> -- | S85: =_xlfn.XLOOKUP(G85,'Kraken Trades'!$A$2:$A$28,'Kraken Trades'!$D$2:$D$28,"--",0) -> -- | T85: =_xlfn.XLOOKUP(G85,'Kraken Trades'!$A$2:$A$28,'Kraken Trades'!$E$2:$E$28,"--",0) -> -- | U85: =_xlfn.XLOOKUP(G85,'Kraken Trades'!$A$2:$A$28,'Kraken Trades'!$F$2:$F$28,"--",0) -> -- | V85: =_xlfn.XLOOKUP(G85,'Kraken Trades'!$A$2:$A$28,'Kraken Trades'!$G$2:$G$28,"--",0) -> -- | W85: =_xlfn.XLOOKUP(G85,'Kraken Trades'!$A$2:$A$28,'Kraken Trades'!$H$2:$H$28,"--",0) -> -- | X85: =_xlfn.XLOOKUP(G85,'Kraken Trades'!$A$2:$A$28,'Kraken Trades'!$I$2:$I$28,"--",0) -> -- | Y85: =_xlfn.XLOOKUP(G85,'Kraken Trades'!$A$2:$A$28,'Kraken Trades'!$J$2:$J$28,"--",0) -> -- | Z85: =_xlfn.XLOOKUP(G85,'Kraken Trades'!$A$2:$A$28,'Kraken Trades'!$K$2:$K$28,"--",0) -> -- | AA85: =_xlfn.XLOOKUP(G85,'Kraken Trades'!$A$2:$A$28,'Kraken Trades'!$L$2:$L$28,"--",0) -> -- | AB85: =_xlfn.XLOOKUP(G85,'Kraken Trades'!$A$2:$A$28,'Kraken Trades'!$M$2:$M$28,"--",0) -> --
A86: 45104 | B86: yes | E86: =_xlfn.XLOOKUP(D86,'DEST TAGs'!$A$2:$A$5,'DEST TAGs'!$B$2:$B$5,"--",0) -> -- | F86: LEJUTJ-AL7CJ-3HGV6A | G86: QYP53N2-OBD4GP-74M5B2 | H86: 45037.427 | I86: deposit | K86: currency | L86: ZGBP | M86: 3500 | N86: 0 | O86: 3604.4022 | P86: =_xlfn.XLOOKUP(G86,'Kraken Trades'!$A$2:$A$28,'Kraken Trades'!$A$2:$A$28,"--",0) -> -- | Q86: =_xlfn.XLOOKUP(G86,'Kraken Trades'!$A$2:$A$28,'Kraken Trades'!$B$2:$B$28,"--",0) -> -- | R86: =_xlfn.XLOOKUP(G86,'Kraken Trades'!$A$2:$A$28,'Kraken Trades'!$C$2:$C$28,"--",0) -> -- | S86: =_xlfn.XLOOKUP(G86,'Kraken Trades'!$A$2:$A$28,'Kraken Trades'!$D$2:$D$28,"--",0) -> -- | T86: =_xlfn.XLOOKUP(G86,'Kraken Trades'!$A$2:$A$28,'Kraken Trades'!$E$2:$E$28,"--",0) -> -- | U86: =_xlfn.XLOOKUP(G86,'Kraken Trades'!$A$2:$A$28,'Kraken Trades'!$F$2:$F$28,"--",0) -> -- | V86: =_xlfn.XLOOKUP(G86,'Kraken Trades'!$A$2:$A$28,'Kraken Trades'!$G$2:$G$28,"--",0) -> -- | W86: =_xlfn.XLOOKUP(G86,'Kraken Trades'!$A$2:$A$28,'Kraken Trades'!$H$2:$H$28,"--",0) -> -- | X86: =_xlfn.XLOOKUP(G86,'Kraken Trades'!$A$2:$A$28,'Kraken Trades'!$I$2:$I$28,"--",0) -> -- | Y86: =_xlfn.XLOOKUP(G86,'Kraken Trades'!$A$2:$A$28,'Kraken Trades'!$J$2:$J$28,"--",0) -> -- | Z86: =_xlfn.XLOOKUP(G86,'Kraken Trades'!$A$2:$A$28,'Kraken Trades'!$K$2:$K$28,"--",0) -> -- | AA86: =_xlfn.XLOOKUP(G86,'Kraken Trades'!$A$2:$A$28,'Kraken Trades'!$L$2:$L$28,"--",0) -> -- | AB86: =_xlfn.XLOOKUP(G86,'Kraken Trades'!$A$2:$A$28,'Kraken Trades'!$M$2:$M$28,"--",0) -> --
A87: 45104 | B87: yes | E87: =_xlfn.XLOOKUP(D87,'DEST TAGs'!$A$2:$A$5,'DEST TAGs'!$B$2:$B$5,"--",0) -> -- | F87: LYQPUH-I32RR-YE44I3 | G87: T7CJOI-B2NNA-2XOZVX | H87: 45037.489 | I87: trade | K87: currency | L87: ZGBP | M87: -860.8966 | N87: 0 | O87: 2743.5056 | P87: =_xlfn.XLOOKUP(G87,'Kraken Trades'!$A$2:$A$28,'Kraken Trades'!$A$2:$A$28,"--",0) -> T7CJOI-B2NNA-2XOZVX | Q87: =_xlfn.XLOOKUP(G87,'Kraken Trades'!$A$2:$A$28,'Kraken Trades'!$B$2:$B$28,"--",0) -> ONWRF5-UZ2FN-ZUG2A6 | R87: =_xlfn.XLOOKUP(G87,'Kraken Trades'!$A$2:$A$28,'Kraken Trades'!$C$2:$C$28,"--",0) -> XRPGBP | S87: =_xlfn.XLOOKUP(G87,'Kraken Trades'!$A$2:$A$28,'Kraken Trades'!$D$2:$D$28,"--",0) -> 0.031121528 | T87: =_xlfn.XLOOKUP(G87,'Kraken Trades'!$A$2:$A$28,'Kraken Trades'!$E$2:$E$28,"--",0) -> buy | U87: =_xlfn.XLOOKUP(G87,'Kraken Trades'!$A$2:$A$28,'Kraken Trades'!$F$2:$F$28,"--",0) -> market | V87: =_xlfn.XLOOKUP(G87,'Kraken Trades'!$A$2:$A$28,'Kraken Trades'!$G$2:$G$28,"--",0) -> 0.37676 | W87: =_xlfn.XLOOKUP(G87,'Kraken Trades'!$A$2:$A$28,'Kraken Trades'!$H$2:$H$28,"--",0) -> 860.8966 | X87: =_xlfn.XLOOKUP(G87,'Kraken Trades'!$A$2:$A$28,'Kraken Trades'!$I$2:$I$28,"--",0) -> 2.2383312 | Y87: =_xlfn.XLOOKUP(G87,'Kraken Trades'!$A$2:$A$28,'Kraken Trades'!$J$2:$J$28,"--",0) -> 2285 | Z87: =_xlfn.XLOOKUP(G87,'Kraken Trades'!$A$2:$A$28,'Kraken Trades'!$K$2:$K$28,"--",0) -> 0 | AA87: =_xlfn.XLOOKUP(G87,'Kraken Trades'!$A$2:$A$28,'Kraken Trades'!$L$2:$L$28,"--",0) -> initiated | AB87: =_xlfn.XLOOKUP(G87,'Kraken Trades'!$A$2:$A$28,'Kraken Trades'!$M$2:$M$28,"--",0) -> LOHSU5-BSLCE-ZQLVUP,L6574Z-POCSK-2F2GNE,LYQPUH-I32RR-YE44I3
A88: 45104 | B88: yes | E88: =_xlfn.XLOOKUP(D88,'DEST TAGs'!$A$2:$A$5,'DEST TAGs'!$B$2:$B$5,"--",0) -> -- | F88: L6574Z-POCSK-2F2GNE | G88: T7CJOI-B2NNA-2XOZVX | H88: 45037.489 | I88: trade | K88: currency | L88: XXRP | M88: 2285 | N88: 0 | O88: 2285.7494 | P88: =_xlfn.XLOOKUP(G88,'Kraken Trades'!$A$2:$A$28,'Kraken Trades'!$A$2:$A$28,"--",0) -> T7CJOI-B2NNA-2XOZVX | Q88: =_xlfn.XLOOKUP(G88,'Kraken Trades'!$A$2:$A$28,'Kraken Trades'!$B$2:$B$28,"--",0) -> ONWRF5-UZ2FN-ZUG2A6 | R88: =_xlfn.XLOOKUP(G88,'Kraken Trades'!$A$2:$A$28,'Kraken Trades'!$C$2:$C$28,"--",0) -> XRPGBP | S88: =_xlfn.XLOOKUP(G88,'Kraken Trades'!$A$2:$A$28,'Kraken Trades'!$D$2:$D$28,"--",0) -> 0.031121528 | T88: =_xlfn.XLOOKUP(G88,'Kraken Trades'!$A$2:$A$28,'Kraken Trades'!$E$2:$E$28,"--",0) -> buy | U88: =_xlfn.XLOOKUP(G88,'Kraken Trades'!$A$2:$A$28,'Kraken Trades'!$F$2:$F$28,"--",0) -> market | V88: =_xlfn.XLOOKUP(G88,'Kraken Trades'!$A$2:$A$28,'Kraken Trades'!$G$2:$G$28,"--",0) -> 0.37676 | W88: =_xlfn.XLOOKUP(G88,'Kraken Trades'!$A$2:$A$28,'Kraken Trades'!$H$2:$H$28,"--",0) -> 860.8966 | X88: =_xlfn.XLOOKUP(G88,'Kraken Trades'!$A$2:$A$28,'Kraken Trades'!$I$2:$I$28,"--",0) -> 2.2383312 | Y88: =_xlfn.XLOOKUP(G88,'Kraken Trades'!$A$2:$A$28,'Kraken Trades'!$J$2:$J$28,"--",0) -> 2285 | Z88: =_xlfn.XLOOKUP(G88,'Kraken Trades'!$A$2:$A$28,'Kraken Trades'!$K$2:$K$28,"--",0) -> 0 | AA88: =_xlfn.XLOOKUP(G88,'Kraken Trades'!$A$2:$A$28,'Kraken Trades'!$L$2:$L$28,"--",0) -> initiated | AB88: =_xlfn.XLOOKUP(G88,'Kraken Trades'!$A$2:$A$28,'Kraken Trades'!$M$2:$M$28,"--",0) -> LOHSU5-BSLCE-ZQLVUP,L6574Z-POCSK-2F2GNE,LYQPUH-I32RR-YE44I3
A89: 45104 | B89: yes | E89: =_xlfn.XLOOKUP(D89,'DEST TAGs'!$A$2:$A$5,'DEST TAGs'!$B$2:$B$5,"--",0) -> -- | F89: LOHSU5-BSLCE-ZQLVUP | G89: T7CJOI-B2NNA-2XOZVX | H89: 45037.489 | I89: trade | K89: currency | L89: KFEE | M89: 0 | N89: 277.32 | O89: 5564.48 | P89: =_xlfn.XLOOKUP(G89,'Kraken Trades'!$A$2:$A$28,'Kraken Trades'!$A$2:$A$28,"--",0) -> T7CJOI-B2NNA-2XOZVX | Q89: =_xlfn.XLOOKUP(G89,'Kraken Trades'!$A$2:$A$28,'Kraken Trades'!$B$2:$B$28,"--",0) -> ONWRF5-UZ2FN-ZUG2A6 | R89: =_xlfn.XLOOKUP(G89,'Kraken Trades'!$A$2:$A$28,'Kraken Trades'!$C$2:$C$28,"--",0) -> XRPGBP | S89: =_xlfn.XLOOKUP(G89,'Kraken Trades'!$A$2:$A$28,'Kraken Trades'!$D$2:$D$28,"--",0) -> 0.031121528 | T89: =_xlfn.XLOOKUP(G89,'Kraken Trades'!$A$2:$A$28,'Kraken Trades'!$E$2:$E$28,"--",0) -> buy | U89: =_xlfn.XLOOKUP(G89,'Kraken Trades'!$A$2:$A$28,'Kraken Trades'!$F$2:$F$28,"--",0) -> market | V89: =_xlfn.XLOOKUP(G89,'Kraken Trades'!$A$2:$A$28,'Kraken Trades'!$G$2:$G$28,"--",0) -> 0.37676 | W89: =_xlfn.XLOOKUP(G89,'Kraken Trades'!$A$2:$A$28,'Kraken Trades'!$H$2:$H$28,"--",0) -> 860.8966 | X89: =_xlfn.XLOOKUP(G89,'Kraken Trades'!$A$2:$A$28,'Kraken Trades'!$I$2:$I$28,"--",0) -> 2.2383312 | Y89: =_xlfn.XLOOKUP(G89,'Kraken Trades'!$A$2:$A$28,'Kraken Trades'!$J$2:$J$28,"--",0) -> 2285 | Z89: =_xlfn.XLOOKUP(G89,'Kraken Trades'!$A$2:$A$28,'Kraken Trades'!$K$2:$K$28,"--",0) -> 0 | AA89: =_xlfn.XLOOKUP(G89,'Kraken Trades'!$A$2:$A$28,'Kraken Trades'!$L$2:$L$28,"--",0) -> initiated | AB89: =_xlfn.XLOOKUP(G89,'Kraken Trades'!$A$2:$A$28,'Kraken Trades'!$M$2:$M$28,"--",0) -> LOHSU5-BSLCE-ZQLVUP,L6574Z-POCSK-2F2GNE,LYQPUH-I32RR-YE44I3
A90: 45104 | B90: yes | E90: =_xlfn.XLOOKUP(D90,'DEST TAGs'!$A$2:$A$5,'DEST TAGs'!$B$2:$B$5,"--",0) -> -- | G90: AIBSN7X-X3SUAT-BEXDZF | H90: 45037.49 | I90: withdrawal | K90: currency | L90: XXRP | M90: -2285 | N90: 0.02 | P90: =_xlfn.XLOOKUP(G90,'Kraken Trades'!$A$2:$A$28,'Kraken Trades'!$A$2:$A$28,"--",0) -> -- | Q90: =_xlfn.XLOOKUP(G90,'Kraken Trades'!$A$2:$A$28,'Kraken Trades'!$B$2:$B$28,"--",0) -> -- | R90: =_xlfn.XLOOKUP(G90,'Kraken Trades'!$A$2:$A$28,'Kraken Trades'!$C$2:$C$28,"--",0) -> -- | S90: =_xlfn.XLOOKUP(G90,'Kraken Trades'!$A$2:$A$28,'Kraken Trades'!$D$2:$D$28,"--",0) -> -- | T90: =_xlfn.XLOOKUP(G90,'Kraken Trades'!$A$2:$A$28,'Kraken Trades'!$E$2:$E$28,"--",0) -> -- | U90: =_xlfn.XLOOKUP(G90,'Kraken Trades'!$A$2:$A$28,'Kraken Trades'!$F$2:$F$28,"--",0) -> -- | V90: =_xlfn.XLOOKUP(G90,'Kraken Trades'!$A$2:$A$28,'Kraken Trades'!$G$2:$G$28,"--",0) -> -- | W90: =_xlfn.XLOOKUP(G90,'Kraken Trades'!$A$2:$A$28,'Kraken Trades'!$H$2:$H$28,"--",0) -> -- | X90: =_xlfn.XLOOKUP(G90,'Kraken Trades'!$A$2:$A$28,'Kraken Trades'!$I$2:$I$28,"--",0) -> -- | Y90: =_xlfn.XLOOKUP(G90,'Kraken Trades'!$A$2:$A$28,'Kraken Trades'!$J$2:$J$28,"--",0) -> -- | Z90: =_xlfn.XLOOKUP(G90,'Kraken Trades'!$A$2:$A$28,'Kraken Trades'!$K$2:$K$28,"--",0) -> -- | AA90: =_xlfn.XLOOKUP(G90,'Kraken Trades'!$A$2:$A$28,'Kraken Trades'!$L$2:$L$28,"--",0) -> -- | AB90: =_xlfn.XLOOKUP(G90,'Kraken Trades'!$A$2:$A$28,'Kraken Trades'!$M$2:$M$28,"--",0) -> --
A91: 45104 | B91: yes | C91: https://bithomp.com/explorer/2B372258F7200F7B81D0C160CDB258C6FC22178C7DB0F9D84AC8334D16853A79 | D91: 518294827 | E91: =_xlfn.XLOOKUP(D91,'DEST TAGs'!$A$2:$A$5,'DEST TAGs'!$B$2:$B$5,"--",0) -> Alex Smirnov | F91: LCM3SC-IITEQ-LN5XXH | G91: AIBSN7X-X3SUAT-BEXDZF | H91: 45037.491 | I91: withdrawal | K91: currency | L91: XXRP | M91: -2285 | N91: 0.02 | O91: 0.72944334 | P91: =_xlfn.XLOOKUP(G91,'Kraken Trades'!$A$2:$A$28,'Kraken Trades'!$A$2:$A$28,"--",0) -> -- | Q91: =_xlfn.XLOOKUP(G91,'Kraken Trades'!$A$2:$A$28,'Kraken Trades'!$B$2:$B$28,"--",0) -> -- | R91: =_xlfn.XLOOKUP(G91,'Kraken Trades'!$A$2:$A$28,'Kraken Trades'!$C$2:$C$28,"--",0) -> -- | S91: =_xlfn.XLOOKUP(G91,'Kraken Trades'!$A$2:$A$28,'Kraken Trades'!$D$2:$D$28,"--",0) -> -- | T91: =_xlfn.XLOOKUP(G91,'Kraken Trades'!$A$2:$A$28,'Kraken Trades'!$E$2:$E$28,"--",0) -> -- | U91: =_xlfn.XLOOKUP(G91,'Kraken Trades'!$A$2:$A$28,'Kraken Trades'!$F$2:$F$28,"--",0) -> -- | V91: =_xlfn.XLOOKUP(G91,'Kraken Trades'!$A$2:$A$28,'Kraken Trades'!$G$2:$G$28,"--",0) -> -- | W91: =_xlfn.XLOOKUP(G91,'Kraken Trades'!$A$2:$A$28,'Kraken Trades'!$H$2:$H$28,"--",0) -> -- | X91: =_xlfn.XLOOKUP(G91,'Kraken Trades'!$A$2:$A$28,'Kraken Trades'!$I$2:$I$28,"--",0) -> -- | Y91: =_xlfn.XLOOKUP(G91,'Kraken Trades'!$A$2:$A$28,'Kraken Trades'!$J$2:$J$28,"--",0) -> -- | Z91: =_xlfn.XLOOKUP(G91,'Kraken Trades'!$A$2:$A$28,'Kraken Trades'!$K$2:$K$28,"--",0) -> -- | AA91: =_xlfn.XLOOKUP(G91,'Kraken Trades'!$A$2:$A$28,'Kraken Trades'!$L$2:$L$28,"--",0) -> -- | AB91: =_xlfn.XLOOKUP(G91,'Kraken Trades'!$A$2:$A$28,'Kraken Trades'!$M$2:$M$28,"--",0) -> --
A92: 45104 | B92: yes | E92: =_xlfn.XLOOKUP(D92,'DEST TAGs'!$A$2:$A$5,'DEST TAGs'!$B$2:$B$5,"--",0) -> -- | F92: LS3LWD-WUVCK-VNJFVN | G92: TV2CUE-4ALGJ-DLH5SJ | H92: 45037.515 | I92: trade | K92: currency | L92: ZGBP | M92: -250.3096 | N92: 0 | O92: 2493.196 | P92: =_xlfn.XLOOKUP(G92,'Kraken Trades'!$A$2:$A$28,'Kraken Trades'!$A$2:$A$28,"--",0) -> TV2CUE-4ALGJ-DLH5SJ | Q92: =_xlfn.XLOOKUP(G92,'Kraken Trades'!$A$2:$A$28,'Kraken Trades'!$B$2:$B$28,"--",0) -> OV46XD-ZO26J-BCHG5E | R92: =_xlfn.XLOOKUP(G92,'Kraken Trades'!$A$2:$A$28,'Kraken Trades'!$C$2:$C$28,"--",0) -> XRPGBP | S92: =_xlfn.XLOOKUP(G92,'Kraken Trades'!$A$2:$A$28,'Kraken Trades'!$D$2:$D$28,"--",0) -> 0.01565625 | T92: =_xlfn.XLOOKUP(G92,'Kraken Trades'!$A$2:$A$28,'Kraken Trades'!$E$2:$E$28,"--",0) -> buy | U92: =_xlfn.XLOOKUP(G92,'Kraken Trades'!$A$2:$A$28,'Kraken Trades'!$F$2:$F$28,"--",0) -> market | V92: =_xlfn.XLOOKUP(G92,'Kraken Trades'!$A$2:$A$28,'Kraken Trades'!$G$2:$G$28,"--",0) -> 0.37640544 | W92: =_xlfn.XLOOKUP(G92,'Kraken Trades'!$A$2:$A$28,'Kraken Trades'!$H$2:$H$28,"--",0) -> 250.30962 | X92: =_xlfn.XLOOKUP(G92,'Kraken Trades'!$A$2:$A$28,'Kraken Trades'!$I$2:$I$28,"--",0) -> 0.650805 | Y92: =_xlfn.XLOOKUP(G92,'Kraken Trades'!$A$2:$A$28,'Kraken Trades'!$J$2:$J$28,"--",0) -> 665 | Z92: =_xlfn.XLOOKUP(G92,'Kraken Trades'!$A$2:$A$28,'Kraken Trades'!$K$2:$K$28,"--",0) -> 0 | AA92: =_xlfn.XLOOKUP(G92,'Kraken Trades'!$A$2:$A$28,'Kraken Trades'!$L$2:$L$28,"--",0) -> initiated | AB92: =_xlfn.XLOOKUP(G92,'Kraken Trades'!$A$2:$A$28,'Kraken Trades'!$M$2:$M$28,"--",0) -> LLMMB3-QKWQR-UXWHAT,LH4Q2I-JSAQ4-7ME3PF,LS3LWD-WUVCK-VNJFVN
A93: 45104 | B93: yes | E93: =_xlfn.XLOOKUP(D93,'DEST TAGs'!$A$2:$A$5,'DEST TAGs'!$B$2:$B$5,"--",0) -> -- | F93: LH4Q2I-JSAQ4-7ME3PF | G93: TV2CUE-4ALGJ-DLH5SJ | H93: 45037.515 | I93: trade | K93: currency | L93: XXRP | M93: 665 | N93: 0 | O93: 665.72944 | P93: =_xlfn.XLOOKUP(G93,'Kraken Trades'!$A$2:$A$28,'Kraken Trades'!$A$2:$A$28,"--",0) -> TV2CUE-4ALGJ-DLH5SJ | Q93: =_xlfn.XLOOKUP(G93,'Kraken Trades'!$A$2:$A$28,'Kraken Trades'!$B$2:$B$28,"--",0) -> OV46XD-ZO26J-BCHG5E | R93: =_xlfn.XLOOKUP(G93,'Kraken Trades'!$A$2:$A$28,'Kraken Trades'!$C$2:$C$28,"--",0) -> XRPGBP | S93: =_xlfn.XLOOKUP(G93,'Kraken Trades'!$A$2:$A$28,'Kraken Trades'!$D$2:$D$28,"--",0) -> 0.01565625 | T93: =_xlfn.XLOOKUP(G93,'Kraken Trades'!$A$2:$A$28,'Kraken Trades'!$E$2:$E$28,"--",0) -> buy | U93: =_xlfn.XLOOKUP(G93,'Kraken Trades'!$A$2:$A$28,'Kraken Trades'!$F$2:$F$28,"--",0) -> market | V93: =_xlfn.XLOOKUP(G93,'Kraken Trades'!$A$2:$A$28,'Kraken Trades'!$G$2:$G$28,"--",0) -> 0.37640544 | W93: =_xlfn.XLOOKUP(G93,'Kraken Trades'!$A$2:$A$28,'Kraken Trades'!$H$2:$H$28,"--",0) -> 250.30962 | X93: =_xlfn.XLOOKUP(G93,'Kraken Trades'!$A$2:$A$28,'Kraken Trades'!$I$2:$I$28,"--",0) -> 0.650805 | Y93: =_xlfn.XLOOKUP(G93,'Kraken Trades'!$A$2:$A$28,'Kraken Trades'!$J$2:$J$28,"--",0) -> 665 | Z93: =_xlfn.XLOOKUP(G93,'Kraken Trades'!$A$2:$A$28,'Kraken Trades'!$K$2:$K$28,"--",0) -> 0 | AA93: =_xlfn.XLOOKUP(G93,'Kraken Trades'!$A$2:$A$28,'Kraken Trades'!$L$2:$L$28,"--",0) -> initiated | AB93: =_xlfn.XLOOKUP(G93,'Kraken Trades'!$A$2:$A$28,'Kraken Trades'!$M$2:$M$28,"--",0) -> LLMMB3-QKWQR-UXWHAT,LH4Q2I-JSAQ4-7ME3PF,LS3LWD-WUVCK-VNJFVN
A94: 45104 | B94: yes | E94: =_xlfn.XLOOKUP(D94,'DEST TAGs'!$A$2:$A$5,'DEST TAGs'!$B$2:$B$5,"--",0) -> -- | F94: LLMMB3-QKWQR-UXWHAT | G94: TV2CUE-4ALGJ-DLH5SJ | H94: 45037.515 | I94: trade | K94: currency | L94: KFEE | M94: 0 | N94: 80.66 | O94: 5483.82 | P94: =_xlfn.XLOOKUP(G94,'Kraken Trades'!$A$2:$A$28,'Kraken Trades'!$A$2:$A$28,"--",0) -> TV2CUE-4ALGJ-DLH5SJ | Q94: =_xlfn.XLOOKUP(G94,'Kraken Trades'!$A$2:$A$28,'Kraken Trades'!$B$2:$B$28,"--",0) -> OV46XD-ZO26J-BCHG5E | R94: =_xlfn.XLOOKUP(G94,'Kraken Trades'!$A$2:$A$28,'Kraken Trades'!$C$2:$C$28,"--",0) -> XRPGBP | S94: =_xlfn.XLOOKUP(G94,'Kraken Trades'!$A$2:$A$28,'Kraken Trades'!$D$2:$D$28,"--",0) -> 0.01565625 | T94: =_xlfn.XLOOKUP(G94,'Kraken Trades'!$A$2:$A$28,'Kraken Trades'!$E$2:$E$28,"--",0) -> buy | U94: =_xlfn.XLOOKUP(G94,'Kraken Trades'!$A$2:$A$28,'Kraken Trades'!$F$2:$F$28,"--",0) -> market | V94: =_xlfn.XLOOKUP(G94,'Kraken Trades'!$A$2:$A$28,'Kraken Trades'!$G$2:$G$28,"--",0) -> 0.37640544 | W94: =_xlfn.XLOOKUP(G94,'Kraken Trades'!$A$2:$A$28,'Kraken Trades'!$H$2:$H$28,"--",0) -> 250.30962 | X94: =_xlfn.XLOOKUP(G94,'Kraken Trades'!$A$2:$A$28,'Kraken Trades'!$I$2:$I$28,"--",0) -> 0.650805 | Y94: =_xlfn.XLOOKUP(G94,'Kraken Trades'!$A$2:$A$28,'Kraken Trades'!$J$2:$J$28,"--",0) -> 665 | Z94: =_xlfn.XLOOKUP(G94,'Kraken Trades'!$A$2:$A$28,'Kraken Trades'!$K$2:$K$28,"--",0) -> 0 | AA94: =_xlfn.XLOOKUP(G94,'Kraken Trades'!$A$2:$A$28,'Kraken Trades'!$L$2:$L$28,"--",0) -> initiated | AB94: =_xlfn.XLOOKUP(G94,'Kraken Trades'!$A$2:$A$28,'Kraken Trades'!$M$2:$M$28,"--",0) -> LLMMB3-QKWQR-UXWHAT,LH4Q2I-JSAQ4-7ME3PF,LS3LWD-WUVCK-VNJFVN
A95: 45104 | B95: yes | E95: =_xlfn.XLOOKUP(D95,'DEST TAGs'!$A$2:$A$5,'DEST TAGs'!$B$2:$B$5,"--",0) -> -- | G95: AIBJP5F-GBOJO3-3NXNL2 | H95: 45037.516 | I95: withdrawal | K95: currency | L95: XXRP | M95: -665 | N95: 0.02 | P95: =_xlfn.XLOOKUP(G95,'Kraken Trades'!$A$2:$A$28,'Kraken Trades'!$A$2:$A$28,"--",0) -> -- | Q95: =_xlfn.XLOOKUP(G95,'Kraken Trades'!$A$2:$A$28,'Kraken Trades'!$B$2:$B$28,"--",0) -> -- | R95: =_xlfn.XLOOKUP(G95,'Kraken Trades'!$A$2:$A$28,'Kraken Trades'!$C$2:$C$28,"--",0) -> -- | S95: =_xlfn.XLOOKUP(G95,'Kraken Trades'!$A$2:$A$28,'Kraken Trades'!$D$2:$D$28,"--",0) -> -- | T95: =_xlfn.XLOOKUP(G95,'Kraken Trades'!$A$2:$A$28,'Kraken Trades'!$E$2:$E$28,"--",0) -> -- | U95: =_xlfn.XLOOKUP(G95,'Kraken Trades'!$A$2:$A$28,'Kraken Trades'!$F$2:$F$28,"--",0) -> -- | V95: =_xlfn.XLOOKUP(G95,'Kraken Trades'!$A$2:$A$28,'Kraken Trades'!$G$2:$G$28,"--",0) -> -- | W95: =_xlfn.XLOOKUP(G95,'Kraken Trades'!$A$2:$A$28,'Kraken Trades'!$H$2:$H$28,"--",0) -> -- | X95: =_xlfn.XLOOKUP(G95,'Kraken Trades'!$A$2:$A$28,'Kraken Trades'!$I$2:$I$28,"--",0) -> -- | Y95: =_xlfn.XLOOKUP(G95,'Kraken Trades'!$A$2:$A$28,'Kraken Trades'!$J$2:$J$28,"--",0) -> -- | Z95: =_xlfn.XLOOKUP(G95,'Kraken Trades'!$A$2:$A$28,'Kraken Trades'!$K$2:$K$28,"--",0) -> -- | AA95: =_xlfn.XLOOKUP(G95,'Kraken Trades'!$A$2:$A$28,'Kraken Trades'!$L$2:$L$28,"--",0) -> -- | AB95: =_xlfn.XLOOKUP(G95,'Kraken Trades'!$A$2:$A$28,'Kraken Trades'!$M$2:$M$28,"--",0) -> --
A96: 45104 | B96: yes | C96: https://bithomp.com/explorer/6CF6E9B042139AEAC3F03C58EA3F40D8F934935AD52F22AAC440D121986AC864 | D96: 442734179 | E96: =_xlfn.XLOOKUP(D96,'DEST TAGs'!$A$2:$A$5,'DEST TAGs'!$B$2:$B$5,"--",0) -> Evgeniy Ulyukin | F96: LPFMZW-EERWF-MFAIVE | G96: AIBJP5F-GBOJO3-3NXNL2 | H96: 45037.517 | I96: withdrawal | K96: currency | L96: XXRP | M96: -665 | N96: 0.02 | O96: 0.70944334 | P96: =_xlfn.XLOOKUP(G96,'Kraken Trades'!$A$2:$A$28,'Kraken Trades'!$A$2:$A$28,"--",0) -> -- | Q96: =_xlfn.XLOOKUP(G96,'Kraken Trades'!$A$2:$A$28,'Kraken Trades'!$B$2:$B$28,"--",0) -> -- | R96: =_xlfn.XLOOKUP(G96,'Kraken Trades'!$A$2:$A$28,'Kraken Trades'!$C$2:$C$28,"--",0) -> -- | S96: =_xlfn.XLOOKUP(G96,'Kraken Trades'!$A$2:$A$28,'Kraken Trades'!$D$2:$D$28,"--",0) -> -- | T96: =_xlfn.XLOOKUP(G96,'Kraken Trades'!$A$2:$A$28,'Kraken Trades'!$E$2:$E$28,"--",0) -> -- | U96: =_xlfn.XLOOKUP(G96,'Kraken Trades'!$A$2:$A$28,'Kraken Trades'!$F$2:$F$28,"--",0) -> -- | V96: =_xlfn.XLOOKUP(G96,'Kraken Trades'!$A$2:$A$28,'Kraken Trades'!$G$2:$G$28,"--",0) -> -- | W96: =_xlfn.XLOOKUP(G96,'Kraken Trades'!$A$2:$A$28,'Kraken Trades'!$H$2:$H$28,"--",0) -> -- | X96: =_xlfn.XLOOKUP(G96,'Kraken Trades'!$A$2:$A$28,'Kraken Trades'!$I$2:$I$28,"--",0) -> -- | Y96: =_xlfn.XLOOKUP(G96,'Kraken Trades'!$A$2:$A$28,'Kraken Trades'!$J$2:$J$28,"--",0) -> -- | Z96: =_xlfn.XLOOKUP(G96,'Kraken Trades'!$A$2:$A$28,'Kraken Trades'!$K$2:$K$28,"--",0) -> -- | AA96: =_xlfn.XLOOKUP(G96,'Kraken Trades'!$A$2:$A$28,'Kraken Trades'!$L$2:$L$28,"--",0) -> -- | AB96: =_xlfn.XLOOKUP(G96,'Kraken Trades'!$A$2:$A$28,'Kraken Trades'!$M$2:$M$28,"--",0) -> --
A97: 45104 | B97: yes | E97: =_xlfn.XLOOKUP(D97,'DEST TAGs'!$A$2:$A$5,'DEST TAGs'!$B$2:$B$5,"--",0) -> -- | G97: QYPHWHX-IOFHMF-IMEWSP | H97: 45037.698 | I97: deposit | K97: currency | L97: ZGBP | M97: 2000 | N97: 0 | P97: =_xlfn.XLOOKUP(G97,'Kraken Trades'!$A$2:$A$28,'Kraken Trades'!$A$2:$A$28,"--",0) -> -- | Q97: =_xlfn.XLOOKUP(G97,'Kraken Trades'!$A$2:$A$28,'Kraken Trades'!$B$2:$B$28,"--",0) -> -- | R97: =_xlfn.XLOOKUP(G97,'Kraken Trades'!$A$2:$A$28,'Kraken Trades'!$C$2:$C$28,"--",0) -> -- | S97: =_xlfn.XLOOKUP(G97,'Kraken Trades'!$A$2:$A$28,'Kraken Trades'!$D$2:$D$28,"--",0) -> -- | T97: =_xlfn.XLOOKUP(G97,'Kraken Trades'!$A$2:$A$28,'Kraken Trades'!$E$2:$E$28,"--",0) -> -- | U97: =_xlfn.XLOOKUP(G97,'Kraken Trades'!$A$2:$A$28,'Kraken Trades'!$F$2:$F$28,"--",0) -> -- | V97: =_xlfn.XLOOKUP(G97,'Kraken Trades'!$A$2:$A$28,'Kraken Trades'!$G$2:$G$28,"--",0) -> -- | W97: =_xlfn.XLOOKUP(G97,'Kraken Trades'!$A$2:$A$28,'Kraken Trades'!$H$2:$H$28,"--",0) -> -- | X97: =_xlfn.XLOOKUP(G97,'Kraken Trades'!$A$2:$A$28,'Kraken Trades'!$I$2:$I$28,"--",0) -> -- | Y97: =_xlfn.XLOOKUP(G97,'Kraken Trades'!$A$2:$A$28,'Kraken Trades'!$J$2:$J$28,"--",0) -> -- | Z97: =_xlfn.XLOOKUP(G97,'Kraken Trades'!$A$2:$A$28,'Kraken Trades'!$K$2:$K$28,"--",0) -> -- | AA97: =_xlfn.XLOOKUP(G97,'Kraken Trades'!$A$2:$A$28,'Kraken Trades'!$L$2:$L$28,"--",0) -> -- | AB97: =_xlfn.XLOOKUP(G97,'Kraken Trades'!$A$2:$A$28,'Kraken Trades'!$M$2:$M$28,"--",0) -> --
A98: 45104 | B98: yes | E98: =_xlfn.XLOOKUP(D98,'DEST TAGs'!$A$2:$A$5,'DEST TAGs'!$B$2:$B$5,"--",0) -> -- | F98: LX6CSO-DWG2P-6FM2FV | G98: QYPHWHX-IOFHMF-IMEWSP | H98: 45037.708 | I98: deposit | K98: currency | L98: ZGBP | M98: 2000 | N98: 0 | O98: 4493.196 | P98: =_xlfn.XLOOKUP(G98,'Kraken Trades'!$A$2:$A$28,'Kraken Trades'!$A$2:$A$28,"--",0) -> -- | Q98: =_xlfn.XLOOKUP(G98,'Kraken Trades'!$A$2:$A$28,'Kraken Trades'!$B$2:$B$28,"--",0) -> -- | R98: =_xlfn.XLOOKUP(G98,'Kraken Trades'!$A$2:$A$28,'Kraken Trades'!$C$2:$C$28,"--",0) -> -- | S98: =_xlfn.XLOOKUP(G98,'Kraken Trades'!$A$2:$A$28,'Kraken Trades'!$D$2:$D$28,"--",0) -> -- | T98: =_xlfn.XLOOKUP(G98,'Kraken Trades'!$A$2:$A$28,'Kraken Trades'!$E$2:$E$28,"--",0) -> -- | U98: =_xlfn.XLOOKUP(G98,'Kraken Trades'!$A$2:$A$28,'Kraken Trades'!$F$2:$F$28,"--",0) -> -- | V98: =_xlfn.XLOOKUP(G98,'Kraken Trades'!$A$2:$A$28,'Kraken Trades'!$G$2:$G$28,"--",0) -> -- | W98: =_xlfn.XLOOKUP(G98,'Kraken Trades'!$A$2:$A$28,'Kraken Trades'!$H$2:$H$28,"--",0) -> -- | X98: =_xlfn.XLOOKUP(G98,'Kraken Trades'!$A$2:$A$28,'Kraken Trades'!$I$2:$I$28,"--",0) -> -- | Y98: =_xlfn.XLOOKUP(G98,'Kraken Trades'!$A$2:$A$28,'Kraken Trades'!$J$2:$J$28,"--",0) -> -- | Z98: =_xlfn.XLOOKUP(G98,'Kraken Trades'!$A$2:$A$28,'Kraken Trades'!$K$2:$K$28,"--",0) -> -- | AA98: =_xlfn.XLOOKUP(G98,'Kraken Trades'!$A$2:$A$28,'Kraken Trades'!$L$2:$L$28,"--",0) -> -- | AB98: =_xlfn.XLOOKUP(G98,'Kraken Trades'!$A$2:$A$28,'Kraken Trades'!$M$2:$M$28,"--",0) -> --
A99: 45104 | B99: yes | E99: =_xlfn.XLOOKUP(D99,'DEST TAGs'!$A$2:$A$5,'DEST TAGs'!$B$2:$B$5,"--",0) -> -- | F99: LMRL7X-JMOJX-OKACJ4 | G99: T63DO7-M3A2C-PSS3NQ | H99: 45038.353 | I99: trade | K99: currency | L99: ZGBP | M99: -2764.0467 | N99: 0 | O99: 1729.1493 | P99: =_xlfn.XLOOKUP(G99,'Kraken Trades'!$A$2:$A$28,'Kraken Trades'!$A$2:$A$28,"--",0) -> T63DO7-M3A2C-PSS3NQ | Q99: =_xlfn.XLOOKUP(G99,'Kraken Trades'!$A$2:$A$28,'Kraken Trades'!$B$2:$B$28,"--",0) -> O6ZBZU-C2XIF-MQOVIG | R99: =_xlfn.XLOOKUP(G99,'Kraken Trades'!$A$2:$A$28,'Kraken Trades'!$C$2:$C$28,"--",0) -> XRPGBP | S99: =_xlfn.XLOOKUP(G99,'Kraken Trades'!$A$2:$A$28,'Kraken Trades'!$D$2:$D$28,"--",0) -> 0.019630787 | T99: =_xlfn.XLOOKUP(G99,'Kraken Trades'!$A$2:$A$28,'Kraken Trades'!$E$2:$E$28,"--",0) -> buy | U99: =_xlfn.XLOOKUP(G99,'Kraken Trades'!$A$2:$A$28,'Kraken Trades'!$F$2:$F$28,"--",0) -> market | V99: =_xlfn.XLOOKUP(G99,'Kraken Trades'!$A$2:$A$28,'Kraken Trades'!$G$2:$G$28,"--",0) -> 0.36369037 | W99: =_xlfn.XLOOKUP(G99,'Kraken Trades'!$A$2:$A$28,'Kraken Trades'!$H$2:$H$28,"--",0) -> 2764.0468 | X99: =_xlfn.XLOOKUP(G99,'Kraken Trades'!$A$2:$A$28,'Kraken Trades'!$I$2:$I$28,"--",0) -> 7.1865217 | Y99: =_xlfn.XLOOKUP(G99,'Kraken Trades'!$A$2:$A$28,'Kraken Trades'!$J$2:$J$28,"--",0) -> 7600 | Z99: =_xlfn.XLOOKUP(G99,'Kraken Trades'!$A$2:$A$28,'Kraken Trades'!$K$2:$K$28,"--",0) -> 0 | AA99: =_xlfn.XLOOKUP(G99,'Kraken Trades'!$A$2:$A$28,'Kraken Trades'!$L$2:$L$28,"--",0) -> initiated | AB99: =_xlfn.XLOOKUP(G99,'Kraken Trades'!$A$2:$A$28,'Kraken Trades'!$M$2:$M$28,"--",0) -> L6AGHL-WO5W6-S3TVAM,LB4MAJ-LLAHT-NJFAVY,LMRL7X-JMOJX-OKACJ4
A100: 45104 | B100: yes | E100: =_xlfn.XLOOKUP(D100,'DEST TAGs'!$A$2:$A$5,'DEST TAGs'!$B$2:$B$5,"--",0) -> -- | F100: LB4MAJ-LLAHT-NJFAVY | G100: T63DO7-M3A2C-PSS3NQ | H100: 45038.353 | I100: trade | K100: currency | L100: XXRP | M100: 7600 | N100: 0 | O100: 7600.7094 | P100: =_xlfn.XLOOKUP(G100,'Kraken Trades'!$A$2:$A$28,'Kraken Trades'!$A$2:$A$28,"--",0) -> T63DO7-M3A2C-PSS3NQ | Q100: =_xlfn.XLOOKUP(G100,'Kraken Trades'!$A$2:$A$28,'Kraken Trades'!$B$2:$B$28,"--",0) -> O6ZBZU-C2XIF-MQOVIG | R100: =_xlfn.XLOOKUP(G100,'Kraken Trades'!$A$2:$A$28,'Kraken Trades'!$C$2:$C$28,"--",0) -> XRPGBP | S100: =_xlfn.XLOOKUP(G100,'Kraken Trades'!$A$2:$A$28,'Kraken Trades'!$D$2:$D$28,"--",0) -> 0.019630787 | T100: =_xlfn.XLOOKUP(G100,'Kraken Trades'!$A$2:$A$28,'Kraken Trades'!$E$2:$E$28,"--",0) -> buy | U100: =_xlfn.XLOOKUP(G100,'Kraken Trades'!$A$2:$A$28,'Kraken Trades'!$F$2:$F$28,"--",0) -> market | V100: =_xlfn.XLOOKUP(G100,'Kraken Trades'!$A$2:$A$28,'Kraken Trades'!$G$2:$G$28,"--",0) -> 0.36369037 | W100: =_xlfn.XLOOKUP(G100,'Kraken Trades'!$A$2:$A$28,'Kraken Trades'!$H$2:$H$28,"--",0) -> 2764.0468 | X100: =_xlfn.XLOOKUP(G100,'Kraken Trades'!$A$2:$A$28,'Kraken Trades'!$I$2:$I$28,"--",0) -> 7.1865217 | Y100: =_xlfn.XLOOKUP(G100,'Kraken Trades'!$A$2:$A$28,'Kraken Trades'!$J$2:$J$28,"--",0) -> 7600 | Z100: =_xlfn.XLOOKUP(G100,'Kraken Trades'!$A$2:$A$28,'Kraken Trades'!$K$2:$K$28,"--",0) -> 0 | AA100: =_xlfn.XLOOKUP(G100,'Kraken Trades'!$A$2:$A$28,'Kraken Trades'!$L$2:$L$28,"--",0) -> initiated | AB100: =_xlfn.XLOOKUP(G100,'Kraken Trades'!$A$2:$A$28,'Kraken Trades'!$M$2:$M$28,"--",0) -> L6AGHL-WO5W6-S3TVAM,LB4MAJ-LLAHT-NJFAVY,LMRL7X-JMOJX-OKACJ4
...

Sheet Kraken Trades
A1: txid | B1: ordertxid | C1: pair | D1: time | E1: type | F1: ordertype | G1: price | H1: cost | I1: fee | J1: vol | K1: margin | L1: misc | M1: ledgers
A2: TVJHYS-EB5IK-4X5X33 | B2: OX3DXP-OFPAQ-NWPXZK | C2: XRPGBP | D2: 0.027545139 | E2: buy | F2: market | G2: 0.28462991 | H2: 1499.9996 | I2: 3.899999 | J2: 5270 | K2: 0 | L2: initiated | M2: LJHWVK-UM23A-Z4NP7D,LS3HC5-BWXDY-DROKXS,LOC5M4-VGITG-62OW6U
A3: TONPXD-KPDZU-5WAK7C | B3: OA5AQQ-YBGEA-2YGS2M | C3: XRPGBP | D3: 0.0096805556 | E3: buy | F3: market | G3: 0.31800562 | H3: 302.10534 | I3: 0.78547389 | J3: 950 | K3: 0 | L3: initiated | M3: L7GPCS-DXW2B-NSUS3D,LJGS5J-JIVT5-2JPEC4,LAQ6TD-TG2HT-I27ECB
A4: TFUFLH-JICVN-QIRXBC | B4: ON4G3V-EWYBS-PENEAQ | C4: XRPGBP | D4: 0.035511574 | E4: buy | F4: market | G4: 0.31492011 | H4: 850.28431 | I4: 2.2107392 | J4: 2700 | K4: 0 | L4: initiated | M4: L2AZFP-MHOGI-Z6IC76,LQENTR-CXN3S-V2AFUZ,LQ5Y6F-GXLDN-OQIMCY
A5: TS6ESC-QJCTE-7REB62 | B5: OVMH6P-VMU7P-E44AOJ | C5: XRPGBP | D5: 0.0046458333 | E5: buy | F5: market | G5: 0.33092 | H5: 175.3876 | I5: 0.45600776 | J5: 530 | K5: 0 | L5: initiated | M5: L7JNEK-NXJOR-PGHOYD,LKUCJL-B6QP6-HVTZSZ,LNTCL3-MS5IQ-JHFPLF
A6: T2M2QR-PKI5J-Y5JL6X | B6: OZ72GI-QOAPH-LJIKPV | C6: XRPGBP | D6: 0.0331875 | E6: buy | F6: market | G6: 0.30773392 | H6: 675.47596 | I6: 1.7562375 | J6: 2195 | K6: 0 | L6: initiated | M6: LZGQC7-CBHKO-BKBP4U,LWHU3C-IQK4G-3GOKIF,LP4NHA-4C2MD-2TNAQM
A7: TWTDYI-ASIKO-VCFX6I | B7: ORTVJB-TAVRW-O7R7BW | C7: XRPGBP | D7: 0.0086203704 | E7: buy | F7: market | G7: 0.31604 | H7: 235.4498 | I7: 0.61216948 | J7: 745 | K7: 0 | L7: initiated | M7: LRNHWZ-57VHX-HWWRUW,LPEDUI-QCVOM-6NRCON,LQG5LY-EWTI6-RSHFAR
A8: TC3PHC-GCMVA-E6STJY | B8: O3NVLB-QN7EY-FMQ6CE | C8: XRPGBP | D8: 0.010349537 | E8: buy | F8: market | G8: 0.31624 | H8: 215.0432 | I8: 0.55911232 | J8: 680 | K8: 0 | L8: initiated | M8: LVPZY3-Q45Q7-LMRC3C,LWLOFX-MMUGN-TTVA5O,L6CQJL-6WC7R-HFAEGK
A9: TVEO4I-KY7HQ-QBBWUM | B9: OXYUXG-MWUSN-R5UQHK | C9: XRPGBP | D9: 0.029686343 | E9: buy | F9: market | G9: 0.36706496 | H9: 256.94547 | I9: 0.66805822 | J9: 700 | K9: 0 | L9: initiated | M9: L6SMP6-NDAWR-2UIRQZ,LJDYPI-R6LH7-E2EA6H,LKTWBH-PHKLE-CC24C2
A10: TDGV6W-7Q63J-E4QJW6 | B10: O3ZHGF-QQMXC-EVF2YX | C10: XRPGBP | D10: 0.002775463 | E10: buy | F10: market | G10: 0.36426906 | H10: 1327.7607 | I10: 3.4521778 | J10: 3645 | K10: 0 | L10: initiated | M10: L6W2JN-Z6XBJ-36ZUNE,LU2EIK-LAETH-JD4F56,LBOVA7-4FOSU-VDWKFU
A11: T2SYNS-QPPLR-RWCR6N | B11: OKJB6I-BNMCX-D6SSRD | C11: XRPGBP | D11: 0.002130787 | E11: buy | F11: market | G11: 0.41528174 | H11: 1536.5424 | I11: 3.9950103 | J11: 3700 | K11: 0 | L11: initiated | M11: LR74IH-UWJYR-KCPT4I,LZCKOU-6WH7Y-OAOCFE,LCCMR6-CUGBS-OVGXI6
A12: TYKAIB-CIGAO-B5OBU6 | B12: OY7NWP-OJ4KS-EHEOGI | C12: XRPGBP | D12: 0.013769676 | E12: buy | F12: market | G12: 0.40534709 | H12: 800.56051 | I12: 2.0814573 | J12: 1975 | K12: 0 | L12: initiated | M12: LIGGLP-ATT37-DVOVHS,LXNJSC-GVZ6M-MTAFRA,L4UFCK-RHGHP-4I25WP
A13: TABUT2-6TCYQ-U2OQ3G | B13: OJFZRV-MR4H3-OT5OQC | C13: XRPGBP | D13: 0.02658912 | E13: buy | F13: market | G13: 0.42067 | H13: 98.85745 | I13: 0.25702937 | J13: 235 | K13: 0 | L13: initiated | M13: LSRT4P-ZF56G-DOKHCB,LET3FK-M2Y2E-OFAZFN,LWSASC-3X4CP-OD5E5A
... A28: TWKZY3-4OKNO-MWV523 | B28: O6MF5N-KP7DR-EH74Y2 | C28: XRPGBP | D28: 0.01891088 | E28: buy | F28: market | G28: 0.38812839 | H28: 310.58033 | I28: 0.80750887 | J28: 800.2 | K28: 0 | L28: initiated | M28: LQGCOP-MDJCB-5FVDPW,LBTWTL-SDRTI-CCBGAN,LOUUK5-XAOKU-VYIOQN
K179: =XLOOKUP(B179,

Sheet DEST TAGs
A1: DEST TAG | B1: WHO
A2: 518294827 | B2: Alex Smirnov
A3: 547786843 | B3: Aleksey Trofimov
A4: 442734179 | B4: Evgeniy Ulyukin
A5: 373650723 | B5: Ivan Maltsev
